Workbook

Sheet Base de Dados FORMS
A1: Carimbo de data/hora | B1: 1) Este é um lugar (ambiente físico) agradável para trabalhar. | C1: 1) Gostaria de deixar um comentário sobre? | D1: 2) Eu recebo os equipamentos e recursos necessários para realizar o meu trabalho. | E1: 2) Gostaria de deixar um comentário sobre? | F1: 3) As pessoas aqui estão dispostas a fazer um pouco além da sua obrigação para concluir um trabalho. | G1: 3) Gostaria de deixar um comentário sobre? | H1: 4) Pode-se contar com a colaboração das pessoas por aqui. | I1: 4) Gostaria de deixar um comentário sobre? | J1: 5) A empresa oferece treinamentos ou oportunidades de desenvolvimento para o meu crescimento profissional. | K1: 5) Gostaria de deixar um comentário sobre? | L1: 6) Você tem uma visão clara de para onde estamos indo (futuro da empresa) e como fazer para chegar lá. | M1: 6) Gostaria de deixar um comentário sobre? | N1: 7) A empresa demonstra reconhecimento pelo bom trabalho e pelo esforço extra. | O1: 7) Gostaria de deixar um comentário sobre? | P1: 8) As pessoas aqui nesta empresa são remuneradas adequadamente em relação a outras empresas do mesmo segmento de mercado. | Q1: 8) Gostaria de deixar um comentário sobre? | R1: 9) Meu trabalho tem um sentido especial. Para mim, não é só “mais um emprego”. | S1: 9) Gostaria de deixar um comentário sobre? | T1: 10) Quando é contratado um funcionário novo, as pessoas fazem com que ele se sinta bem-vindo. | U1: 10) Gostaria de deixar um comentário sobre? | V1: 11) Tenho orgulho de contar com as pessoas que trabalho aqui. | W1: 11) Gostaria de deixar um comentário sobre? | X1: 12) As pessoas aqui têm vontade de vir para o trabalho. | Y1: 12) Gostaria de deixar um comentário sobre? | Z1: 13) Eu me sinto à vontade na empresa, sem precisar fingir que sou outra pessoa. | AA1: 13) Gostaria de deixar um comentário sobre? | AB1: 14) Existem canais de comunicação bem definidos para que os colaboradores possam expressar suas sugestões e reivindicações. | AC1: 14) Gostaria de deixar um comentário sobre? | AD1: 15) Você acredita que a empresa só promoveria uma demissão em massa como último recurso. | AE1: 15) Gostaria de deixar um comentário sobre? | AF1: 16) As pessoas são encorajadas a equilibrar sua vida profissional e pessoal. | AG1: 16) Gostaria de deixar um comentário sobre? | AH1: 17) Você sabe com clareza quem é seu líder (superior imediato). | AI1: 17) Gostaria de deixar um comentário sobre? | AJ1: 18) O seu líder (superior imediato) deixa claro o que ele espera do seu trabalho. | AK1: 18) Gostaria de deixar um comentário sobre? | AL1: 19) O seu líder demonstra comprometimento com o negócio da empresa (interesse no crescimento da empresa). | AM1: 19) Gostaria de deixar um comentário sobre? | AN1: 20) O seu líder é honesto e ético na condução dos negócios. | AO1: 20) Gostaria de deixar um comentário sobre? | AP1: 21) O seu líder demonstra interesse sincero por você como pessoa e não somente como empregado. | AQ1: 21) Gostaria de deixar um comentário sobre? | AR1: 22) É fácil se aproximar do seu líder e é também fácil de falar com ele. | AS1: 22) Gostaria de deixar um comentário sobre? | AT1: 23) O seu líder treina as pessoas com o foco nas suas necessidades. | AU1: 23) Gostaria de deixar um comentário sobre? | AV1: 24) O seu líder reconhece os erros como oportunidades de aprendizado. | AW1: 24) Gostaria de deixar um comentário sobre? | AX1: 25) O seu líder demonstra interesse nas ideias e sugestões que você e seus companheiros apresentam e toma ações com base nelas. | AY1: 25) Gostaria de deixar um comentário sobre? | AZ1: 26) O seu líder lhe mantém informado sobre assuntos importantes e sobre mudanças na empresa. | BA1: 26) Gostaria de deixar um comentário sobre? | BB1: 27) O seu líder tem uma visão clara de para onde estamos indo (futuro da empresa) e o que fazer para chegar lá. | BC1: 27) Gostaria de deixar um comentário sobre? | BD1: 28) O seu líder confia no bom trabalho das pessoas sem precisar vigiá-las. | BE1: 28) Gostaria de deixar um comentário sobre? | BF1: 29) O seu líder envolve as pessoas em decisões que afetam atividades e seu ambiente de trabalho. | BG1: 29) Gostaria de deixar um comentário sobre? | BH1: 30) O seu líder trata todos da mesma forma, sem proteger ninguém. | BI1: 30) Gostaria de deixar um comentário sobre? | BJ1: 31) O seu líder sabe coordenar pessoas e distribuir tarefas adequadamente. | BK1: 31) Gostaria de deixar um comentário sobre? | BL1: 32) O seu líder dá autonomia às pessoas. | BM1: 32) Gostaria de deixar um comentário sobre? | BN1: 33) O seu líder age de acordo com o que fala. | BO1: 33) Gostaria de deixar um comentário sobre? | BP1: 34) O seu líder dá feedback (crítica construtiva) sobre o desempenho de seu trabalho. | BQ1: 34) Gostaria de deixar um comentário sobre? | BR1: 35) As pessoas aqui na empresa são bem tratadas independentemente da sua idade, cor, religião ou sexo. | BS1: 35) Gostaria de deixar um comentário sobre? | BT1: 36) Você alguma vez já foi humilhado pelo seu líder ou presenciou alguma humilhação. | BU1: 36) Gostaria de deixar um comentário sobre? | BV1: 37) Aqui as pessoas se importam umas com as outras. | BW1: 37) Gostaria de deixar um comentário sobre? | BX1: 38) Existe um sentimento de equipe por aqui. | BY1: 38) Gostaria de deixar um comentário sobre? | BZ1: 39) Nós sempre comemoramos as metas atingidas e os eventos especiais. | CA1: 39) Gostaria de deixar um comentário sobre? | CB1: 40) As pessoas fazem “politicagem” (puxa saco) como forma de obter resultados. | CC1: 40) Gostaria de deixar um comentário sobre? | CD1: 41) A Diretoria da empresa é aberta a sugestões e é fácil falar com ela. | CE1: 41) Gostaria de deixar um comentário sobre? | CF1: 42) Você tem um bom relacionamento com a Diretoria da empresa. | CG1: 42) Gostaria de deixar um comentário sobre? | CH1: 43) Eu sou bem tratado, independente de minha função na empresa. | CI1: 43) Gostaria de deixar um comentário sobre? | CJ1: 44) Sinto que sou valorizado aqui e que posso fazer a diferença. | CK1: 44) Gostaria de deixar um comentário sobre? | CL1: 45) Este é um lugar agradável para se trabalhar. | CM1: 45) Gostaria de deixar um comentário sobre? | CN1: 46) Existe fofoca por aqui. | CO1: 46) Gostaria de deixar um comentário sobre? | CP1: 47) Percebo um clima de rivalidade (competição interna) aqui. | CQ1: 47) Gostaria de deixar um comentário sobre? | CR1: 48) Pretendo trabalhar aqui ainda por muito tempo. | CS1: 48) Gostaria de deixar um comentário sobre? | CT1: 49) Existe um bom relacionamento entre as áreas da empresa (equipes das diferentes expertises de conhecimento). | CU1: 49) Gostaria de deixar um comentário sobre? | CV1: 50) Levando-se tudo em conta, eu diria que este é um excelente lugar para trabalhar. | CW1: 50) Gostaria de deixar um comentário sobre? | CX1: 51) Marque os TRÊS (03) benefícios que você julga mais importantes , independente se a empresa oferece ou não. | CY1: 51) Gostaria de deixar um comentário sobre? | CZ1: 52) Cite 3 (três) PONTOS FORTES DA EMPRESA (o que já é bom na empresa). | DA1: 53) Cite 3 (três) PONTOSDE MELHORIA DA EMPRESA (o que ainda precisa ser mudado na empresa). | DB1: 54) Este espaço é seu, use-o para registrar comentários e sugestões não abordados anteriormente.
A2: 45687.339 | B2: Concordo Sempre | D2: Concordo | F2: Concordo Sempre | H2: Concordo | J2: Concordo | L2: Concordo Sempre | N2: Concordo | P2: Discordo | Q2: Eu acho q poderíamos melhorar o salário pq hoje ao nosso redor tudo está muito acima do preço e a dificuldade aumenta,Em relação aos benefícios, acho q poderíamos melhorar o vale alimentação, pq hoje em dia um almoço custa em torno de 21$ , poderíamos melhorar também em questão de vale academia | R2: Concordo | S2: Procuro crescer e acrescentar profissionalismo dentro da família nordeste | T2: Concordo | V2: Concordo | X2: Concordo | Z2: Concordo | AB2: Concordo Sempre | AC2: Nosso supervisor nos dá a liberdade de expressar ideias e opiniões para a melhora do dia a dia | AD2: Discordo | AE2: Acho q a empresa deve tomar a decisão de demissão a partir do momento q a pessoa não se dispõe a cumprir seu dever como ctl | AF2: Concordo Sempre | AH2: Concordo Sempre | AI2: Sim, um cara mente aberta e muito parceiro de serviço de todas as horas | AJ2: Concordo Sempre | AK2: Não só deixa claro, como ajuda a melhorar todos os dias | AL2: Concordo Sempre | AM2: Visão plena em relação ao crescimento da família nordeste | AN2: Concordo Sempre | AP2: Concordo Sempre | AQ2: Sim, a ajuda é diária como pessoa e profissional | AR2: Concordo Sempre | AT2: Concordo | AV2: Concordo | AX2: Concordo | AZ2: Concordo | BB2: Concordo Sempre | BD2: Concordo | BF2: Concordo Sempre | BH2: Concordo | BJ2: Concordo Sempre | BL2: Concordo | BN2: Concordo Sempre | BP2: Concordo Sempre | BR2: Concordo Sempre | BT2: Concordo Sempre | BV2: Concordo Sempre | BX2: Concordo Sempre | BZ2: Concordo Sempre | CB2: Concordo | CD2: Concordo | CF2: Discordo | CG2: Ainda não conheci ainda a diretoria | CH2: Concordo | CJ2: Concordo | CL2: Concordo | CN2: Concordo | CP2: Concordo | CR2: Concordo | CT2: Concordo | CV2: Concordo | CW2: Lugar excelente pra trabalhar | CX2: Assistência Médica, Auxílio Combustível, Vale Alimentação, Empréstimo Consignado, Gympass (Convênio Academias) | CY2: Melhorais benefícios | CZ2: união, metodologia de trabalho, incentivo, | DA2: salário, vale alimentação, melhoria de benefícios.. | DB2: O vale academia ajudaria muito as pessoas q gostam de fazer Sport e incentiva a vida pessoal
A3: 45687.339 | B3: Concordo Sempre | C3: . | D3: Concordo Sempre | E3: . | F3: Concordo | G3: . | H3: Discordo | I3: De alguns,não de todos | J3: Concordo | K3: . | L3: Concordo Sempre | M3: . | N3: Concordo Sempre | O3: . | P3: Concordo Sempre | Q3: Sim | R3: Concordo Sempre | S3: Sim | T3: Concordo Sempre | U3: Sim | V3: Concordo Sempre | W3: Sim | X3: Discordo | Y3: Não todos | Z3: Concordo Sempre | AA3: Sim | AB3: Concordo Sempre | AC3: Sim | AD3: Concordo Sempre | AE3: Sim | AF3: Concordo | AG3: Sim | AH3: Concordo Sempre | AI3: Sim | AJ3: Concordo Sempre | AK3: Sim | AL3: Concordo Sempre | AM3: Sim | AN3: Concordo Sempre | AO3: Sim | AP3: Concordo Sempre | AQ3: Sim | AR3: Concordo Sempre | AS3: Muito acessível | AT3: Concordo Sempre | AU3: Sim | AV3: Concordo Sempre | AW3: Sim | AX3: Concordo Sempre | AY3: Sim | AZ3: Concordo Sempre | BA3: Sim | BB3: Concordo Sempre | BC3: Sim | BD3: Concordo Sempre | BE3: Sim | BF3: Discordo | BG3: Não | BH3: Concordo Sempre | BI3: Sim | BJ3: Concordo Sempre | BK3: Sim | BL3: Concordo | BM3: Na medida do possível | BN3: Concordo Sempre | BO3: Sim | BP3: Concordo Sempre | BQ3: Sim | BR3: Concordo Sempre | BS3: Sim | BT3: Discordo Sempre | BU3: Nunca | BV3: Concordo Sempre | BW3: Sim | BX3: Concordo Sempre | BY3: Sim | BZ3: Concordo Sempre | CA3: Sim | CB3: Discordo | CC3: Não | CD3: Concordo Sempre | CE3: Sim | CF3: Concordo Sempre | CG3: Sim | CH3: Concordo Sempre | CI3: Sim | CJ3: Concordo Sempre | CK3: Sim | CL3: Concordo Sempre | CM3: Sim | CN3: Concordo | CO3: Existe muitos fofoca por aqui | CP3: Discordo | CQ3: Não | CR3: Concordo Sempre | CS3: Sim | CT3: Concordo | CU3: Sim | CV3: Concordo Sempre | CW3: Sim sem dúvidas | CX3: Auxílio Combustível, Refeição na Empresa, Vale Refeição, Vale Alimentação, Cesta Básica | CY3: . | CZ3: Como eu sou tratado,pagamentos sem nem um dia de atraso e o convívio com todos. | DA3: Pra mim está indo tudo bem,não tem nada a melhorar no meu ver | DB3: Sucesso Nordeste!!!
A4: 45687.34 | B4: Concordo Sempre | C4: . | D4: Concordo Sempre | E4: . | F4: Concordo | G4: . | H4: Discordo | I4: De alguns,não de todos | J4: Concordo | K4: . | L4: Concordo Sempre | M4: . | N4: Concordo Sempre | O4: . | P4: Concordo Sempre | Q4: Sim | R4: Concordo Sempre | S4: Sim | T4: Concordo Sempre | U4: Sim | V4: Concordo Sempre | W4: Sim | X4: Discordo | Y4: Não todos | Z4: Concordo Sempre | AA4: Sim | AB4: Concordo Sempre | AC4: Sim | AD4: Concordo Sempre | AE4: Sim | AF4: Concordo | AG4: Sim | AH4: Concordo Sempre | AI4: Sim | AJ4: Concordo Sempre | AK4: Sim | AL4: Concordo Sempre | AM4: Sim | AN4: Concordo Sempre | AO4: Sim | AP4: Concordo Sempre | AQ4: Sim | AR4: Concordo Sempre | AS4: Muito acessível | AT4: Concordo Sempre | AU4: Sim | AV4: Concordo Sempre | AW4: Sim | AX4: Concordo Sempre | AY4: Sim | AZ4: Concordo Sempre | BA4: Sim | BB4: Concordo Sempre | BC4: Sim | BD4: Concordo Sempre | BE4: Sim | BF4: Discordo | BG4: Não | BH4: Concordo Sempre | BI4: Sim | BJ4: Concordo Sempre | BK4: Sim | BL4: Concordo | BM4: Na medida do possível | BN4: Concordo Sempre | BO4: Sim | BP4: Concordo Sempre | BQ4: Sim | BR4: Concordo Sempre | BS4: Sim | BT4: Discordo Sempre | BU4: Nunca | BV4: Concordo Sempre | BW4: Sim | BX4: Concordo Sempre | BY4: Sim | BZ4: Concordo Sempre | CA4: Sim | CB4: Discordo | CC4: Não | CD4: Concordo Sempre | CE4: Sim | CF4: Concordo Sempre | CG4: Sim | CH4: Concordo Sempre | CI4: Sim | CJ4: Concordo Sempre | CK4: Sim | CL4: Concordo Sempre | CM4: Sim | CN4: Concordo | CO4: Existe muitos fofoca por aqui | CP4: Discordo | CQ4: Não | CR4: Concordo Sempre | CS4: Sim | CT4: Concordo | CU4: Sim | CV4: Concordo Sempre | CW4: Sim sem dúvidas | CX4: Auxílio Combustível, Refeição na Empresa, Vale Refeição, Vale Alimentação, Cesta Básica | CY4: . | CZ4: Como eu sou tratado,pagamentos sem nem um dia de atraso e o convívio com todos. | DA4: Pra mim está indo tudo bem,não tem nada a melhorar no meu ver | DB4: Sucesso Nordeste!!!
A5: 45687.347 | B5: Concordo Sempre | C5: Me sinto muito bem trabalhando na Nordeste, aqui tem pessoas maravilhosas. | D5: Concordo | E5: . | F5: Concordo | G5: . | H5: Concordo | I5: . | J5: Discordo | K5: Já foi prometido alguns cursos para nosso desenvolvimento profissional, mas até o momento ainda não tivemos nenhum retorno sobre. | L5: Concordo Sempre | M5: . | N5: Concordo | O5: . | P5: Concordo | Q5: . | R5: Concordo Sempre | S5: Amo o que eu faço | T5: Concordo Sempre | U5: Aqui acolhemos todo mundo bem | V5: Concordo | W5: . | X5: Concordo | Y5: . | Z5: Concordo Sempre | AA5: . | AB5: Concordo | AC5: . | AD5: Concordo | AE5: . | AF5: Concordo | AG5: . | AH5: Concordo | AI5: . | AJ5: Concordo | AK5: . | AL5: Concordo | AM5: . | AN5: Concordo | AO5: . | AP5: Concordo | AQ5: . | AR5: Concordo Sempre | AS5: . | AT5: Concordo | AV5: Concordo | AX5: Concordo | AZ5: Concordo | BB5: Concordo | BD5: Concordo Sempre | BF5: Discordo | BG5: Não, não acontece | BH5: Concordo | BJ5: Concordo | BL5: Concordo | BN5: Concordo | BP5: Concordo | BR5: Concordo Sempre | BT5: Discordo Sempre | BU5: Nunca aconteceu nada desse tipo na empresa. | BV5: Concordo | BX5: Concordo | BZ5: Concordo Sempre | CB5: Concordo | CD5: Concordo | CF5: Concordo Sempre | CH5: Concordo | CJ5: Discordo | CK5: Me sinto desvalorizado pelas pessoas que trabalham aqui e não pela empresa. | CL5: Concordo | CN5: Concordo | CP5: Discordo | CQ5: Não temos rivalidade.. assim eu penso | CR5: Concordo | CT5: Concordo | CV5: Concordo | CW5: . | CX5: Assistência Médica, Auxílio Combustível, Multibenefícios Alimentação/ Refeição, Cesta Básica, Day Off | CY5: 1 | CZ5: Benefícios, salários em dia, somos livres para trabalhar. | DA5: Oportunidades de crescimento, reconhecer o esforço, escutar mais os colaboradores. | DB5: .
A6: 45687.347 | B6: Concordo | C6: . | D6: Concordo | E6: . | F6: Concordo | G6: . | H6: Concordo | I6: . | J6: Concordo | K6: . | L6: Concordo | M6: . | N6: Concordo | O6: . | P6: Concordo | Q6: . | R6: Concordo Sempre | S6: . | T6: Concordo Sempre | U6: . | V6: Concordo | W6: . | X6: Concordo | Y6: . | Z6: Concordo Sempre | AA6: . | AB6: Concordo | AC6: . | AD6: Concordo | AE6: . | AF6: Concordo | AG6: . | AH6: Concordo | AI6: . | AJ6: Concordo | AK6: . | AL6: Concordo Sempre | AM6: . | AN6: Concordo Sempre | AO6: . | AP6: Concordo Sempre | AQ6: . | AR6: Concordo Sempre | AS6: . | AT6: Concordo Sempre | AU6: . | AV6: Concordo | AW6: . | AX6: Concordo Sempre | AY6: . | AZ6: Concordo Sempre | BA6: . | BB6: Concordo Sempre | BC6: . | BD6: Concordo | BE6: . | BF6: Concordo Sempre | BG6: . | BH6: Concordo | BI6: . | BJ6: Concordo | BK6: . | BL6: Concordo | BM6: . | BN6: Concordo Sempre | BO6: . | BP6: Concordo Sempre | BQ6: . | BR6: Concordo Sempre | BS6: . | BT6: Discordo Sempre | BU6: Nunca. | BV6: Concordo | BW6: . | BX6: Concordo | BY6: . | BZ6: Concordo Sempre | CA6: . | CB6: Discordo | CC6: Não. | CD6: Concordo Sempre | CE6: . | CF6: Concordo Sempre | CG6: . | CH6: Concordo Sempre | CI6: . | CJ6: Concordo Sempre | CK6: . | CL6: Concordo Sempre | CM6: . | CN6: Discordo | CO6: Não no meu setor. | CP6: Concordo | CQ6: Em alguma situações. | CR6: Concordo Sempre | CS6: . | CT6: Concordo | CU6: . | CV6: Concordo Sempre | CW6: . | CX6: Assistência Médica, Assistência Odontológica, Auxílio Combustível, Vale Refeição, Vale Alimentação | CY6: . | CZ6: Agilidade,processos,convivência. | DA6: Sala comercial,área de descanso, variar mix de equipamentos. | DB6: humberto.aragao@nordesteloc.com.br
A7: 45687.348 | B7: Concordo | D7: Concordo | F7: Discordo Sempre | G7: Não vejo ninguém faz oq eu fasso além da minha obrigação | H7: Discordo | J7: Discordo Sempre | K7: Nunca tiver oportunidade aqui | L7: Concordo | N7: Discordo Sempre | O7: Pra mim não | P7: Concordo | R7: Concordo Sempre | T7: Discordo | U7: No começo sim mais depois não | V7: Discordo Sempre | X7: Concordo | Y7: Eu sim mais não sei as outras pessoas | Z7: Concordo Sempre | AB7: Discordo | AD7: Concordo | AF7: Concordo | AH7: Discordo | AJ7: Discordo | AL7: Discordo | AN7: Concordo | AP7: Discordo Sempre | AR7: Concordo Sempre | AT7: Discordo Sempre | AV7: Discordo | AX7: Discordo Sempre | AZ7: Concordo Sempre | BB7: Concordo Sempre | BD7: Discordo Sempre | BF7: Discordo Sempre | BH7: Discordo Sempre | BJ7: Discordo | BL7: Concordo | BN7: Discordo Sempre | BP7: Concordo | BR7: Concordo Sempre | BT7: Discordo Sempre | BU7: Sim muitos vezes | BV7: Discordo | BX7: Discordo Sempre | BZ7: Concordo Sempre | CB7: Discordo | CD7: Concordo Sempre | CF7: Concordo Sempre | CH7: Discordo Sempre | CI7: Minha função aqui e desvalorizada não pela empresa mais sim pela equipe de trabalho | CJ7: Discordo Sempre | CL7: Concordo Sempre | CN7: Discordo Sempre | CO7: Aqui só que tem e fofoca | CP7: Concordo | CR7: Concordo Sempre | CT7: Concordo | CV7: Concordo Sempre | CW7: Lugar e bom pra trabalhar mais as pessoas não | CX7: Assistência Médica, Assistência Odontológica, Vale Alimentação, Cesta Básica, Seguro de Vida | CY7: Os benefícios são bom mais queira outro | CZ7: Sem resposta | DA7: Não sei oq fala | DB7: Sem resposta
A8: 45687.349 | B8: Concordo Sempre | C8: . | D8: Concordo Sempre | E8: . | F8: Discordo Sempre | G8: Por mais que seja uma equipe pequena, infelizmente a maioria é dotado de uma política individualista, gerando muitas vezes inclusive conflitos e fugindo das responsabilidades de suas próprias funções | H8: Concordo | I8: . | J8: Concordo | K8: Sei que temos por obrigação apostar em nosso próprio conhecimento, através cursos por exemplo, mas seria interessante a empresa oferecer algo “fora da caixa”. Exemplo: um curso pago de alto nível em técnica de vendas para o setor comercial. | L8: Concordo Sempre | M8: . | N8: Concordo Sempre | O8: Uma das políticas da empresa de maior prestígio sem dúvida alguma é o reconhecimento! | P8: Concordo Sempre | Q8: . | R8: Concordo Sempre | S8: Tenho por natureza entregar excelência e dedicação em tudo que faço. | T8: Concordo | U8: . | V8: Discordo | W8: Nem todos são amigavelmente saudáveis | X8: Discordo | Y8: Tem pessoas que demonstram nitidamente não só pela aparência ao chegar na empresa, quanto pelas próprias palavras, a sua insatisfação | Z8: Concordo Sempre | AA8: . | AB8: Concordo Sempre | AC8: . | AD8: Concordo | AE8: . | AF8: Concordo Sempre | AG8: . | AH8: Concordo Sempre | AI8: . | AJ8: Concordo Sempre | AK8: . | AL8: Concordo Sempre | AM8: . | AN8: Concordo Sempre | AO8: . | AP8: Concordo Sempre | AQ8: Não só a mim como a todos. Sempre solicito, disposto a ajudar. Amigo de todos (até mesmo dos que não merecem) | AR8: Concordo Sempre | AS8: . | AT8: Concordo Sempre | AU8: . | AV8: Concordo | AW8: . | AX8: Concordo | AY8: . | AZ8: Concordo Sempre | BA8: . | BB8: Concordo Sempre | BC8: . | BD8: Concordo Sempre | BE8: Confia até demais. Poderia ser um pouco mais de malícia, pessoas erram e fazem coisas erradas quase que o tempo inteiro | BF8: Concordo Sempre | BG8: Sempre democrático | BH8: Concordo | BI8: . | BJ8: Concordo | BK8: . | BL8: Concordo | BM8: . | BN8: Concordo | BO8: . | BP8: Concordo Sempre | BQ8: . | BR8: Concordo Sempre | BS8: Empresa inclusiva em todos os campos | BT8: Discordo Sempre | BU8: Jamais presenciei | BV8: Discordo Sempre | BW8: A maioria das pessoas quando não podem ajudar, tentam prejudicar o colega | BX8: Discordo | BY8: Infelizmente por diversas vezes o individualismo prevalece | BZ8: Concordo Sempre | CA8: . | CB8: Discordo Sempre | CC8: Nunca presenciei | CD8: Concordo Sempre | CE8: Diretores sem acessíveis e dispostos a ouvirem | CF8: Concordo Sempre | CG8: . | CH8: Concordo Sempre | CI8: . | CJ8: Concordo | CK8: . | CL8: Concordo | CM8: . | CN8: Discordo Sempre | CO8: A fofoca na empresa Chega a ser cultural. | CP8: Concordo Sempre | CQ8: . | CR8: Discordo | CS8: No momento não consigo enxergar oportunidades além devido ao nosso próprio mercado (escasso infelizmente), e busco sempre crescimento na área profissional, não a tôa que me capacito constantemente para isso. | CT8: Concordo | CU8: . | CV8: Concordo | CW8: . | CX8: Assistência Médica, Assistência Odontológica, Auxílio Combustível, Multibenefícios Alimentação/ Refeição, Empréstimo Consignado | CY8: . | CZ8: Transparência, pontualidade salarial e inclusão. | DA8: Vale alimentação defasado, banco de horas individual (como sugestão) | DB8: Sugestão/solicitação que já foi realizada anteriormente porém não acatada: banheiros exclusivos individuais para homens e mulheres
A9: 45687.349 | B9: Concordo Sempre | C9: Ambiente Agradável | D9: Concordo | E9: Recebo. | F9: Discordo | G9: Alguns não., falta um pouco mais de comprimento de algumas pessoas para ajuda o próximo e para seu próprio crescimento. | H9: Concordo | I9: Porém, nem sempre. | J9: Discordo | K9: Em Relação a treinamentos poderíamos te um pouco mais, fazer parceiras com entidades de cursos profissionalizante. | L9: Concordo | M9: Crescimento gigantesco. | N9: Concordo | O9: As vezes. | P9: Concordo | Q9: Acredito que sim. | R9: Concordo Sempre | S9: Amo o que faço. | T9: Concordo Sempre | U9: Sim, com certeza | V9: Concordo | W9: Turma boa | X9: Concordo | Y9: Acredito que sim. | Z9: Concordo Sempre | AA9: Empresa leve, me sinto muito a vontade. | AB9: Concordo | AC9: As vezes. | AD9: Concordo Sempre | AE9: Espero que nunca aconteça | AF9: Concordo | AG9: Sim, porém depende de cada um | AH9: Concordo Sempre | AI9: Sim | AJ9: Concordo | AK9: Sim | AL9: Concordo | AM9: Sim | AN9: Concordo Sempre | AO9: Sim | AP9: Concordo Sempre | AQ9: Sim, se damos super bem | AR9: Concordo Sempre | AS9: Certeza | AT9: Concordo Sempre | AU9: Demais. | AV9: Concordo | AW9: Sim | AX9: Concordo | AY9: Sim | AZ9: Concordo Sempre | BA9: Sim | BB9: Concordo | BC9: Sim | BD9: Concordo Sempre | BE9: Sim | BF9: Concordo Sempre | BG9: Sim | BH9: Discordo | BI9: Não | BJ9: Discordo | BK9: Deixa a desejar um pouco na cobrança das atividades diárias. | BL9: Concordo Sempre | BM9: Demais. | BN9: Concordo | BO9: Sim | BP9: Concordo | BQ9: Sim sim | BR9: Concordo Sempre | BS9: Certeza | BT9: Discordo Sempre | BU9: Nunca | BV9: Concordo | BW9: Sim | BX9: Concordo | BY9: Sim | BZ9: Concordo Sempre | CA9: Sim | CB9: Discordo | CC9: Não | CD9: Concordo | CE9: Sim | CF9: Concordo Sempre | CG9: Muito. | CH9: Concordo Sempre | CI9: Sim | CJ9: Concordo | CK9: Sim | CL9: Concordo Sempre | CM9: Muito agradável | CN9: Concordo | CO9: As vezes | CP9: Concordo | CQ9: As vezes | CR9: Concordo Sempre | CS9: Sim | CT9: Concordo | CU9: Sim | CV9: Concordo Sempre | CW9: Ótimo | CX9: Assistência Médica, Assistência Odontológica, Auxílio Combustível, Vale Refeição, Auxílio Educação | CY9: Bons auxílios | CZ9: Empresa ótima de trabalho. Ambiente Agradável Fazemos o que e certo | DA9: Oportunidade de cursos Promoções | DB9: Tudo tranquilo.
A10: 45687.349 | B10: Concordo Sempre | D10: Concordo | E10: Mas poderia melhorar um pouco mas nós epis | F10: Concordo | H10: Concordo Sempre | J10: Concordo | L10: Concordo | N10: Discordo | O10: Acho q deveria ganhar um pouco mas na extra | P10: Concordo | R10: Concordo | S10: Ela saber reconhecer o trabalhador | T10: Concordo | V10: Concordo | X10: Discordo | Y10: Tem umas q vem arrastado | Z10: Concordo Sempre | AB10: Discordo | AD10: Concordo | AF10: Concordo Sempre | AH10: Concordo Sempre | AJ10: Concordo | AL10: Concordo Sempre | AM10: Sempre ajuda na evolução da empresa | AN10: Concordo Sempre | AP10: Concordo Sempre | AQ10: Sempre tenta ajudar os colaboradores da empresa | AR10: Concordo Sempre | AS10: Uma pessoa ótima | AT10: Concordo | AV10: Concordo | AX10: Concordo | AZ10: Concordo Sempre | BB10: Concordo | BD10: Concordo | BF10: Discordo | BH10: Concordo Sempre | BJ10: Concordo | BL10: Concordo | BN10: Concordo | BP10: Concordo Sempre | BR10: Concordo Sempre | BS10: Todos são tratados. Da msm forma | BT10: Discordo Sempre | BV10: Concordo | BW10: A maioria sim | BX10: Concordo | BZ10: Concordo Sempre | CB10: Concordo | CC10: Sempre tem uma pessoa q puxa o saco . | CD10: Discordo | CF10: Discordo | CH10: Concordo Sempre | CJ10: Concordo Sempre | CL10: Concordo | CN10: Concordo | CO10: Tem 2 q gosta de uma fofoca | CP10: Discordo | CR10: Concordo Sempre | CT10: Concordo | CV10: Concordo | CW10: Tudo mundo ajuda | CX10: Auxílio Combustível, Multibenefícios Alimentação/ Refeição, Auxílio Educação, Cesta Básica, Empréstimo Consignado | CY10: Seria muito bom nesses auxílio pra nós colaboradores | CZ10: Prestativa, oportunidade, evolução, | DA10: Salaria, ajuda de custo de combustível, auxílio alimentação | DB10: Muito obrigado pela oportunidade..mas ajude a melhorar nas nossas respostas
A11: 45687.35 | B11: Concordo | D11: Discordo | E11: A quantidade de fardamento é insuficiente, mecânicos e externo principalmente que suam mais e precisam lavar as fadas mais vezes em pouco tempo elas ficam desquitaras, velhas e com uma aparência ruim | F11: Discordo | G11: Existe sim pessoas que vc ver fazendo o além dando seu melhor mas tem algumas pessoas que fazem apenas o que é solicitado em seu cargo | H11: Concordo | J11: Discordo | K11: Cabe melhorias em relação a treinamentos, vejo que as pessoas que estão entrando por exemplo não tem treinamento nem sobre os equipamentos nem sobre os processos da empresa. | L11: Concordo | N11: Concordo | P11: Discordo Sempre | Q11: Em relação a remuneração vejo que as outras empresas no mercado pagam melhor, tanto fixo que chega ser uma diferença de 500,00 a menos distante , outro ponto seria a melhoria no valor da alimentação pois atualmente conseguimos até comprar a refeição mais algo pra beber e acompanhar não . Uma melhoria poderia ter um benefício de auxílio a academia outras empresas no mesmo segmento no mercado possui e é ideal para incentivar o funcionário a cuidar da saúde. | R11: Concordo Sempre | T11: Concordo | V11: Concordo | X11: Concordo | Z11: Concordo Sempre | AB11: Discordo | AC11: Cabe melhoria uma sugestão era ter um contato ouvidoria para que os funcionário pudessem expressar suas reivindicação, ideias e pedidos de ajuda. | AD11: Concordo | AF11: Concordo | AH11: Concordo Sempre | AJ11: Concordo Sempre | AL11: Concordo Sempre | AN11: Concordo Sempre | AP11: Concordo Sempre | AR11: Concordo | AT11: Discordo | AU11: Meu líder creio que não tem suporte para treinar quem vem chegando na empresa de colaborador novo e nem atualizações . | AV11: Concordo | AX11: Concordo | AZ11: Concordo | BB11: Concordo Sempre | BD11: Concordo | BF11: Concordo | BH11: Concordo | BJ11: Concordo | BL11: Concordo | BN11: Concordo | BP11: Concordo | BQ11: Meu líder está sempre chamando os funcionários para feedbook | BR11: Concordo Sempre | BT11: Discordo Sempre | BU11: Nunca vi o líder agir dessa forma | BV11: Discordo | BW11: Existe pessoas sim que se importam com as outras mas existe algumas que pensam somente em si | BX11: Concordo | BZ11: Concordo Sempre | CB11: Concordo | CD11: Concordo | CF11: Concordo | CH11: Concordo Sempre | CJ11: Concordo | CL11: Concordo | CN11: Discordo | CO11: Não vejo fofoca no sentido de prejudicar a empresa ou algum colaborador | CP11: Discordo | CQ11: Vejo aqui entre as áreas os colaboradores se ajudando | CR11: Concordo | CT11: Concordo | CV11: Concordo | CW11: Existem pontos de melhorias que creio que será ouvido e aos poucos trabalhados e por isso ainda sim é um lugar bom de se trabalhar | CX11: Assistência Médica, Multibenefícios Alimentação/ Refeição, Auxílio Educação, Gympass (Convênio Academias), Day Off | CY11: Creio que alguns benefício que ainda não possuímos são simples por exemplo o day off é um deles . | CZ11: Transparência. Pontualidade. Cordialidade. | DA11: Salário. Benefícios. Treinamentos. | DB11: Creio que a Nordeste tem total capacidade de melhoria tanto que essa pesquisa é um dos indícios disso uma empresa que está em crescimento ainda assim é uma boa empresa pra se trabalhar, indicaria como uma boa empresa porém as melhorias em relação a benefícios , salários e treinamentos são os mais importantes
A12: 45687.353 | B12: Concordo | D12: Concordo | F12: Concordo | H12: Concordo | J12: Concordo | L12: Concordo | N12: Concordo | P12: Discordo | Q12: Acredito que deva melhorar em relação aos benefícios, tipo aumentar o valor do vale refeição para 25,00 por dia, Vale cultura, Gim pés, vale combustível para quem tem veículo próprio mas não faz uso do vale transporte. | R12: Concordo | T12: Concordo | V12: Concordo | X12: Concordo | Z12: Concordo | AB12: Discordo | AC12: Deveriam ter um setor para este tipo de atendimento/suporte aos funcionários | AD12: Concordo | AF12: Discordo | AH12: Concordo Sempre | AJ12: Concordo | AL12: Concordo Sempre | AN12: Concordo Sempre | AP12: Discordo | AQ12: As vezes sentimos falta desse diálogo diário, para que entendam as nossas necessidades | AR12: Concordo | AT12: Discordo | AU12: Falta de treinamentos específicos para a condução das nossas equipes | AV12: Concordo Sempre | AX12: Concordo | AZ12: Discordo | BA12: As vezes ficamos desenformados sobre as decisões estratégicas da empresa | BB12: Concordo | BD12: Concordo | BF12: Concordo | BH12: Concordo | BJ12: Concordo | BL12: Concordo | BN12: Concordo | BP12: Concordo | BR12: Concordo Sempre | BS12: É notório que nesta empresa se respeitam as diversidades | BT12: Discordo | BV12: Concordo | BX12: Concordo | BZ12: Concordo Sempre | CB12: Discordo | CD12: Concordo | CE12: Só precisam estar mais disponíveis a ouvir mais as sugestões | CF12: Concordo Sempre | CH12: Concordo | CJ12: Concordo Sempre | CL12: Concordo Sempre | CN12: Concordo | CP12: Discordo | CR12: Concordo Sempre | CT12: Concordo | CV12: Concordo Sempre | CW12: Ambiente descontraído e bom para se trabalhar | CX12: Auxílio Combustível, Multibenefícios Alimentação/ Refeição, Enxoval Maternidade, Seguro de Vida, Empréstimo Consignado | CY12: Estes benefícios irão fazer com que a empresa se torne uma referência no mercado | CZ12: Tem oportunidade de crescimento; Ambiente leve e descontraído; Empresa que valoriza as pessoas | DA12: No intuito de se tornar uma empresa melhor | DB12: Esta empresa está em crescimento e acreditamos que ela vai conseguir os seus objetivos, só que em paralelo deva melhorar os seus benefícios para que se torne uma empresa desejada para se trabalhar, valorizar a sua mão de obra pois é diferenciada e deve ser tratada diferente do mercado.
A13: 45687.353 | B13: Concordo | D13: Concordo | F13: Concordo | H13: Concordo | J13: Concordo | L13: Concordo | N13: Concordo | P13: Concordo | R13: Concordo | T13: Concordo | V13: Concordo | X13: Concordo | Z13: Concordo | AB13: Concordo | AD13: Concordo | AF13: Concordo | AH13: Concordo | AJ13: Concordo | AL13: Concordo | AN13: Concordo | AP13: Concordo | AR13: Concordo | AT13: Concordo | AV13: Concordo | AX13: Concordo | AZ13: Concordo | BB13: Concordo | BD13: Concordo | BF13: Concordo | BH13: Concordo | BJ13: Concordo | BL13: Concordo | BN13: Concordo | BP13: Concordo | BR13: Concordo | BT13: Discordo | BU13: Nunca | BV13: Concordo | BX13: Concordo | BZ13: Discordo | CB13: Discordo | CD13: Concordo | CF13: Concordo | CH13: Concordo | CJ13: Concordo | CL13: Concordo | CN13: Discordo | CP13: Discordo | CR13: Concordo | CT13: Concordo | CV13: Concordo | CW13: Bom | CX13: Assistência Médica, Assistência Odontológica, Auxílio Combustível, Refeição na Empresa, Cesta Básica | CY13: Ser mas valorizador | CZ13: Tudo éu acho bom na empresa não tenho que fala | DA13: Vale combustível | DB13: Gostaria muito do vale combustível
A14: 45687.354 | B14: Concordo | D14: Discordo | E14: Deveríamos receber mais fardamentos | F14: Concordo Sempre | G14: Pois estamos sempre em conjunto ajudando uns aos outros. | H14: Concordo Sempre | J14: Concordo Sempre | K14: Pois sempre estão nos dando oportunidades de aprender | L14: Concordo | N14: Concordo Sempre | P14: Discordo Sempre | Q14: O salário é abaixo do mercado, e algumas funções dentro da empresa deveria receber insalubridade e periculosidade pois trabalhamos com produtos altamente cancerígeno e com produtos químicos | R14: Concordo | T14: Concordo Sempre | U14: Pois todos se dispõe a ajudá-lo a desenvolver sua função e aprender um pouco mais sobre a mesma. | V14: Concordo | X14: Concordo | Z14: Concordo Sempre | AB14: Discordo | AC14: Deveria haver uma ouvidoria | AD14: Concordo | AF14: Concordo | AH14: Concordo | AJ14: Concordo Sempre | AL14: Concordo Sempre | AN14: Concordo Sempre | AP14: Concordo Sempre | AR14: Concordo Sempre | AT14: Concordo | AV14: Concordo Sempre | AX14: Concordo | AZ14: Concordo | BB14: Concordo | BD14: Concordo Sempre | BF14: Concordo | BH14: Concordo Sempre | BJ14: Concordo Sempre | BL14: Concordo | BM14: De acordo com sua função todos tem autonomia moderada | BN14: Concordo Sempre | BP14: Concordo Sempre | BR14: Concordo Sempre | BT14: Discordo | BU14: Pois ele sempre busca nos ajudar e nos compreender | BV14: Concordo | BX14: Concordo | BZ14: Concordo Sempre | CB14: Discordo | CD14: Concordo | CF14: Concordo | CH14: Concordo Sempre | CJ14: Concordo | CL14: Concordo | CN14: Concordo | CP14: Discordo | CR14: Concordo Sempre | CT14: Concordo | CV14: Concordo Sempre | CW14: Pois nós deixa a vontade para desenvolver nossa função | CX14: Assistência Médica, Multibenefícios Alimentação/ Refeição, Auxílio Educação, Seguro de Vida, Empréstimo Consignado, Day Off | CY14: Assistência médica é essencial pois todos estão exposto a sofrer algum acidente de trabalho | CZ14: - A empresa está sempre aberta a novas ideias - A empresa oferece plano de carreira e oportunidades a todos - Estão sempre disposto a ajudar | DA14: - Bonificação deveria ser para todos, pois todos tem participação em locações, toda função é essencial para obtermos as metas. - Deveria melhorar os material dos fardamentos e quantidade - Alguns EPI's poderiam ser melhorados ex, luvas para lavagem, respirador | DB14: .
A15: 45687.354 | B15: Concordo | C15: As pessoas sao muito expressivas e demonstram no ambiente de trabalho muito o sentimentos quando esta com raiva por assunto de trabalho ou vida pessoal e quando se preciaa fazer trabalhos internos ou falar com o proximo repassa no olhar | D15: Concordo | E15: Precisamos de melhoria com os aparelhos celulares por ser antigos | F15: Concordo | G15: Nem sempre | H15: Concordo | I15: Nem sempre todos pensam iguais | J15: Discordo | K15: Gostariamos de cursos com profissionais capacitados para assuntos de comércio, por muitas vezes as reuniões que se fazem para melhorar algo nao é focada apenas nesss assunto sendo abordado assuntos desnecessário ou ate mesmo constrangimento | L15: Concordo Sempre | N15: Concordo Sempre | P15: Concordo Sempre | R15: Concordo Sempre | S15: Um ramo no qual me sinto bem em fazer parte | T15: Concordo Sempre | V15: Concordo Sempre | W15: Todos aqui sao pessoas diferentes uns simpatizam mais que outros | X15: Concordo Sempre | Z15: Concordo Sempre | AB15: Concordo | AD15: Concordo | AE15: Ja saiu pessoas maravilhosas que acrescentavam e por motivos pessoais envolvidos quem estava treinando nao teve paciência enquanto a pessoa estava em tempo de aprendizado | AF15: Concordo Sempre | AH15: Concordo Sempre | AJ15: Concordo Sempre | AL15: Concordo | AM15: Demonstra porem algumas vezes nao nos sentimos ajudados quando necessitamos é muita justificativa de nao da certo dessa forma do que encontrar um meio melhor ja de cara. | AN15: Concordo Sempre | AP15: Concordo Sempre | AR15: Concordo Sempre | AT15: Discordo | AV15: Concordo | AX15: Concordo | AY15: Nem sempre | AZ15: Concordo Sempre | BB15: Concordo Sempre | BD15: Discordo | BF15: Concordo | BH15: Discordo | BJ15: Concordo | BL15: Discordo | BN15: Concordo | BP15: Concordo Sempre | BQ15: Chamada de atenção as vezes de forma que ele se expressa no olhar com uma furia | BR15: Concordo Sempre | BT15: Concordo | BU15: Ja presenciei formas de falar desnecessárias | BV15: Discordo | BW15: Nem sempre | BX15: Concordo | BZ15: Concordo Sempre | CB15: Concordo | CD15: Discordo | CF15: Concordo | CG15: Porem pouco contato na verdade quase nada | CH15: Concordo | CJ15: Concordo | CK15: As vezes so enxergam erros | CL15: Concordo | CN15: Concordo Sempre | CP15: Discordo | CR15: Concordo Sempre | CT15: Concordo | CV15: Concordo Sempre | CW15: . | CX15: Assistência Médica, Auxílio Combustível, Celular, Vale Alimentação, Auxílio Educação, Empréstimo Consignado | CY15: . | CZ15: O comprometimento com o funcionário A dinâmica mensais | DA15: Melhoria do vale combustível e alimentação | DB15: .
A16: 45687.355 | B16: Concordo | D16: Concordo | F16: Concordo Sempre | H16: Concordo Sempre | J16: Discordo | K16: Acredito que poderiam haver mais treinamentos que abrangem todos os setores. | L16: Discordo | N16: Concordo | P16: Discordo | Q16: Acredito que há cargos que os salários podem ser melhorados. | R16: Concordo | T16: Concordo Sempre | V16: Concordo | X16: Concordo | Z16: Concordo Sempre | AB16: Discordo Sempre | AC16: É necessário criação de um canal anônimo de comunicação. | AD16: Discordo | AF16: Concordo | AH16: Concordo | AJ16: Concordo Sempre | AL16: Concordo Sempre | AN16: Concordo Sempre | AP16: Concordo Sempre | AR16: Concordo Sempre | AT16: Concordo | AV16: Concordo | AX16: Concordo Sempre | AZ16: Concordo | BA16: Acredito que possa haver mais clareza em alguns processos. | BB16: Concordo | BD16: Concordo | BF16: Concordo | BH16: Concordo | BJ16: Concordo | BL16: Concordo | BN16: Concordo | BP16: Concordo | BR16: Concordo Sempre | BT16: Discordo | BV16: Concordo Sempre | BX16: Concordo | BZ16: Concordo | CA16: Acredito que outros setores como a manutenção deveriam ter comemoração de metas como outros setores tem. | CB16: Discordo | CD16: Concordo Sempre | CF16: Concordo Sempre | CH16: Concordo Sempre | CJ16: Concordo | CL16: Concordo Sempre | CN16: Concordo | CP16: Discordo | CR16: Concordo | CT16: Concordo Sempre | CV16: Concordo Sempre | CW16: - | CX16: Assistência Médica, Assistência Odontológica, Multibenefícios Alimentação/ Refeição, Gympass (Convênio Academias), Day Off | CY16: - | CZ16: União entre os setores, ambiente respeitoso com todos e gestores acessíveis. | DA16: Espaço físico, flexibilidade de horários e implementação de modelo de trabalho híbrido. | DB16: A implantação de gympass nos benefícios.
A17: 45687.357 | B17: Concordo | D17: Concordo Sempre | F17: Concordo | H17: Concordo | J17: Concordo | L17: Concordo | N17: Concordo Sempre | P17: Concordo | R17: Concordo | T17: Concordo Sempre | V17: Concordo Sempre | X17: Concordo | Z17: Concordo Sempre | AB17: Concordo | AD17: Concordo | AF17: Concordo Sempre | AH17: Concordo Sempre | AJ17: Concordo Sempre | AL17: Concordo Sempre | AN17: Concordo Sempre | AP17: Concordo Sempre | AR17: Concordo Sempre | AT17: Concordo | AV17: Concordo | AX17: Concordo Sempre | AZ17: Concordo | BB17: Concordo Sempre | BD17: Concordo | BF17: Concordo | BH17: Concordo Sempre | BJ17: Concordo Sempre | BL17: Concordo Sempre | BN17: Concordo Sempre | BP17: Concordo Sempre | BR17: Concordo Sempre | BT17: Discordo Sempre | BU17: Sempre fui tratado com muito respeito. | BV17: Concordo | BX17: Concordo Sempre | BZ17: Concordo Sempre | CB17: Discordo | CC17: As pessoas tem boas relações porque os chefes são acessíveis e tranquilos, mas não porque estão procurando promoção dessa forma. | CD17: Concordo Sempre | CF17: Concordo Sempre | CH17: Concordo Sempre | CJ17: Concordo Sempre | CL17: Concordo | CN17: Concordo | CO17: Acredito que todo lugar vai ter um pouco de fofoca. | CP17: Discordo | CQ17: No meu setor eu não vejo isso. | CR17: Concordo | CT17: Concordo | CV17: Concordo Sempre | CW17: Uma das melhores empresas em que trabalhei. | CX17: Assistência Médica, Auxílio Combustível, Vale Refeição, Vale Alimentação, Gympass (Convênio Academias) | CY17: Eu acho interessante um gympass | CZ17: Cultura da empresa é um ponto muito forte Diretores pacientes e acessíveis Bons colegas de trabalho | DA17: Acredito que plano de saúde poderia melhorar e descontar um pouco menos, só isso mesmo. | DB17: Só os parabéns pela pesquisa de clima.
A18: 45687.358 | B18: Concordo | D18: Concordo | F18: Discordo | G18: Na maioria das vezes algumas pessoas apenas fazem aquilo que é pedido ou que está acostumado, ao passar de qualquer responsabilidade rotineira já reclama. | H18: Concordo | I18: Hoje em dia a comunicação e a colaboração é melhor do que já foi a 1 ano, porém sinto falta de alguns colaboradores entenderem que todos os setores fazem a empresa acontecer e por isso todos independente da área de atuação precisam pensar no cliente e nos objetivos que temos para conseguirmos concluir nossas metas e objetivos. | J18: Discordo | K18: Sinto falta de um treinamento específico principalmente para novos colaboradores, nossa área de atuação é muito específica e muitas vezes o profissional não vem preparado e nem com o mínimo de conhecimentos sobre equipamentos, seria uma alternativa criar um tipo de treinamento sobre equipamentos para novos colaboradores. | L18: Concordo | N18: Concordo | P18: Discordo | Q18: Já melhorou bastante desde que abrimos a unidade, mas conhecendo o mercado ainda não chegamos no mesmo padrão salarial. | R18: Concordo Sempre | T18: Concordo Sempre | V18: Concordo | X18: Concordo | Z18: Concordo Sempre | AB18: Discordo | AC18: Normalmente quando precisamos sugerir ou reivindicar precisamos falar com o gerente da unidade, o que poderia acabar sobrecarregando com algo que poderia ser falado diretamente para os setores responsáveis. Seria interessante ser criado um tipo de canal de sugestões e idéias a qual os colaboradores poderiam dar sugestões de melhorias, fazer reivindicações e até expressar idéias. | AD18: Concordo Sempre | AF18: Concordo | AH18: Concordo Sempre | AJ18: Concordo Sempre | AK18: Em todas as conversas que temos ele sempre me instrui naquilo que espera e também almeja para mim profissionalmente, me dando sempre sugestões e feedbacks no que posso melhorar para ser uma boa profissional e crescer na empresa. | AL18: Concordo Sempre | AN18: Concordo Sempre | AP18: Concordo Sempre | AQ18: Em todas as vezes que precisei de ajuda com algo pessoal, ou fiquei doente ou algo relacionado, sempre vi que ele se mostrava prestativo em ajudar e genuinamente preocupado com meu bem estar. | AR18: Concordo Sempre | AT18: Concordo Sempre | AV18: Concordo Sempre | AX18: Concordo | AY18: Eu concordo, porém as vezes eu sinto falta de uma escuta mais ativa, sem interrupções e de tentar realmente entender o que estamos tentando explicar ou dar de idéia. | AZ18: Concordo Sempre | BB18: Concordo Sempre | BD18: Concordo Sempre | BF18: Concordo Sempre | BH18: Concordo | BJ18: Concordo Sempre | BL18: Concordo Sempre | BN18: Concordo Sempre | BP18: Concordo Sempre | BR18: Concordo | BT18: Discordo Sempre | BV18: Concordo | BX18: Discordo | BY18: Existe nos setores em específico, mas sinto falta do sentimento de equipe geral. | BZ18: Concordo Sempre | CB18: Discordo | CD18: Concordo | CE18: Temos fácil acesso para falar e até dar ideias, mas tenho a sensação de que as ideias não são genuinamente aceitas de forma positiva e nem ouvidas com atenção para tentar entender o que temos a dizer, como se o que dizemos até é ouvido no momento, mas logo após já é esquecido sem dar devida atenção. | CF18: Concordo | CH18: Concordo Sempre | CJ18: Concordo | CL18: Concordo Sempre | CN18: Discordo | CP18: Discordo Sempre | CR18: Concordo Sempre | CT18: Concordo | CU18: Há muita coisa pra melhorar ainda, mas já evoluímos bastante | CV18: Concordo Sempre | CW18: Nenhum lugar é perfeito, mas independente de tudo isso, a Nordeste é ótimo lugar para se trabalhar, gosto do meu trabalho e das pessoas com quem convivo mesmo com seus defeitos. | CX18: Assistência Médica, Auxílio Combustível, Multibenefícios Alimentação/ Refeição, Auxílio Educação, Gympass (Convênio Academias) | CY18: . | CZ18: Ambiente de trabalho, comunicação com a liderança e o reconhecimento aos colaboradores. | DA18: Melhoria na gestão de pessoas por parte da diretoria em relação a comunicação mais assertiva e escuta mais ativa, melhor suporte da parte administrativa (financeiro, contábil, comercial...), treinamentos específicos e bem organizados. | DB18: Nada mais a pontuar
A19: 45687.36 | B19: Concordo | D19: Discordo | E19: Agenda é fundamental para organização e planejamento do dia e ainda não recebemos. | F19: Concordo | G19: A maioria sim. | H19: Concordo | J19: Concordo | L19: Concordo | N19: Concordo | P19: Discordo | Q19: Diversas outras empresas do mesmo seguimento tem remunerações maiores, mas o que mais pesa na Nordeste realmente é bom relacionamento na empresa e com os seus diretores. | R19: Concordo | T19: Concordo | U19: O acolhimento da Nordeste realmente é diferenciado. | V19: Concordo | X19: Concordo | Z19: Concordo | AB19: Concordo | AC19: Concordo, mas na maioria das vezes em que são “deixadas” sugestões elas são rebatidas mostrando que não fazem sentido. | AD19: Concordo Sempre | AF19: Concordo Sempre | AH19: Concordo Sempre | AJ19: Concordo Sempre | AL19: Concordo Sempre | AN19: Concordo Sempre | AP19: Concordo | AR19: Concordo | AT19: Concordo Sempre | AV19: Concordo Sempre | AX19: Concordo | AZ19: Concordo | BB19: Concordo | BD19: Concordo Sempre | BF19: Discordo | BG19: Novas decisões ou diretrizes só são comunicadas. | BH19: Discordo | BI19: Depende muito do dia e da situação. | BJ19: Discordo | BK19: É um processo de construção constante, mas existe bastante divergência. | BL19: Concordo Sempre | BN19: Discordo | BO19: Há muita divergência. | BP19: Concordo Sempre | BR19: Concordo | BT19: Concordo | BU19: Existem algumas piadas com terceiros sim | BV19: Concordo | BX19: Concordo Sempre | BZ19: Concordo Sempre | CB19: Discordo Sempre | CC19: Não presenciei. | CD19: Concordo Sempre | CF19: Concordo Sempre | CH19: Concordo Sempre | CJ19: Concordo | CL19: Concordo | CN19: Concordo Sempre | CP19: Discordo | CQ19: A empresa trabalha muito em equipe. | CR19: Concordo Sempre | CT19: Concordo | CV19: Concordo | CW19: Sim é um lugar para se trabalhar | CX19: Assistência Médica, Assistência Odontológica, Multibenefícios Alimentação/ Refeição, Auxílio Educação, Seguro de Vida, Gympass (Convênio Academias), Day Off | CY19: Nada a complementar. | CZ19: Organização, bom relacionamento entre setores, bom relacionamento com os diretores | DA19: Treinamento e desenvolvimento, espaço de trabalho, salário compatível com o mercado. | DB19: Nada a complementar.
A20: 45687.36 | B20: Concordo | C20: . | D20: Concordo | E20: . | F20: Discordo | G20: Pessoal acomodado , so faz o basico fico um pouco preocupado em relaçao a isso !! | H20: Concordo | I20: Porém, para fazer alguma atividades que cabe ao mesmo é preciso que chame ! | J20: Concordo | K20: . | L20: Concordo | M20: Sim, e estou buscando melhoras para crescer junto com a empresa!! | N20: Discordo | O20: Nossos lideres nao reconhece !! | P20: Concordo | R20: Concordo | S20: Gosto do que faço!! | T20: Concordo | V20: Discordo | W20: Eu sou grato pro alguma coisas mais nao tenho orgulho nao , pessoas tende a Ser Falsas | X20: Concordo | Z20: Discordo | AA20: Algumas coisas me deixam na obrigaçao de participar, nao e do meu perfil certas coisas que aqui vejo ou faço! | AB20: Concordo | AC20: O unico canal para esse tipo de situaçao é essa pesquisa de clima e eu espero que realmente fucione! | AD20: Concordo | AE20: Eu acredito, nosso segmento é instavel e sao cheio de supresas !! | AF20: Discordo | AG20: Nao me lembro de ninguem aqui me encorajar am nada ! | AH20: Discordo | AI20: Nao sei .. | AJ20: Discordo | AK20: Nao , muitas falhas na LINDERÇA | AL20: Discordo | AM20: Nao vejo ele comentando muito sobre isso nao !! | AN20: Concordo | AO20: . | AP20: Concordo | AR20: Concordo | AS20: Porem devido algumas falha dele , as conversas e reividicaçoes nao sao cumpridas . | AT20: Discordo | AU20: Nao , nao vejo isso aqui. | AV20: Concordo | AW20: . | AX20: Concordo | AY20: Nao é sempre ! | AZ20: Concordo | BA20: . | BB20: Concordo | BC20: . | BD20: Concordo | BE20: Sim, mais é necessario que haja um acompanhamento , ja que se faz necessario !! | BF20: Concordo | BG20: . | BH20: Discordo | BI20: Ha sempre uma que tem um tratamento diferente ! | BJ20: Discordo | BK20: Muitas falhas nesse tipo de tarefa! | BL20: Concordo | BM20: . | BN20: Discordo | BO20: Nao , fala mais nao faz !! | BP20: Concordo | BQ20: . | BR20: Concordo | BS20: . | BT20: Concordo | BU20: . | BV20: Discordo | BW20: Nao , nao vou generalizar mais muitas aqui nao tem sentimos pelos outros !! | BX20: Discordo | BY20: Muita idividualismo. | BZ20: Concordo | CA20: . | CB20: Concordo | CC20: So so fazem escondido! | CD20: Concordo | CE20: . | CF20: Discordo | CG20: Nao , ainda fexados para alguns assuntos | CH20: Concordo | CI20: . | CJ20: Concordo | CK20: . | CL20: Concordo | CM20: . | CN20: Concordo | CO20: Muita, bastante muitas vezes parte ate de pessoas a Cima de voce | CP20: Concordo | CQ20: Vejo sim, e isso me encomoda | CR20: Concordo | CS20: Tenho certeza que boas coisas estao por vim.. | CT20: Discordo | CU20: Nao , vejo muito cada um no seu !! | CV20: Concordo | CW20: Com alguma coisas a serem corregidas , mais sim digo que é um bom lugar pra trabalhar !! | CX20: Assistência Médica, Auxílio Combustível, Vale Alimentação, Auxílio Educação, Day Off | CY20: . | CZ20: Comprpmisso, atençao com colaborador, e abertas a ideias . | DA20: Mais firmeza dos lideres e compromisso por parte da alguns colabordores . | DB20: .
A21: 45687.36 | B21: Concordo | C21: Eu gosto do meu ambiente de trabalho, pois me sinto beme me sinto leve para realizar minhas atividades | D21: Concordo | E21: Todos os equipamentos que preciso tenho para realizar meu trabalho | F21: Concordo | G21: Sim com certeza | H21: Concordo | I21: Sim | J21: Concordo | K21: Sim | L21: Concordo | M21: Sim com certeza | N21: Concordo | O21: Sim | P21: Discordo | Q21: Não | R21: Concordo Sempre | S21: Sim, pois o meu trabalho tem um grande significado pra mim, e não e só mais um trabalho | T21: Concordo | U21: Sim, sempre fazemos apresentação | V21: Concordo | W21: Sim | X21: Concordo | Y21: Sim | Z21: Concordo | AA21: Me sinto bem no meu ambiente de trabalho, pois não me sinto afadigado com minhas atividades, e não preciso fingir ser alguém que não sou | AB21: Discordo | AC21: Não | AD21: Concordo | AE21: ... | AF21: Concordo | AH21: Concordo | AI21: Sim, sei quem e meu líder | AJ21: Concordo | AK21: Sei o que ele espera, ele espera resultados positivos, eficiência e agilidade no trabalho | AL21: Concordo | AM21: Sempre uma pessoa comprometida com o trabalho, interessado, e empenhado com o crescimento 📈 da empresa e tem uma visão clara do futuro e sabe o que quer para si, e para os demais | AN21: Concordo | AO21: Meu líder e honesto, tem uma boa conduta, um bom caráter para lidar com os negócios da empresa e sempre e transparente | AP21: Concordo | AQ21: Meu líder não só me vê como um simples funcionário, pois me vê além do que um funcionário, pois me vê como um um amigo e não só como funcionário | AR21: Concordo | AS21: Sim, pois o que precisamos o que ele sempre está aqui pra nós estender a mão e propor soluções para cada tipo de situação | AT21: Concordo | AU21: Sim, sempre nos instrui nos mostrando o caminho certo para o que devemos fazer, onde estamos errando para que não erre mais, como um bom pastor que guia as ovelhas | AV21: Concordo | AX21: Concordo | AY21: Sim, pois sempre está apto para ouvir nossas ideias de melhoria e sempre melhora nossas ideias | AZ21: Concordo | BA21: Sim pois todos os assuntos que nos convém saber ele está sempre nos deixando por dentro sempre | BB21: Concordo | BD21: Concordo | BE21: Sim, pois ele confia no nosso trabalho isso e o que um elo de confiança que temos, confiança e base de tudo sem isso o trabalho não rende, o trabalho não sai legal então confiança e tudo | BF21: Concordo | BH21: Concordo | BI21: Sim, pois ele não passa a mão na cabeça de ninguém, pois ele prática a justiça ⚖️♎ para todos | BJ21: Concordo | BL21: Concordo | BM21: Sim, vejo meu linder dar autonomia para as pessoas, eu acho isso muito importante | BN21: Concordo | BO21: Sim, pois age da forma como fala | BP21: Concordo | BQ21: Ele está sempre dando feedback, tá sempre chamando a gente pra dar opinião, falando como podemos agir pra melhorar como funcionário | BR21: Concordo | BT21: Discordo | BV21: Discordo | BX21: Concordo | BY21: Sim,. existe pois estamos sempre tentando ajudar uns aos outros | BZ21: Concordo | CA21: Sim, pois eu só acho que devíamos melhorar um pouco no valor, pois acho muito pouco para nossa região | CB21: Discordo | CC21: Discordo pois não vejo isso entre nós | CD21: Concordo | CF21: Concordo | CG21: ... | CH21: Concordo | CI21: Sou sim, independente da minha posição de trabalho | CJ21: Concordo | CK21: ... | CL21: Concordo | CM21: Sim, pois meu lugar de trabalho e bom pra trabalhar e leve | CN21: Concordo | CO21: ... | CP21: Discordo | CQ21: Não vejo entre nós | CR21: Concordo | CS21: Sim com certeza por muito tempo se Deus permitir | CT21: Discordo | CU21: .... | CV21: Concordo | CW21: Sim concordo plenamente | CX21: Assistência Médica, Celular, Refeição na Empresa, Seguro de Vida, Empréstimo Consignado, Gympass (Convênio Academias) | CY21: .. | CZ21: Reconhecimento profissional. Benefícios ... | DA21: Eu acho que devíamos ter uma ouvidoria para ouvir nossas queixas reclamações, acho que e importante em questão ao salário e pago muito tarde eu acho que seja um ponto de melhoria para melhorara e pagar pela manhã | DB21: Eu acho que deviam ser pergunta melhores, e menos perguntas pois tem muitas perguntas
A22: 45687.36 | B22: Concordo | D22: Concordo | F22: Concordo | H22: Concordo | J22: Concordo | L22: Concordo | N22: Concordo | P22: Discordo | Q22: Salários um pouco a baixo do mercado, incluindo ticket. | R22: Concordo | T22: Concordo | V22: Concordo | X22: Discordo | Y22: Falando por mim próprio, eu sempre venho com vontade e disposição para trabalhar, os meus colegas eu já não sei, aparentemente sim, alguns. | Z22: Concordo | AB22: Concordo | AC22: Na unidade de São Luís o gestor está sempre aberto a ouvir os colaboradores e sempre fazendo feedbacks para tratar assuntos de melhorias para a equipe. | AD22: Concordo Sempre | AF22: Concordo | AH22: Concordo | AJ22: Concordo | AL22: Concordo | AN22: Concordo | AP22: Concordo | AR22: Concordo | AT22: Concordo | AV22: Concordo | AX22: Concordo | AZ22: Concordo | BB22: Concordo | BD22: Discordo | BE22: Em partes sim em partes não, muitas vezes tem aquela olhada no sistema de monitoramento, mas nada prejudicial. Acredito que seja normal em todas as empresas. | BF22: Discordo | BH22: Concordo | BJ22: Concordo | BL22: Concordo | BN22: Concordo | BP22: Concordo | BR22: Concordo | BT22: Discordo Sempre | BV22: Concordo | BX22: Concordo | BZ22: Concordo | CB22: Discordo | CD22: Concordo | CF22: Concordo | CH22: Concordo | CJ22: Concordo | CL22: Concordo | CN22: Concordo | CP22: Discordo | CR22: Concordo Sempre | CT22: Concordo | CV22: Concordo | CW22: Ambiente legal, com pessoas boas, competentes, companheiras, etc. | CX22: Assistência Médica, Auxílio Combustível, Multibenefícios Alimentação/ Refeição, Seguro de Vida, Day Off | CY22: Poderia ter mais que cinco opções! | CZ22: Reconhecimento de profissionais, ambiente leve, valorização. | DA22: Valorização de salários, valorização de ticket, treinamentos adequados com nossas marcas parceiras (todas). | DB22: Nada além do que já foi observado nos comentários.
A23: 45687.361 | B23: Concordo | D23: Concordo | F23: Concordo | H23: Concordo | J23: Concordo | L23: Concordo | N23: Concordo | P23: Discordo | Q23: Em relação a área da manutenção, já vi que em outras locadoras o salário é mais acima do que é pago aqui atualmente | R23: Concordo | T23: Concordo | V23: Concordo Sempre | X23: Concordo | Z23: Concordo | AB23: Concordo | AD23: Concordo | AF23: Concordo | AH23: Concordo | AJ23: Discordo | AK23: Discordo pois meu superior imediato seria o supervisor e no caso não temos tanto contato, é uma pessoa ausente no meu cotidiano | AL23: Discordo | AM23: Discordo se tratando da supervisão, me baseio por questão do supervisor demonstrar que não tem tanto interesse em estar mais presente, trazer as melhorias que o setor tem dificuldades | AN23: Concordo | AP23: Discordo Sempre | AQ23: Discordo pois já aconteceram situações de ser mais humano e tentar se colocar no lugar do colaborador, faltou empatia | AR23: Concordo | AT23: Concordo | AV23: Concordo | AX23: Concordo | AZ23: Concordo | BB23: Concordo | BD23: Concordo | BF23: Concordo | BH23: Concordo | BJ23: Concordo | BL23: Concordo | BN23: Concordo | BP23: Concordo | BR23: Concordo | BT23: Discordo Sempre | BV23: Concordo | BX23: Concordo | BZ23: Discordo Sempre | CA23: Discordo pois, setores comercias e financeiros atingem suas metas de locações, mas tudo aqui é uma engrenagem todos colaboram para que essas metas sejam batidas, porém sempre é apenas um setor específico que vai comemorar | CB23: Concordo | CC23: Concordo pois já presenciei pessoas perto de gestores agindo dessa maneira | CD23: Discordo | CE23: Discordo pois geralmente falamos com intermediários | CF23: Concordo | CH23: Concordo | CJ23: Concordo | CL23: Concordo | CN23: Concordo | CP23: Concordo | CQ23: Concordo por conta do evento de destaque do mês, acaba muitas vezes trazendo um pouco de rivalidade, acredito que seria melhor achar um evento que conseguisse unir mais as pessoas | CR23: Concordo | CT23: Concordo | CV23: Discordo | CW23: Discordo em questão de benefícios, não chegar a ser ótimo, pois a empresa não ajuda quem tem transporte próprio a chegar na empresa, o plano de saúde é caro para o salário que recebemos | CX23: Assistência Médica, Auxílio Combustível, Multibenefícios Alimentação/ Refeição, Cesta Básica, Seguro de Vida | CY23: Auxílio combustível é algo que é essencial pois geralmente corresponde a 20% do que recebemos, ainda mais pra quem mora mais distante da empresa, acaba que o colaborador paga para trabalhar em certas partes Sobre o seguro de vida é essencial, pois realizamos manutenções externas de moto e corremos grandes riscos na estrada, não só pela nossa condução mais também por depender dos outros condutores ao redor e a empresa simplesmente não dá nem uma assistência quanto a isso, somos responsáveis por tudo, moto, multa, nossa segurança e não recebemos nada em troca disso | CZ23: Ambiente agradável Ferramentas de trabalho Colaboradores com vontade de ajudar | DA23: Banheiros Segurança em questão de o portão sempre estar aberto e não ter ninguém para mapear quem está entrando e saindo da empresa Estacionamento com Proteção de sol para as motos e segurança dos transportes dos colaboradores | DB23: A principal dor atualmente é sobre o custo para chegar na empresa, peço encarecidamente que isso seja bem revisto e que consigam a melhor solução para melhorar a vontade dos colaboradores e o ambiente do trabalho, e sobre a liderança acredito que eles deveriam lutar mais pra trazer mais melhorias para o setor, o supervisor poderia ser mais presente
A24: 45687.361 | B24: Concordo | D24: Concordo | F24: Concordo | H24: Concordo | J24: Discordo | K24: Por não receber mas treinamento. | L24: Concordo | N24: Concordo | P24: Concordo | R24: Concordo | T24: Concordo | V24: Concordo | X24: Concordo | Z24: Concordo | AB24: Concordo | AD24: Concordo | AF24: Concordo | AH24: Concordo | AJ24: Concordo | AL24: Concordo | AN24: Concordo | AP24: Concordo | AR24: Concordo | AT24: Concordo | AV24: Concordo | AX24: Concordo | AZ24: Concordo | BB24: Concordo | BD24: Concordo | BF24: Concordo | BH24: Concordo | BJ24: Concordo | BL24: Concordo | BN24: Concordo | BP24: Concordo | BR24: Concordo | BT24: Discordo | BV24: Concordo | BX24: Concordo | BZ24: Concordo | CB24: Discordo | CD24: Concordo | CF24: Concordo | CH24: Concordo | CJ24: Concordo | CL24: Concordo | CN24: Discordo | CP24: Discordo | CR24: Concordo | CT24: Concordo | CV24: Concordo | CW24: Tem pessoas boa para trabalha. | CX24: Assistência Médica, Auxílio Combustível, Multibenefícios Alimentação/ Refeição, Auxílio Educação, Seguro de Vida | CY24: Ok | CZ24: Ambinte de trabalho, reconhecimento, valorização | DA24: Mais treinamento, valorização de salario,valorização do ticket. | DB24: Tudo que comentei é minha opinião
A25: 45687.361 | B25: Concordo | D25: Concordo | F25: Concordo | G25: Nem sempre, acredito que às vezes falta um pouco de motivação. | H25: Concordo Sempre | J25: Discordo | K25: Desde que entrei na Nordeste, aproximadamente um ano, ainda não vi a empresa fornecer treinamentos, tanto na parte operacional, como quanto aos conhecimentos do sistema utilizado. A aprendizagem é somente através da vivência ou de um outro colaborador que, nem sempre tem toda a disponibilidade para ensinar da melhor forma. | L25: Concordo | N25: Concordo | P25: Discordo | Q25: Percebo que a disponibilidade de mão de obra em São Luís é bem escassa para este segmento e, devido a isso, ao encontrar um colaborador que se adeque às necessidades da empresa, o ideal seria uma remuneração mais adequada. | R25: Concordo | S25: Gosto de trabalhar “processos”, a soma disso com o ambiente agradável e as possibilidades de crescimento me fazem concordar. | T25: Discordo | U25: Normalmente, quando a correria tá grande, nem dá tempo de pensar nessa receptividade. Normalmente o que acontece é o convívio do dia a dia que vai sendo estabelecido. | V25: Concordo | X25: Concordo | Z25: Discordo | AA25: Nem sempre. Respondi anteriormente que gosto de trabalhar com processos estabelecidos. Quando isso não acontece, sinto que não estou fazendo a coisa certa, mesmo que isso seja em prol de algo benéfico para a meta. Processo é processo. | AB25: Discordo Sempre | AC25: Não há. Deveria ter. | AD25: Concordo | AF25: Concordo | AH25: Concordo | AJ25: Concordo Sempre | AK25: É nítido nos feedbacks. | AL25: Concordo | AN25: Concordo | AP25: Concordo | AR25: Concordo | AT25: Concordo | AV25: Concordo | AX25: Concordo | AZ25: Concordo Sempre | BB25: Discordo Sempre | BD25: Concordo | BF25: Concordo Sempre | BH25: Concordo | BJ25: Concordo | BL25: Discordo | BM25: Nem sempre. Mas acredito que realmente seja pensando em algo que no momento não está sendo visível por quem tenta tomar uma determinada decisão. | BN25: Concordo | BP25: Concordo Sempre | BR25: Concordo Sempre | BT25: Discordo Sempre | BU25: Nunca presenciei alguma situação desse tipo. | BV25: Discordo | BW25: Nem todo mundo. Algumas pessoas não estão preocupadas apenas em “fazer o seu” e ir embora. | BX25: Concordo Sempre | BZ25: Concordo Sempre | CB25: Concordo | CC25: Certas atitudes me fazem pensar que sim. | CD25: Concordo Sempre | CF25: Concordo | CH25: Concordo Sempre | CJ25: Concordo Sempre | CL25: Concordo | CN25: Concordo | CP25: Discordo | CQ25: Não há. | CR25: Discordo | CS25: Acredito que isso depende da motivação. Isso vai de acordo com o quanto sou reconhecido na empresa. Obviamente…Eu sendo aquele cara que se esforça para ser reconhecido. É um fator determinante sobre o desejo de permanência de qualquer colaborador. Perspectivas de crescimento | CT25: Concordo | CV25: Concordo | CW25: Vejo que o ambiente leve faz com que até mesmo as preocupações do dia a dia se relevem, se tornando mais simples a resolução de vários problemas. | CX25: Assistência Médica, Assistência Odontológica, Vale Alimentação, Gympass (Convênio Academias), Day Off | CY25: Day off! Kk | CZ25: Possibilidades de crescimento dentro da empresa; ambiente leve; comunicação com lideranças. | DA25: Melhoria na possibilidade de solicitações e reivindicações; melhoria na acessibilidade de acompanhamento psicológico; disponibilização de treinamentos em geral. | DB25: Gostaria de reforçar sobre a questão da disponibilidade de treinamentos, pois acredito que isso contribuiria positivamente com a confiança/segurança do próprio colaborador com qualquer que seja o procedimento relacionado à sua área de atuação na empresa.
A26: 45687.362 | B26: Concordo Sempre | D26: Concordo | F26: Discordo | G26: Acredito que podemos trabalhar melhor nas pessoas o espírito de ajuda entre áreas, e colaboração dentro da equipe com intuito de gerar uma melhor ajuda nas atividades. | H26: Concordo | J26: Concordo | L26: Discordo | M26: Acredito que possamos deixar mais claro para todos quais os objetivos de futuro da empresa. | N26: Discordo | O26: Acredito que podemos ter um processo de promoção e reconhecimento mais claro, para que as pessoas possam buscar alcançar. | P26: Discordo | Q26: Conheço pessoas com as mesmas funções em empresas do mesmo seguimento, que possuem salários bem superiores. | R26: Concordo Sempre | T26: Concordo | V26: Concordo Sempre | X26: Concordo | Z26: Concordo Sempre | AB26: Discordo | AC26: É confuso se de fato existem esses canais. | AD26: Concordo | AF26: Concordo | AH26: Concordo Sempre | AJ26: Concordo | AL26: Concordo | AN26: Concordo | AP26: Discordo | AQ26: Acredito que poderia ter um olhar mais humanizado. | AR26: Concordo | AT26: Concordo | AV26: Discordo | AW26: Acho que poderia ter feedbacks frequentes | AX26: Discordo | AY26: Acredito que falta um pouco de ação, sobre novas ideias. | AZ26: Concordo Sempre | BB26: Discordo | BC26: Acho que falta deixar mais claro qual objetivo da empresa pro futuro. | BD26: Concordo | BF26: Concordo | BH26: Discordo | BI26: Acho que tem pessoas que possuem relacionamento pessoal e isso acaba afetando. | BJ26: Concordo | BL26: Concordo Sempre | BN26: Discordo | BO26: Vejo incoerência entre fale e ações | BP26: Concordo | BR26: Concordo Sempre | BT26: Discordo Sempre | BU26: Nunca vivi e nem presenciei nada. | BV26: Concordo | BX26: Concordo | BZ26: Discordo | CA26: Acho que devia ter comemorações sempre que as metas fossem alcançadas. | CB26: Concordo | CD26: Concordo | CF26: Concordo | CH26: Concordo | CJ26: Discordo | CK26: Acredito poder trabalhar para fazer a diferença. Mas poderia ser mais valorizada. | CL26: Concordo | CN26: Concordo Sempre | CO26: Muita | CP26: Concordo | CR26: Concordo | CT26: Discordo | CU26: Acredito que poderia ser melhor integrada as equipes. | CV26: Concordo | CW26: Concordo | CX26: Assistência Médica, Auxílio Combustível, Multibenefícios Alimentação/ Refeição, Gympass (Convênio Academias), Day Off | CY26: Auxílio combustível é algo que deveria ser aplicado o mais breve possível. Levando em consideração a quantidade de pessoas que utilizam seu próprio transporte para vim trabalhar. Se todos decidissem vim de ônibus a empresa não teria que arcar? Então fica a sugestão para que busquem isso, pois seria algo muito atrativo para todos. E a empresa só tem a ganhar | CZ26: Ambiente jovem, cultura presente, bons profissionais | DA26: Reconhecimento, comunicação, evitar relacionamentos pessoais | DB26: Acredito que a empresa possa buscar melhorias contínuas, sempre ouvindo as pessoas e tomando uma ação sobre isso. Ouvir as críticas, e sugestões para que possam criar ações futuras.
A27: 45687.363 | B27: Discordo | C27: Solicito algumas melhorias no ambiente de trabalho | D27: Discordo | E27: Má qualidade do epi(bota,capacete,entre outros) | F27: Concordo Sempre | H27: Concordo Sempre | J27: Concordo Sempre | K27: A empresa necessita de treinamentos para os funcionários | L27: Concordo Sempre | N27: Discordo | P27: Discordo | R27: Concordo | T27: Concordo | V27: Concordo Sempre | X27: Discordo | Z27: Concordo | AB27: Discordo | AD27: Concordo Sempre | AF27: Discordo | AH27: Concordo | AJ27: Concordo | AL27: Concordo | AN27: Concordo | AP27: Concordo | AR27: Concordo | AT27: Concordo | AV27: Concordo | AX27: Concordo | AZ27: Concordo | BB27: Concordo Sempre | BD27: Concordo Sempre | BF27: Concordo Sempre | BH27: Discordo | BJ27: Concordo Sempre | BL27: Concordo | BN27: Concordo | BP27: Concordo | BR27: Concordo | BT27: Discordo | BV27: Discordo Sempre | BX27: Concordo Sempre | BZ27: Concordo | CB27: Concordo Sempre | CD27: Discordo | CF27: Concordo Sempre | CH27: Concordo Sempre | CJ27: Concordo Sempre | CL27: Concordo Sempre | CN27: Concordo | CP27: Discordo Sempre | CR27: Concordo | CT27: Discordo | CV27: Concordo | CW27: Sim,é um bom ambiente de trabalho | CX27: Assistência Médica, Assistência Odontológica, Auxílio Combustível, Refeição na Empresa, Multibenefícios Alimentação/ Refeição, Cesta Básica, Seguro de Vida, Gympass (Convênio Academias) | CY27: Mais benefícios para os funcionários | CZ27: Boá relação interpessoal entre os funcionários | DA27: Benefícios para os funcionários | DB27: Isso é tudo!!
A28: 45687.363 | B28: Concordo Sempre | C28: Clima agradável, sintonia da equipe em crescimento da empresa | D28: Concordo Sempre | E28: Não | F28: Concordo | G28: Não | H28: Concordo Sempre | I28: Não | J28: Concordo | K28: Não | L28: Concordo Sempre | M28: Não | N28: Concordo | O28: Não | P28: Concordo | Q28: Não | R28: Concordo Sempre | S28: Não | T28: Concordo Sempre | U28: Não | V28: Concordo Sempre | W28: Não | X28: Concordo | Y28: Não | Z28: Concordo | AA28: Não | AB28: Discordo | AC28: Não | AD28: Concordo Sempre | AE28: Não | AF28: Concordo Sempre | AG28: Não | AH28: Concordo Sempre | AI28: Não | AJ28: Concordo Sempre | AK28: Não | AL28: Concordo Sempre | AM28: Não | AN28: Concordo Sempre | AO28: Não | AP28: Concordo Sempre | AQ28: Não | AR28: Concordo Sempre | AS28: Não | AT28: Concordo Sempre | AU28: Não | AV28: Concordo Sempre | AW28: Não | AX28: Concordo Sempre | AY28: Não | AZ28: Concordo Sempre | BA28: Não | BB28: Concordo Sempre | BC28: Não | BD28: Concordo Sempre | BE28: Não | BF28: Concordo | BG28: Não | BH28: Concordo Sempre | BI28: Não | BJ28: Concordo Sempre | BK28: Não | BL28: Concordo Sempre | BM28: Não | BN28: Concordo Sempre | BO28: Não | BP28: Concordo Sempre | BQ28: Não | BR28: Concordo Sempre | BS28: Não | BT28: Discordo | BU28: Não | BV28: Concordo | BW28: Não | BX28: Concordo | BY28: Não | BZ28: Concordo | CA28: Não | CB28: Discordo | CC28: Não | CD28: Concordo Sempre | CE28: Não | CF28: Concordo Sempre | CG28: Não | CH28: Concordo | CI28: Não | CJ28: Concordo Sempre | CK28: Não | CL28: Concordo Sempre | CM28: Não | CN28: Discordo | CO28: Não | CP28: Discordo | CQ28: Não | CR28: Concordo Sempre | CS28: Não | CT28: Concordo | CU28: Não | CV28: Concordo Sempre | CW28: Não | CX28: Assistência Médica, Multibenefícios Alimentação/ Refeição, Auxílio Educação, Empréstimo Consignado, Gympass (Convênio Academias) | CY28: Não | CZ28: Comunicação com a Diretoria, Clima interno e Benefícios | DA28: Mais benefícios, Trilha clara para crescimento interno | DB28: Não
A29: 45687.366 | B29: Concordo Sempre | C29: * | D29: Concordo | E29: * | F29: Discordo | G29: Algumas pessoas são muito acomodadas, não tem a pró-atividade e nem muito menos disponibilidade de ajudar o próximo ou fazer atividades além de suas obrigações. | H29: Discordo | I29: Nem todos, alguns fazem o mínimo | J29: Concordo | K29: Os treinamentos poderiam se expandir para todos, principalmente para os serviços gerais. | L29: Concordo | N29: Concordo Sempre | O29: Nem todos os colaboradores são reconhecidos ou dado a oportunidade de crescimento. | P29: Concordo Sempre | Q29: O salário é o base, o que diferencia são os benefícios. | R29: Concordo Sempre | T29: Concordo Sempre | U29: Passam os maus hábitos, como fofoca ou buscam induzem a não se esforçar, pois não terão reconhecimento no final. | V29: Concordo | X29: Concordo Sempre | Y29: Alguns se sentem desmotivados | Z29: Discordo | AA29: Você acaba mandando a sua personalidade para entrar/ser aceito no "grupo" | AB29: Discordo Sempre | AC29: Não tem, o líder não toma ação para mudar um cenário ou ocorrido que gerou desconforto. Logo alguns preferem não falar ou tem medo de repassar para a direção | AD29: Concordo | AF29: Concordo Sempre | AG29: Pelo líder não, por outras pessoas | AH29: Concordo | AJ29: Concordo | AL29: Concordo Sempre | AN29: Concordo Sempre | AO29: Quando se trata de gestão das pessoas, deixa a desejar. | AP29: Discordo | AQ29: Apenas trabalho | AR29: Concordo Sempre | AS29: Falta ação para tomar decisão quando surge um desconforto no time | AT29: Discordo | AU29: Não tem treinamento | AV29: Concordo Sempre | AX29: Concordo Sempre | AZ29: Concordo | BB29: Concordo Sempre | BD29: Discordo | BE29: Não tem, alguma pessoas são acomodadas | BF29: Discordo | BG29: Falta ação para melhoria | BH29: Discordo | BI29: Alguns pensam que tem preferência/apreço em um colaborador problemático | BJ29: Discordo | BK29: Deixa todos muito a vontade | BL29: Concordo Sempre | BM29: Mas nem todos sabem se direcionaram sem sozinhos | BN29: Discordo | BO29: "Passa a mão" na cabeça ou "fecha os olhos" para muitas coisas erradas dentro da empresa | BP29: Concordo Sempre | BQ29: O que é feito com um não é feito com o outro, desfavorecomento | BR29: Concordo | BT29: Concordo Sempre | BU29: Quando fica nervoso não sabe dosar as palavras | BV29: Discordo | BW29: Apenas se interferir com o seu trabalho | BX29: Discordo | BY29: Alguns buscam união, outros fazer apenas a sua parte | BZ29: Concordo | CB29: Discordo | CC29: Não identifiquei | CD29: Concordo | CF29: Concordo | CH29: Concordo Sempre | CJ29: Concordo Sempre | CL29: Concordo | CN29: Concordo | CO29: Sem moderação, os colaboradores não sabem viver em harmonia | CP29: Concordo Sempre | CQ29: No comercial e entre os mecânicos | CR29: Concordo Sempre | CS29: Caso outra empresa me oferecer um emprego com uma melhor remuneração e a Nordeste não valorizar o meu desempenho, aceitarei a proposta. | CT29: Concordo Sempre | CU29: Os colaboradores mais novo têm um bom entrosamento, os antigos são acomodados | CV29: Concordo | CW29: * | CX29: Assistência Médica, Multibenefícios Alimentação/ Refeição, Gympass (Convênio Academias), Day Off, Trabalhar ate quinta | CY29: * | CZ29: Os diretores são próximos dos colaboradores A empresa sempre trás ações diferentes Busca um trabalho mais harmonioso | DA29: A colaboração dos colaboradores Os colaboradores ser mais eficientes ou ter um controle mais rigoroso nas atividades para não deitar tão a vontade e acabar perdendo o controle Ter um espaço melhor para o descanso | DB29: Os diretores precisão ser mais presentes nas filias, pois acaba que os colabores fazem o que acham ser o certo e não tem a orientação correta.
A30: 45687.368 | B30: Concordo Sempre | D30: Concordo | F30: Concordo | H30: Concordo | J30: Concordo | L30: Concordo | N30: Concordo | P30: Discordo | Q30: Nao, poderia ser mais valorizado | R30: Concordo | T30: Concordo Sempre | V30: Concordo | X30: Concordo | Z30: Concordo | AB30: Discordo | AC30: Não existe, poderiam procurar um meio de melhorar isso | AD30: Concordo | AF30: Concordo | AH30: Concordo | AJ30: Concordo Sempre | AL30: Concordo Sempre | AN30: Concordo | AP30: Concordo | AR30: Concordo Sempre | AT30: Concordo Sempre | AV30: Concordo | AX30: Concordo | AZ30: Concordo | BB30: Concordo | BD30: Concordo | BF30: Concordo | BH30: Concordo | BJ30: Concordo | BL30: Concordo | BN30: Concordo | BP30: Concordo | BR30: Concordo | BT30: Discordo Sempre | BU30: Nunca me aconteceu | BV30: Concordo | BX30: Concordo | BZ30: Concordo | CB30: Discordo | CC30: Nunca percebi isso | CD30: Concordo | CF30: Concordo | CH30: Concordo | CJ30: Concordo | CL30: Concordo | CN30: Discordo | CO30: Nunca reparei nisso | CP30: Discordo | CQ30: acredito que não | CR30: Discordo | CS30: Dependendo das oportunidades | CT30: Concordo | CV30: Concordo | CW30: É um local tranquilo e confortável | CX30: Assistência Médica, Auxílio Combustível, Multibenefícios Alimentação/ Refeição, Gympass (Convênio Academias), Day Off | CY30: . | CZ30: Trabalho em equipe, organização e ambiente saudável | DA30: Modelo de trabalho híbrido poderia melhorar a qualidade de vida de colaboradores que conseguem fazer seu trabalho de casa/ Melhoria de Benefícios/ Criar um plano de carreira claro para os colaboradores poderem ver as oportunidades de crescimento dentro da empresa/ Tornar mais confortável a sala de descanso dos colaboradores | DB30: .
A31: 45687.372 | B31: Concordo Sempre | D31: Concordo Sempre | F31: Concordo Sempre | H31: Concordo Sempre | J31: Concordo Sempre | L31: Concordo Sempre | N31: Concordo Sempre | P31: Concordo | R31: Concordo Sempre | T31: Concordo Sempre | V31: Concordo Sempre | X31: Concordo Sempre | Z31: Concordo Sempre | AB31: Concordo | AD31: Concordo | AF31: Concordo Sempre | AH31: Concordo Sempre | AJ31: Concordo Sempre | AL31: Concordo Sempre | AN31: Concordo Sempre | AP31: Concordo Sempre | AR31: Concordo Sempre | AT31: Concordo Sempre | AV31: Concordo Sempre | AX31: Concordo Sempre | AZ31: Concordo Sempre | BB31: Concordo Sempre | BD31: Concordo Sempre | BF31: Concordo Sempre | BH31: Concordo Sempre | BJ31: Concordo Sempre | BL31: Concordo Sempre | BN31: Concordo Sempre | BP31: Concordo Sempre | BR31: Concordo Sempre | BT31: Discordo Sempre | BV31: Concordo Sempre | BX31: Concordo Sempre | BZ31: Concordo Sempre | CB31: Discordo | CD31: Concordo Sempre | CF31: Concordo Sempre | CH31: Concordo Sempre | CJ31: Concordo Sempre | CL31: Concordo Sempre | CN31: Concordo | CP31: Concordo | CR31: Concordo Sempre | CT31: Concordo | CV31: Concordo Sempre | CW31: Concordo | CX31: Assistência Médica, Assistência Odontológica, Auxílio Combustível, Multibenefícios Alimentação/ Refeição, Kit Baby, Day Off, Auxilio familia. | CY31: Apenas isso | CZ31: Vontade em ajudar principalmente quem é novato, ambiente alto astral promovendo sextou e outras atividades, a facilidade de acesso aos lideres e donos da empresa pois estao sempre disponiveis a conversar. | DA31: Area de descanso maior e mais ventilada, auxilio combustivel pois acredito que 80% dos funcionarios nao usam vale transporte, cantina mais bem equipada com assentos melhores e ventilacao melhor. | DB31: Apenas agradecer pois é uma empresa que faz a diferença e promove um ambiente agradavel de se trabalhar, alem das oportunidades oferecidas buscando crescimento dos proprios funcionarios e nao de quem é de fora.
A32: 45687.376 | B32: Concordo | C32: Não | D32: Concordo | E32: Não | F32: Concordo | G32: Não | H32: Concordo | I32: Não | J32: Concordo | K32: Meus gestores sempre nos auxiliam com nosso crescimento | L32: Concordo | N32: Concordo | P32: Concordo | R32: Concordo | T32: Concordo | U32: É nítido como a empresa abraça o novo funcionário e faz com que tenhamos uma boa recepção | V32: Concordo | W32: Não | X32: Concordo | Y32: Não | Z32: Concordo | AA32: Não | AB32: Concordo Sempre | AC32: Não | AD32: Concordo | AE32: Não | AF32: Concordo | AG32: Não | AH32: Concordo | AI32: Não | AJ32: Concordo | AK32: Não | AL32: Concordo | AM32: Não | AN32: Concordo | AO32: Não | AP32: Concordo | AQ32: Não | AR32: Concordo | AS32: Não | AT32: Concordo | AU32: Não | AV32: Concordo | AW32: Não | AX32: Concordo | AY32: Não | AZ32: Concordo | BA32: Não | BB32: Concordo | BC32: Não | BD32: Concordo | BE32: Não | BF32: Concordo | BG32: Não | BH32: Concordo | BI32: Não | BJ32: Concordo | BK32: Não | BL32: Concordo | BM32: Não | BN32: Concordo | BO32: Não | BP32: Concordo | BQ32: Não | BR32: Concordo | BS32: Não | BT32: Discordo Sempre | BU32: Essa atitude não condiz com a empresa, pelo contrário, todos somos muito bem tratados | BV32: Concordo | BW32: Não | BX32: Concordo | BY32: Não | BZ32: Concordo | CA32: Não | CB32: Discordo | CC32: Não | CD32: Concordo | CE32: Não | CF32: Concordo | CG32: Não | CH32: Concordo | CI32: Não | CJ32: Concordo | CK32: Não | CL32: Concordo | CM32: Não | CN32: Concordo Sempre | CO32: Não | CP32: Discordo Sempre | CQ32: Não | CR32: Concordo | CS32: Não | CT32: Concordo | CU32: Não | CV32: Concordo | CW32: Não | CX32: Assistência Médica, Assistência Odontológica, Auxílio Combustível, Multibenefícios Alimentação/ Refeição, Gympass (Convênio Academias) | CY32: Não | CZ32: 1- Ambiente agradável de se trabalhar 2- Poder sempre contar com a gestão e opinar para melhorias | DA32: 1- Local de descanso 2 - Não ter divisão(anexo), acho que isso acaba separando um pouco os colaboradores | DB32: No geral é uma empresa boa de se trabalhar e vejo o empenho da gestão em tornar a empresa um exemplo
A33: 45687.381 | B33: Concordo | D33: Concordo | F33: Concordo | H33: Concordo | J33: Discordo Sempre | L33: Concordo | N33: Concordo | P33: Concordo | R33: Concordo | T33: Concordo | V33: Concordo | X33: Concordo | Z33: Concordo | AB33: Concordo | AD33: Concordo | AF33: Concordo | AH33: Concordo | AJ33: Concordo | AL33: Concordo | AN33: Concordo | AP33: Concordo | AR33: Concordo | AT33: Concordo | AV33: Concordo | AX33: Concordo | AZ33: Concordo | BB33: Concordo | BD33: Concordo | BF33: Concordo | BH33: Concordo | BJ33: Concordo | BL33: Concordo | BN33: Concordo | BP33: Concordo | BR33: Concordo | BT33: Discordo | BV33: Concordo | BX33: Concordo | BZ33: Concordo | CB33: Discordo | CD33: Concordo | CF33: Concordo | CH33: Concordo | CJ33: Concordo | CL33: Concordo | CN33: Discordo | CP33: Discordo | CR33: Concordo | CT33: Concordo | CV33: Concordo | CW33: Gostaria que melhorase mas nos benefícios | CX33: Auxílio Combustível, Multibenefícios Alimentação/ Refeição, Auxílio Educação, Empréstimo Consignado, Gympass (Convênio Academias) | CY33: Gostaria desses benefícios | CZ33: Transparência salário em dias reconhecimento | DA33: Salário benefício muck | DB33: Gostaria que melhorase nos benefícios
A34: 45687.381 | B34: Concordo | D34: Concordo | F34: Concordo Sempre | H34: Concordo | J34: Discordo | K34: Dentro do período que estou na empresa ainda não teve oportunidade de treinamentos para meu setor. | L34: Concordo | N34: Concordo | P34: Discordo | Q34: Salário está abaixo que o ofertado dentro do mercado de trabalho hoje. | R34: Concordo | T34: Discordo | U34: O se sentir bem-vindo vai além do dizer um “bem-vindo, sucesso!”, ele vai dizer mesmo no dia a dia. E já presenciei momentos em que colaborador novato talvez se sentiu desconfortável com a maneira que estava sendo tratado naquele momento. | V34: Concordo | X34: Concordo | Z34: Concordo | AB34: Concordo | AD34: Concordo | AF34: Concordo | AH34: Concordo | AJ34: Concordo | AL34: Concordo Sempre | AN34: Concordo Sempre | AP34: Concordo | AR34: Concordo Sempre | AT34: Concordo | AV34: Concordo | AX34: Concordo | AZ34: Concordo | BB34: Concordo Sempre | BD34: Concordo Sempre | BF34: Concordo | BH34: Concordo Sempre | BJ34: Concordo | BL34: Concordo | BN34: Concordo | BP34: Concordo | BR34: Concordo | BT34: Discordo | BU34: Nunca presenciei essa atitude do meu líder. | BV34: Concordo | BX34: Concordo | BZ34: Concordo | CB34: Discordo | CC34: Não presenciei até o momento essa atitude. | CD34: Concordo Sempre | CF34: Concordo Sempre | CH34: Concordo | CJ34: Concordo | CL34: Concordo | CN34: Concordo | CP34: Discordo | CQ34: Pelo contrário sinto um clima de ajuda mútua. | CR34: Concordo | CT34: Discordo | CU34: Já fui tratado de forma arrogante em outro setor, na frente de todos que lá estavam. | CV34: Concordo | CW34: Gosto do clima leve do meu setor em trabalhar, a forma como meu líder faz os feedbacks conosco e como a diretoria é acessível a todos os colaboradores. | CX34: Assistência Médica, Auxílio Combustível, Multibenefícios Alimentação/ Refeição, Gympass (Convênio Academias), Day Off | CY34: A porcentagem de desconto do plano de saúde poderia ser negociado para ser menor. | CZ34: Diretoria acessível/oportunidade de crescimento/Clima leve para trabalhar. | DA34: Benefício de plano de saúde ter um desconto menor em folha de pagamento/Salário competitivo com Mercado/treinamentos específico para cada setor. | DB34: Gosto do clima leve do meu setor em trabalhar, a forma como meu líder faz os feedbacks conosco e como a diretoria é acessível a todos os colaboradores.
A35: 45687.381 | B35: Concordo | D35: Concordo Sempre | F35: Concordo | H35: Concordo | J35: Concordo | L35: Concordo | N35: Discordo | O35: Existem diferentes formas de reconhecimento. Acredito que no meu setor existe o reconhecimento pelo trabalho realizado em forma feedbacks, mas não em forma salarial e ausência metas bem definidas para a obtenção da melhoria. | P35: Concordo | R35: Concordo Sempre | T35: Concordo Sempre | V35: Concordo Sempre | X35: Concordo | Z35: Concordo Sempre | AB35: Concordo | AD35: Concordo | AF35: Concordo | AH35: Concordo Sempre | AJ35: Concordo Sempre | AL35: Concordo Sempre | AN35: Concordo Sempre | AP35: Concordo Sempre | AR35: Concordo Sempre | AT35: Concordo | AV35: Concordo Sempre | AX35: Concordo | AZ35: Concordo Sempre | BB35: Concordo Sempre | BD35: Concordo Sempre | BF35: Concordo Sempre | BH35: Concordo Sempre | BJ35: Concordo | BL35: Concordo Sempre | BN35: Concordo Sempre | BP35: Concordo Sempre | BR35: Concordo Sempre | BT35: Discordo Sempre | BU35: Jamais. | BV35: Concordo | BX35: Concordo | BZ35: Discordo | CA35: Na verdade não existe meta para o meu setor. Mas eventos gerais da empresa são ótimos e inclusivos. | CB35: Discordo | CC35: Não que eu conheça. | CD35: Concordo | CF35: Concordo Sempre | CH35: Concordo Sempre | CJ35: Concordo | CL35: Concordo Sempre | CN35: Concordo | CO35: Existe em toda e qualquer organização. Seja positiva ou negativa. | CP35: Discordo | CQ35: Não há rivalidade. | CR35: Concordo Sempre | CT35: Concordo Sempre | CV35: Concordo Sempre | CW35: Ótimo lugar para se trabalhar. Se tem amor pelo que se faz aqui! | CX35: Assistência Odontológica, Auxílio Combustível, Vale Alimentação, Auxílio Educação, Gympass (Convênio Academias) | CY35: São estes apenas. | CZ35: 1 - Forte qualidade na integração de relacionamento entre todos da empresa (setores etc) e ambiente agradável. 2 - Empresa sempre busca inovação, crescimento e liberdade para o colaborador. 3 - Empresa que tem bons eventos e momentos especiais para colaboradores e para datas importantes pra própria empresa. | DA35: 1 - Criteriosidade e mensuração de entregas dos colaboradores para valorização salarial/promocional. 2 - Estabelecer um plano de carreiras 3 - Mais parcerias educacionais para incentivar formação de seus colaboradores | DB35: Acredito que todos os pontos foram abordados.
A36: 45687.383 | B36: Concordo Sempre | D36: Concordo Sempre | F36: Concordo Sempre | H36: Concordo Sempre | J36: Concordo Sempre | L36: Concordo Sempre | N36: Concordo | P36: Concordo Sempre | R36: Concordo Sempre | T36: Concordo Sempre | V36: Concordo Sempre | X36: Concordo | Z36: Concordo Sempre | AB36: Concordo | AD36: Concordo | AF36: Concordo Sempre | AH36: Concordo | AJ36: Concordo | AL36: Concordo | AN36: Concordo | AP36: Discordo | AR36: Concordo | AT36: Discordo | AV36: Discordo | AX36: Discordo | AZ36: Concordo | BB36: Discordo | BD36: Concordo | BF36: Concordo | BH36: Discordo | BJ36: Discordo | BL36: Concordo | BN36: Discordo | BP36: Discordo | BR36: Concordo Sempre | BT36: Concordo | BV36: Discordo | BX36: Discordo | BZ36: Discordo | CB36: Concordo | CD36: Concordo | CF36: Concordo | CH36: Concordo Sempre | CJ36: Concordo | CL36: Concordo Sempre | CN36: Concordo | CP36: Discordo | CR36: Concordo Sempre | CT36: Concordo Sempre | CV36: Concordo Sempre | CW36: . | CX36: Assistência Médica, Assistência Odontológica, Auxílio Combustível, Vale Alimentação, Auxílio Educação | CY36: . | CZ36: Boa liderança Comprometimento Visão | DA36: . | DB36: .
A37: 45687.383 | B37: Concordo | C37: Poderia melhorar a questão do refeitório, que fica muito próximo ao teto e faz muito calor no momento que seria para relaxar | D37: Discordo | E37: É necessário um fardamento mais adequado para todos. A qualidade da blusa é um pouco inferior, e acaba desbotando e ficando com bolinhas muito rápido. Mesmo sendo lavada à mão. Cadeiras apropriadas que não prejudiquem a coluna. | F37: Concordo | H37: Concordo | J37: Discordo | K37: Precisa ser criado uma pauta de treinamento para novos integrantes, para que eles não se sintam perdidos e facilite esse processo de integração. De repente criar uma “universidade” virtual da própria Nordeste com treinamentos exclusivos para os funcionários, de acordo com o seu cargo | L37: Concordo | M37: Nosso gerente sempre conversa sobre as perspectivas de crescimento da empresa, nos trazendo uma visão mais clara do negócio | N37: Concordo | P37: Discordo | Q37: Com uma breve pesquisa, consegue-se mensurar a diferença de salário e de benefícios. Empresas ofertam vale alimentação acima do nosso. Possuem vale cultura, gympass, entre outros | R37: Concordo | T37: Concordo | V37: Concordo | X37: Concordo | Z37: Concordo | AB37: Discordo | AC37: Será interessante a implantação de um canal exclusivo, onde possamos falar diretamente com um psicólogo, por exemplo. E fazer as sugestões e reivindicações necessárias | AD37: Concordo | AF37: Concordo | AH37: Concordo | AJ37: Concordo | AK37: Sempre faz feedbacks nos direcionando da melhor forma | AL37: Concordo | AM37: Nos encoraja sempre q darmos o nosso melhor, para que coincida nosso crescimento profissional com o da empresa | AN37: Concordo | AP37: Concordo | AQ37: Em momentos que estamos com algum tipo de dificuldade na vida pessoal, seja por saúde ou não, ele sempre busca entender sobre oq estamos passando | AR37: Concordo Sempre | AT37: Concordo Sempre | AV37: Concordo | AX37: Concordo | AZ37: Concordo Sempre | BB37: Concordo Sempre | BD37: Concordo | BF37: Concordo | BH37: Concordo | BJ37: Concordo | BL37: Concordo | BN37: Concordo | BP37: Concordo | BR37: Concordo | BT37: Discordo Sempre | BU37: Nunca existiu essa situação | BV37: Concordo | BX37: Concordo | BZ37: Concordo Sempre | CB37: Discordo | CC37: Nosso gestor não aprova esse tipo de prática e corta qualquer possibilidade da mesma | CD37: Concordo | CF37: Concordo | CH37: Concordo | CJ37: Concordo | CL37: Concordo | CN37: Discordo | CP37: Discordo Sempre | CQ37: Sempre estamos nos ajustando, pois sabemos que o bom trabalho do outro não irá afetar nosso desempenho e reconhecimento | CR37: Concordo | CT37: Concordo | CV37: Concordo | CW37: Concordo, porém precisa avaliar as melhorias citadas | CX37: Assistência Médica, Auxílio Combustível, Multibenefícios Alimentação/ Refeição, Empréstimo Consignado, Day Off | CY37: São benefícios que deveriam ser implementados | CZ37: Transparecia Comprometimento Reconhecimento | DA37: • Pontualidade nos pagamentos • Revisão na forma de pagamento de bônus e comissões, mesmo no atingimento de todas as metas individuais, não é recebido quando o geral não é batido • Melhorar a gestão de pessoas de modo geral, por parte dos gestores da matriz | DB37: De modo geral é uma empresa boa de trabalhar. Me sinto confortável e feliz. Porém precisa ser revisado com carinho todos os pontos aqui citados, pois nos afeta e pode acabar criando um ambiente pesado
A38: 45687.387 | B38: Concordo | D38: Concordo | F38: Concordo | H38: Concordo Sempre | J38: Discordo | K38: Deveria ter um suporte de treinamento, tanto para os colaboradores quanto para as pessoas que entram na empresa. | L38: Concordo | N38: Concordo | P38: Discordo | R38: Concordo | T38: Concordo Sempre | U38: Todos recebem bem e ajuda no que pode. | V38: Concordo | X38: Concordo | Y38: Mas as segundas feiras é complicado. | Z38: Concordo | AB38: Discordo | AC38: Deveria melhorar mais os meios de comunicação, poderia ter uma opção de psicólogo para quando tivermos cansados mentalmente poder desabafar, conversar. Ou um canal para ouvir nossas sugestões, ideias ou críticas. | AD38: Concordo | AF38: Concordo | AH38: Concordo | AJ38: Concordo | AL38: Concordo | AM38: É uma pessoa que se dedica e se preocupa ao máximo com os negócios, busca melhorias e soluciona problemas. | AN38: Concordo Sempre | AP38: Concordo | AR38: Concordo Sempre | AS38: É uma pessoa que está sempre aberta para ouvir e conversar. | AT38: Concordo | AV38: Concordo | AX38: Concordo | AZ38: Concordo | BA38: Ele nos mantém sempre informados e atualizados. | BB38: Concordo | BD38: Concordo | BF38: Concordo | BH38: Concordo | BJ38: Concordo | BL38: Concordo | BN38: Concordo | BP38: Concordo | BQ38: Ele sempre fala dos pontos que devemos melhorar, nos elogia e aconselha a fazer sempre um curso para nos especializar mais. | BR38: Concordo | BT38: Discordo | BU38: É uma pessoa super gente boa e sempre trata os seus colaboradores bem como se fosse seus filhos. | BV38: Concordo | BX38: Concordo | BZ38: Concordo | CB38: Discordo | CD38: Discordo | CE38: É difícil ter uma comunicação com eles. | CF38: Discordo | CG38: São umas pessoas super legais, porém não tivemos muito contato. | CH38: Concordo | CJ38: Concordo | CL38: Concordo | CN38: Discordo | CO38: Aqui, o ambiente é bem profissional, e não temos espaço para fofocas. | CP38: Discordo | CQ38: Na verdade, a gente foca em crescer juntos. Não vejo rivalidade entre ninguém, todo mundo se apoia. | CR38: Concordo | CT38: Discordo | CU38: Tem algumas pessoas que são bem fechadas. | CV38: Concordo | CW38: A empresa proporciona um ambiente de trabalho positivo, com uma cultura colaborativa, oportunidades de crescimento e respeito pelos funcionários. É um ótimo lugar para desenvolver a carreira. | CX38: Assistência Médica, Multibenefícios Alimentação/ Refeição, Seguro de Vida, Gympass (Convênio Academias), Day Off | CY38: . | CZ38: 1- A qualidade dos nossos produtos e serviços 2- Valorização dos funcionários 3- Transparência | DA38: 1- deveria melhorar mais na questão do salário, cair na data certa ( se dia 15 ou 31 cair sábado e domingo), o salário deve cair na sexta feira e pela manhã, o salário cai muito tarde, poderia ser agendado para cair na data certa e pela manhã. 2- Ter um suporte de treinamento 3- deveria ter um curso voltado para cada área da empresa para os colaboradores se especializar mais. | DB38: .
A39: 45687.391 | B39: Concordo | C39: Não. | D39: Concordo Sempre | E39: Não. | F39: Concordo | G39: Não. | H39: Concordo Sempre | I39: Não. | J39: Concordo | K39: Não. | L39: Discordo | M39: O objetivo da empresa é crescer e expandir, mas como será feito isso, não se sabe, nem quando que se pretende ser tomado os passos para esse objetivo. Falta transparência neste quesito, além de não haver um melhor preparo da equipe pra receber as novas atribuições e atividades, prejudicando os processos atuais. | N39: Concordo | O39: Poderia ser melhor. Pouco acontece, mas acontece. | P39: Concordo | Q39: Está na média. | R39: Discordo | S39: A empresa em si não incentiva a produção do melhor trabalho possível, não existem metas ou recompensas a serem alcançadas. Todo o sentido vem do crescimento individual como profissional para encontrar melhores oportunidades no futuro. | T39: Concordo Sempre | U39: É um ponto forte da Nordeste. | V39: Concordo | W39: Não. | X39: Discordo | Y39: Obrigações individuais de cada colaborador. Mesmo contexto da resposta 9. | Z39: Concordo Sempre | AA39: Não. | AB39: Discordo Sempre | AC39: Desconheço. | AD39: Discordo | AE39: Independente do que se acredita, se houver necessidade, irá ocorrer. | AF39: Discordo Sempre | AG39: Não acontece. | AH39: Concordo Sempre | AI39: Não. | AJ39: Concordo Sempre | AK39: Não. | AL39: Concordo Sempre | AM39: Não. | AN39: Concordo Sempre | AO39: Não. | AP39: Concordo Sempre | AQ39: Não. | AR39: Concordo Sempre | AS39: Não. | AT39: Concordo | AU39: Não. | AV39: Concordo | AW39: Não. | AX39: Concordo Sempre | AY39: Não. | AZ39: Discordo | BA39: Poderia ser melhor. | BB39: Concordo | BC39: Provavelmente deve ter, essa visão não é repassada. | BD39: Concordo Sempre | BE39: Não. | BF39: Concordo Sempre | BG39: Não. | BH39: Concordo Sempre | BI39: Não. | BJ39: Concordo | BK39: Devido os recentes cortes, isso ainda está em processo de melhoria. | BL39: Concordo Sempre | BM39: Não. | BN39: Concordo Sempre | BO39: Não. | BP39: Concordo | BQ39: Não. | BR39: Concordo Sempre | BS39: Não. | BT39: Discordo Sempre | BU39: Nunca ocorreu, nem presenciei. | BV39: Concordo | BW39: Não. | BX39: Concordo | BY39: Poderia ser melhor. | BZ39: Discordo | CA39: As metas foram extintas, por tanto sem comemoração. Eventos especiais sim, todos comemorados, muito bom trabalho por sinal. | CB39: Discordo Sempre | CC39: Não acontece. | CD39: Concordo | CE39: Não. | CF39: Concordo | CG39: Não. | CH39: Concordo Sempre | CI39: Não. | CJ39: Discordo | CK39: Tratamento é sempre cordial, mas não observo as afirmações acima citadas. | CL39: Concordo Sempre | CM39: Não. | CN39: Concordo Sempre | CO39: Não. | CP39: Discordo Sempre | CQ39: Não observei ainda. | CR39: Discordo | CS39: Apenas se ocorrer oportunidades de crescimento, no momento que perceber que já obtive todo o aprendizado e experiência, devo buscar melhores oportunidades. | CT39: Concordo Sempre | CU39: Não. | CV39: Discordo | CW39: É um bom lugar para se trabalhar, sem dúvidas. | CX39: Assistência Médica, Assistência Odontológica, Auxílio Combustível, Vale Alimentação, Auxílio Educação | CY39: Não. | CZ39: Gestão de pessoas, Endomarketing, Liderança assertiva. | DA39: Implementação do vale combustível, mais transparência com os rumos da empresa, oportunidades de crescimento. | DB39: Os pontos abordados foram satisfatórios.
A40: 45687.392 | B40: Concordo | D40: Concordo | F40: Concordo Sempre | H40: Concordo | J40: Concordo Sempre | L40: Concordo | N40: Concordo | P40: Concordo Sempre | R40: Concordo Sempre | T40: Concordo Sempre | V40: Concordo Sempre | X40: Discordo | Z40: Discordo | AB40: Concordo | AD40: Concordo | AF40: Discordo | AG40: Preciso de um suporte | AH40: Concordo | AJ40: Discordo | AK40: Ele q seu trabalho sai 100% | AL40: Concordo | AN40: Concordo | AP40: Concordo Sempre | AR40: Concordo Sempre | AT40: Concordo Sempre | AV40: Concordo Sempre | AX40: Concordo | AZ40: Concordo | BB40: Concordo | BD40: Discordo | BE40: Ele deixa as pessoas avontade | BF40: Concordo | BH40: Concordo | BJ40: Concordo | BL40: Concordo | BN40: Concordo Sempre | BP40: Concordo | BR40: Concordo | BT40: Discordo | BU40: Nunca | BV40: Discordo | BW40: Aqui são todos unidos | BX40: Concordo Sempre | BZ40: Concordo Sempre | CB40: Concordo | CD40: Concordo | CF40: Concordo | CH40: Concordo Sempre | CJ40: Concordo | CL40: Discordo | CM40: Um lugar muito bom para trabalhar | CN40: Discordo | CO40: Não enzite na empresa | CP40: Concordo | CR40: Concordo Sempre | CT40: Concordo Sempre | CV40: Concordo | CW40: Um salário sair pela manhã | CX40: Assistência Médica, Auxílio Combustível, Vale Refeição, Vale Alimentação, Auxílio Educação, Cesta Básica, Seguro de Vida, Kit Baby | CY40: Salário sair pela manhã | CZ40: Bom lugar para trabalhar | DA40: Ter um técnico de segurança na empresa | DB40: Precisa ter um fardamento
A41: 45687.392 | B41: Concordo | D41: Concordo | F41: Concordo | H41: Concordo | J41: Concordo | L41: Concordo | N41: Concordo | P41: Concordo | R41: Concordo | T41: Concordo | V41: Concordo | X41: Concordo | Z41: Concordo | AB41: Concordo | AD41: Concordo | AF41: Concordo | AH41: Concordo | AJ41: Concordo | AL41: Concordo | AN41: Concordo | AP41: Concordo | AR41: Concordo | AT41: Concordo | AV41: Concordo | AX41: Concordo | AZ41: Concordo | BB41: Concordo | BD41: Concordo | BF41: Concordo | BH41: Concordo | BJ41: Concordo | BL41: Concordo | BN41: Concordo | BP41: Concordo | BR41: Concordo | BT41: Discordo Sempre | BU41: Nunca | BV41: Concordo | BX41: Concordo | BZ41: Concordo | CB41: Concordo | CD41: Concordo | CF41: Concordo | CH41: Concordo | CJ41: Concordo | CL41: Concordo | CN41: Concordo | CP41: Concordo | CR41: Concordo | CT41: Concordo | CV41: Concordo | CW41: Sou feliz de trabalhar na nordeste locação | CX41: Convênio com Livrarias, Auxílio Combustível, Vale Refeição, Multibenefícios Alimentação/ Refeição, Auxílio Educação | CY41: Gosto de fazer o meu trabalho | CZ41: Alimentação o aumento de salário e os benefícios | DA41: Pra mim está bom assim | DB41: Precisa melhora o horário de pagamento cai de manhã e quando for dia 15 for cai no sábado ou dormindo paga sempre dia 14 uma sexta feira
A42: 45687.393 | B42: Concordo | D42: Concordo | F42: Concordo | H42: Concordo | J42: Concordo | L42: Concordo | N42: Discordo | O42: O salário não condiz com a quantidade de função que o funcionário exerce. | P42: Discordo | Q42: O salário não condiz com a quantidade de função que o funcionário exerce.. | R42: Concordo | T42: Concordo Sempre | V42: Concordo | W42: Concordo em partes, acredito que já tenham suas equipes “panelas” e meio que forçam os demais a se enquadrar pra ser aceito. | X42: Discordo | Y42: Depende muito do setor, vejo pessoas descontente, dizendo que “quero ser demitido pra não perder meus direitos”, porém acho mais justo falar com o gestor e ver o que pode ser feito, afinal vai da a vaga pra quem precisa, e a pessoa em si poderá ir a procura de algo que lhe deixará feliz. | Z42: Concordo | AB42: Discordo | AC42: O canal que temos é falar diretamente com o RH, porém nem sempre é colocado em prática novas ideias. | AD42: Concordo | AF42: Concordo | AG42: Em partes concordo. | AH42: Concordo | AJ42: Concordo | AL42: Concordo | AN42: Concordo | AP42: Concordo | AR42: Concordo | AT42: Concordo | AV42: Concordo | AX42: Concordo | AZ42: Concordo | BB42: Concordo | BD42: Discordo | BF42: Discordo | BH42: Discordo | BJ42: Concordo | BL42: Concordo | BN42: Concordo | BP42: Concordo | BR42: Concordo | BT42: Discordo | BV42: Concordo | BX42: Concordo | BZ42: Concordo | CB42: Concordo Sempre | CD42: Discordo | CF42: Concordo | CH42: Concordo | CJ42: Discordo | CL42: Concordo | CN42: Concordo Sempre | CP42: Concordo Sempre | CR42: Concordo | CT42: Concordo | CV42: Concordo | CW42: . | CX42: Assistência Médica, Auxílio Combustível, Multibenefícios Alimentação/ Refeição, Cesta Básica, Gympass (Convênio Academias) | CY42: Acredito que mais de 80% da empresa vem de transporte próprio e não tem um auxílio combustível, pois estamos pagando pra vim trabalhar… Não tem necessidade de ser um valor exorbitante, mas um valor pra “auxiliar” nesse gasto.. melhoraria demais o clima da empresa pois todos já informam o interesse, mas deixam de passar a ideia pq segundo os mesmos “RH é diretoria não vai fazer.. | CZ42: Plano de saúde (poderia melhorar a porcentagem pra empresa). Vale alimentação muito bom, ajuda em casa, e o adiantamento. | DA42: Oportunidades de crescimento, cursos pra uma possível mudança de função, ter a função híbrido.. já trabalhamos com notebook, tem inúmeros trabalhos que daria certo na função híbrido. | DB42: Oportunidades de crescimento, cursos pra uma possível mudança de função, ter a função híbrido.. já trabalhamos com notebook, tem inúmeros trabalhos que daria certo na função híbrido.
A43: 45687.398 | B43: Concordo | D43: Concordo Sempre | F43: Concordo Sempre | H43: Concordo Sempre | J43: Concordo | L43: Concordo Sempre | N43: Concordo Sempre | P43: Concordo | R43: Concordo | T43: Concordo | V43: Concordo | X43: Concordo | Z43: Concordo | AB43: Concordo | AD43: Concordo | AF43: Concordo | AH43: Concordo | AJ43: Concordo | AL43: Concordo | AN43: Concordo | AP43: Concordo | AR43: Concordo | AT43: Concordo | AV43: Concordo | AX43: Concordo | AZ43: Concordo | BB43: Concordo | BD43: Concordo | BF43: Concordo | BH43: Concordo | BJ43: Concordo | BL43: Concordo | BN43: Concordo | BP43: Concordo | BR43: Concordo | BT43: Concordo | BV43: Concordo | BX43: Concordo | BZ43: Concordo | CB43: Discordo | CD43: Concordo | CF43: Concordo | CH43: Concordo | CJ43: Concordo | CL43: Concordo | CN43: Discordo Sempre | CP43: Discordo Sempre | CR43: Concordo | CT43: Concordo | CV43: Concordo | CW43: . | CX43: Assistência Médica, Auxílio Combustível, Multibenefícios Alimentação/ Refeição, Cesta Básica, Gympass (Convênio Academias) | CY43: . | CZ43: Reconhecimento, Respeito, Senso de Justiça | DA43: N/A | DB43: N/A
A44: 45687.406 | B44: Concordo | C44: Ambiente que proporciona crescimento | D44: Concordo | E44: Internet apresentando sinal baixo ultimamente | F44: Concordo Sempre | H44: Concordo Sempre | J44: Concordo Sempre | L44: Concordo Sempre | N44: Concordo Sempre | P44: Concordo Sempre | R44: Concordo Sempre | S44: Tenho um cenário de amplo aprendizado diário. | T44: Concordo Sempre | V44: Concordo Sempre | W44: Sim pra mim é uma empresa que todos os dias venho com muita vontade para trabalhar. | X44: Concordo | Z44: Concordo Sempre | AB44: Concordo Sempre | AD44: Concordo Sempre | AF44: Concordo Sempre | AH44: Concordo Sempre | AJ44: Concordo Sempre | AK44: Sempre com diálogo transparente. | AL44: Concordo Sempre | AN44: Concordo Sempre | AP44: Concordo Sempre | AR44: Concordo Sempre | AT44: Concordo Sempre | AV44: Concordo Sempre | AX44: Concordo Sempre | AZ44: Concordo Sempre | BB44: Concordo Sempre | BD44: Concordo Sempre | BF44: Discordo | BH44: Concordo Sempre | BJ44: Concordo Sempre | BL44: Concordo Sempre | BN44: Concordo Sempre | BP44: Concordo Sempre | BQ44: Sim . Em cada reunião. | BR44: Concordo Sempre | BS44: Ambiente saudável. | BT44: Discordo Sempre | BU44: Sempre.tratada de forma polida pelo meu líder. Mas com outros de outros setores não, já tive situações ruins. | BV44: Concordo | BX44: Concordo Sempre | BZ44: Concordo Sempre | CB44: Discordo Sempre | CD44: Concordo Sempre | CF44: Concordo Sempre | CH44: Concordo Sempre | CJ44: Concordo Sempre | CL44: Concordo Sempre | CN44: Concordo | CO44: Sim , mas acredito que chegando em mim não promovo apenas encerro o fluxo. | CP44: Discordo | CR44: Concordo Sempre | CS44: Acredito que tenho muito a somar e me identifico com a empresa. | CT44: Concordo Sempre | CV44: Concordo Sempre | CW44: Disponibiliza visão de crescimento | CX44: Assistência Médica, Assistência Odontológica, Convênio com Livrarias, Vale Alimentação, Gympass (Convênio Academias) | CY44: Convênio de Academias iria melhorar na saúde e condicionamento. | CZ44: Trabalho em equipe, Atendimento, Resolução nos problemas. | DA44: Comunicação, Fluxo de informações nos e-mails. | DB44: Acredito que nosso trabalho é forte e só tem a cresce.
A45: 45687.407 | B45: Concordo | C45: Mesmo com as adversidades do dia a dia é tão difícil e lidar com o humor das pessoas em momentos o ambiente é agradável | D45: Concordo | F45: Discordo | G45: A vezes sim outras pessoas nem tanto | H45: Concordo | J45: Concordo | L45: Concordo | N45: Concordo | P45: Discordo | Q45: Vejo que tem empresas que remuneram muito mais | R45: Concordo Sempre | S45: Gosto do que faço | T45: Concordo | V45: Concordo Sempre | X45: Concordo | Z45: Concordo | AB45: Discordo Sempre | AC45: Não existe uma ouvidoria | AD45: Concordo | AF45: Concordo | AH45: Concordo | AJ45: Concordo | AL45: Concordo | AN45: Concordo | AP45: Concordo | AR45: Concordo | AT45: Discordo | AU45: As vezes sim as vezes não somente feedbacks | AV45: Concordo | AX45: Concordo | AZ45: Concordo | BB45: Concordo | BD45: Concordo | BF45: Concordo | BH45: Discordo | BJ45: Discordo | BK45: Distribuir tarefas mas coordenar acho que falta mais treinamento para seu desenvolvimento | BL45: Concordo | BN45: Discordo | BP45: Concordo | BR45: Concordo | BT45: Discordo Sempre | BV45: Discordo | BW45: As vezes sim as vezes não | BX45: Concordo | BZ45: Concordo Sempre | CB45: Concordo | CD45: Concordo Sempre | CF45: Concordo Sempre | CH45: Concordo Sempre | CJ45: Concordo | CL45: Concordo | CN45: Concordo Sempre | CP45: Concordo | CR45: Concordo | CT45: Concordo | CV45: Concordo | CW45: É um ambiente os dos diretores tentam deixar descontraído | CX45: Assistência Médica, Multibenefícios Alimentação/ Refeição, Auxílio Educação, Empréstimo Consignado, Gympass (Convênio Academias), Day Off | CY45: Não | CZ45: Pagamento em dia Acesso fácil a diretoria Ambiente em geral festivo e alegre | DA45: Realizar a sala de espera dos cliente Realizar um ambiente mais amplo para sala de descanso e mais confortável Unir a matriz em um ambiente único para que todos os setores se relacionarem | DB45: Sugestões é realizar mais treinamento para a liderança de comportamentos e liderança e comunicar e controle emocional E realizar o pagamento pela parte da manhã e não no fim do expediente
A46: 45687.407 | B46: Discordo | D46: Discordo Sempre | F46: Discordo | H46: Concordo | J46: Discordo Sempre | L46: Discordo | M46: N tem sentido a pergunta …. | N46: Discordo | P46: Discordo | R46: Concordo | T46: Concordo | V46: Concordo | X46: Discordo | Z46: Discordo | AA46: N faz sentido a pergunta | AB46: Discordo Sempre | AD46: Discordo | AE46: N faz sentido a pergunta | AF46: Discordo | AG46: N faz sentido | AH46: Concordo | AJ46: Concordo | AL46: Discordo | AM46: A pergunta n faz sentido | AN46: Discordo | AO46: A pergunta n faz sentido | AP46: Discordo | AQ46: N faz sentido a pergunta | AR46: Concordo | AS46: Fácil mas eles n resolve muita coisa | AT46: Discordo | AU46: Meu líder o supervisor precisa ser treinador na que trabalhamos | AV46: Discordo | AX46: Discordo Sempre | AY46: Líder e supervisor esculta nossas ideias porém nunca vi tomar nenhuma atitude pra que as ideias de melhor aconteça | AZ46: Concordo | BB46: Discordo | BC46: A pergunta n faz sentido | BD46: Discordo | BE46: Na minha área eles sempre tem dúvidas pq ele não entende muito, ocupa o cargo de líder e supervisão só por conta do currículo somente … | BF46: Discordo | BG46: Cobra muito ,, e da parte do líder e supervisão n entrega nada . | BH46: Discordo | BI46: Quem tem cargo maior eles fazem vista grossa, | BJ46: Discordo | BL46: Discordo | BN46: Discordo | BO46: Fala muito e n entrega nada | BP46: Concordo | BR46: Concordo | BT46: Discordo | BV46: Concordo | BX46: Concordo | BZ46: Discordo | CB46: Discordo | CD46: Concordo | CF46: Concordo | CH46: Concordo | CJ46: Discordo | CL46: Concordo | CN46: Concordo | CP46: Discordo | CR46: Discordo | CS46: A pergunta n faz sentido | CT46: Concordo | CV46: Discordo | CW46: A pergunta tem a palavra ,,excelente ,,a empresa n é a melhor, mas n é a pior , excelente poxa também é demais, e meio termo | CX46: Assistência Médica, Auxílio Combustível, Multibenefícios Alimentação/ Refeição, Cesta Básica, Seguro de Vida | CY46: … | CZ46: N faz sentido a pergunta | DA46: Plano de saúde 100% , seguro de vida , vale combustível. | DB46: Pesquisa de clima é sério deveria ser feito por uma auditoria especializada. E n por um colaborador da empresa.
A47: 45687.41 | B47: Concordo | C47: Gosto muito de trabalhar na empresa, sempre temos que melhorar, mas acredito que estamos caminhando para essa evolução. | D47: Concordo Sempre | F47: Concordo Sempre | H47: Concordo | I47: O coletivo é muito importante, mas nem sempre é unanimidade no caso de suporte e de ajuda, porém na sua grande maioria sim. | J47: Concordo | K47: Gostaria de ver mais sobre cursos e workshops de assuntos relacionados ao meio corporativo, liderança e criação. | L47: Discordo | M47: Algumas mudanças não ficam muito claras e recebemos algumas decisões bem por cima, sem explicar melhor o todo. Como por exemplo a mudança do sindicato e o que isso vai impactar no processo atual de segurança do trabalhador. | N47: Concordo | O47: Às vezes sim e não, algumas questões e ações ficam sem receber o mérito que deveria. | P47: Concordo | Q47: Não sei ao certo como é o pagamento nas concorrentes, porém na minha área não existe um plano claro de carreira, gostaria de ver isso ser bem mais visto e avaliado. | R47: Concordo Sempre | S47: Sim, amo minha profissão e visto a camisa da empresa, estou disposto a mostrar todo o meu conhecimento para o crescimento. | T47: Concordo Sempre | U47: Sempre vejo isso, pelo menos na minha sala e comigo mesmo. | V47: Concordo | W47: Em sua maioria, pessoas de humildades, que sempre querem estar dispostas a ajudar. | X47: Concordo | Y47: Na maioria sim, ouço muito alguns relatos de pessoas que gostam de trabalhar sim aqui, alguns poucos reclamam. | Z47: Concordo Sempre | AB47: Discordo | AC47: Gostaria de ver um canal mais claro de comunicação, como um sac, caixa de opiniões e tal. Porém precisamos confiar para onde essa mensagem vai e se ela vai ser vista e avaliada. | AD47: Concordo | AF47: Concordo | AG47: É complicado essa pergunta, acho muito interessante uma vida saudável quando conseguimos ter um tempo para tudo, o trabalho de 8h diários é uma grande parcela do dia, acho interessante o híbrido para algumas áreas. | AH47: Concordo Sempre | AJ47: Concordo | AL47: Concordo Sempre | AN47: Concordo | AP47: Concordo Sempre | AR47: Concordo Sempre | AT47: Concordo | AU47: Poderia haver mais isso, eu concordo até certo ponto. Gostaria de ter mais possibilidades de crescimento e mostrar mais detalhes de como pode ser feita o crescimento. | AV47: Concordo | AW47: Sempre é válido, o erro faz parte do crescimento, o importante é não se repetir. | AX47: Concordo Sempre | AZ47: Concordo | BA47: Acho que algumas informações chegam sempre no final, porém seria mais interessante que se as informações estiverem e for no caso precisar do setor interessante ser avisado com antecedência. | BB47: Concordo | BC47: Acho que tem uma visão sim de onde chegar, porém a clareza em si pra mim não está muito planejada. | BD47: Concordo | BF47: Concordo | BG47: Sempre está disponível e quer saber sempre mais sobre tudo que acontece. | BH47: Discordo | BI47: Acredito que exista sim os favoritos, contratação de familiares, escutas e visões vindas de pessoas que estão mais tempo, mas em sua maioria atualmente eu vejo mudanças nesse caso, já passei por situações que vi um ficar do lado sem realmente saber o contexto da situação e no caso como presenciei vi que estavam totalmente equivocados e por esse favoritismo a pessoa ganhou o caso ao meu ver na dita confiança que eles tinham. | BJ47: Concordo | BL47: Concordo Sempre | BN47: Concordo | BP47: Concordo | BR47: Concordo | BS47: Sem muitos pontos sobre esse tema, estamos em um meio e em uma fase que temos que reeducar ou até mesmo ajudar e dá suporte para alguns sobre esses casos, já ouvi falas e comentários inadequados, porém para melhorar ainda mais, acredito que palestras, momentos de falas e trocas seria interessante. | BT47: Concordo | BU47: Já fui humilhado pelo antigo diretor, em uma das reuniões que estive com ele, o mesmo bateu no peito e disse que quem mandava era ele e eu estava aqui porque ele queria e que eu ficasse quieto, pensei em sair da empresa naquele momento, mas eu respirei e como estava na sala com outras pessoas não quis alarmar e nem seguir na ignorância. Na atual gestão no começo acho que pela imatura presenciei alguns momentos que me deixaram meio perdidos de oscilações de humor, mas nada de extremismo, acho que mesmo para o crescimento profissional e corporativo. | BV47: Concordo Sempre | BX47: Concordo Sempre | BZ47: Concordo Sempre | CA47: Hoje sim! | CB47: Concordo | CC47: Algumas pessoas sim, deixam de falar o que acham e se deixam levar pelo medo e pela babação. | CD47: Concordo Sempre | CF47: Concordo Sempre | CH47: Concordo Sempre | CJ47: Concordo | CK47: Gostaria de ser mais valorizado, não só como promoção, mas com um contexto geral. | CL47: Concordo Sempre | CN47: Concordo | CO47: E onde não têm, hehe. Mas no caso temos algumas pessoas em particular que circulam em muitos ambientes que realmente são conhecidas como fofoqueiras e energias pesadas. | CP47: Discordo | CR47: Concordo | CS47: Sim, sendo bem valorizado e em um cargo de comum acordo que exerço. | CT47: Concordo | CU47: Gostaria de ver mais integrações principalmente com o anexo e com outros setores. | CV47: Concordo | CW47: Sim, ambiente muito bom. | CX47: Assistência Médica, Assistência Odontológica, Convênio com Livrarias, Celular, Vale Refeição, Vale Alimentação, Multibenefícios Alimentação/ Refeição, Auxílio Educação, Cesta Básica, Seguro de Vida, Gympass (Convênio Academias), Day Off, Híbrido | CY47: Mais benefícios como psicologia, massoterapeuta... | CZ47: Bom relacionamento interpessoal, visão de futuro e planejamento. | DA47: Planos de cargos e carreira, segurança em geral, recepção. | DB47: Agradecer por nós ouvir.
A48: 45687.415 | B48: Concordo Sempre | D48: Concordo Sempre | F48: Discordo | H48: Concordo Sempre | J48: Concordo | L48: Concordo | N48: Discordo Sempre | P48: Discordo | R48: Concordo Sempre | T48: Concordo Sempre | V48: Concordo Sempre | X48: Concordo | Z48: Concordo Sempre | AB48: Discordo Sempre | AD48: Concordo Sempre | AF48: Concordo Sempre | AH48: Concordo Sempre | AJ48: Concordo | AL48: Concordo Sempre | AN48: Concordo Sempre | AP48: Concordo | AR48: Discordo | AT48: Concordo Sempre | AV48: Concordo | AX48: Concordo | AZ48: Concordo | BB48: Concordo | BD48: Discordo Sempre | BF48: Concordo | BH48: Discordo | BJ48: Concordo | BL48: Concordo | BN48: Concordo | BP48: Concordo Sempre | BR48: Concordo Sempre | BT48: Discordo | BV48: Concordo | BX48: Concordo | BZ48: Discordo | CB48: Concordo | CD48: Concordo | CF48: Concordo Sempre | CH48: Concordo Sempre | CJ48: Concordo Sempre | CL48: Concordo Sempre | CN48: Concordo Sempre | CP48: Concordo | CR48: Concordo Sempre | CT48: Concordo | CV48: Concordo Sempre | CX48: Assistência Médica, Assistência Odontológica, Multibenefícios Alimentação/ Refeição, Gympass (Convênio Academias), Day Off | CZ48: Diretoria qualificada e engajada, empresa em expansão e oportunidades reais de crescimento profissional | DA48: Melhorar a comunicação interna, otimizar processos e implementar um programa de desenvolvimento de equipes. | DB48: Percebo que a gestão está buscando unir todas as áreas e integrar os colaboradores como parte de uma única empresa. No entanto, ainda vejo a necessidade de um esforço maior nesse ponto, pois algumas áreas sentem uma carga de cobrança maior do que outras. Além disso, a forma como as falhas são apontadas parece ter um peso diferente entre as áreas.
A49: 45687.416 | B49: Concordo | C49: Concordo porém existem pontos de Infraestrutura a melhorar/redimensionar, como banheiros, vestiários e sala de descanso. | D49: Concordo Sempre | E49: Sempre recebi todos recursos necessários e quando não tinha, foi providenciando conforme necessidade. | F49: Concordo | G49: Na maior parte das pessoas sim. | H49: Concordo Sempre | I49: A missão da empresa é bem difundida e sempre estamos com vontade genuína de impactar positivamente o dia daqueles que se relacionam conosco. | J49: Discordo | K49: Existiu alguns pequenos projetos de treinamentos e desenvolvimento, porém foram pontuais. | L49: Concordo Sempre | N49: Concordo Sempre | O49: Isso é visível no alto número de promoções e divulgação de destaques. | P49: Concordo | Q49: Ne media sim | R49: Concordo Sempre | S49: Além de ter um clima bom, fazer parceiros de trabalho o poder impactar diversas pessoas é essencial para o negócio | T49: Concordo Sempre | U49: Sempre temos colaboração | V49: Concordo Sempre | X49: Concordo Sempre | Z49: Concordo | AB49: Discordo | AC49: Esses canais ate existem mas não sao bem definidos ou não utilizados da maneira mais efetiva | AD49: Concordo Sempre | AE49: Seria apenas se houvesse um momento de crise no mercado | AF49: Concordo | AG49: Há ações para esse equilíbrio, porém é algo que precisa de mais investimentos e ser mais falado por todos os setores, principalmente o operacional | AH49: Concordo Sempre | AJ49: Concordo Sempre | AK49: Temos reuniões semanais de alinhamento | AL49: Concordo Sempre | AN49: Concordo Sempre | AP49: Concordo Sempre | AQ49: Dentro da minha expectativa sim | AR49: Concordo Sempre | AT49: Concordo Sempre | AV49: Concordo Sempre | AX49: Concordo Sempre | AZ49: Concordo Sempre | BB49: Concordo Sempre | BD49: Concordo Sempre | BF49: Concordo | BG49: Na maioria das vezes sim | BH49: Concordo Sempre | BJ49: Concordo Sempre | BL49: Concordo Sempre | BN49: Concordo | BP49: Concordo Sempre | BR49: Concordo | BT49: Discordo Sempre | BV49: Concordo | BX49: Concordo | BZ49: Discordo | CA49: Há um atingimento de meta setoriais que uns comemoram e outro não | CB49: Discordo | CC49: Na maior parte das vezes não e sempre que existe soa como tom de brincadeira | CD49: Concordo Sempre | CF49: Concordo Sempre | CH49: Concordo Sempre | CJ49: Concordo Sempre | CL49: Concordo Sempre | CN49: Concordo | CO49: Existe pouco como em qualquer outro tipo de ambiente, fofocas que não chegam a denigrir ou atingir diretamente a ninguém | CP49: Discordo | CQ49: Em algumas pessoas que por talvez disputarem destaque do mês possa criar um sentimento de rivalidade | CR49: Concordo Sempre | CS49: Tendo o reconhecimento da liderança e a perspectiva de crescimento da empresa e com isso gerar mais oportunidades para mim e para equipe | CT49: Concordo | CV49: Concordo Sempre | CW49: Na soma dos pontos positivos e pontos a melhorar, a empresa se destaca por tempo mais pontos positivos | CX49: Assistência Médica, Auxílio Combustível, Multibenefícios Alimentação/ Refeição, Auxílio Educação, Gympass (Convênio Academias) | CY49: Seriam até mais de 5, porém foram os 5 mais relevantes | CZ49: Valorização das pessoas, ambiente colaborativo e gestão ativa | DA49: Infraestrutura relacionada com o número de pessoas na unidade, investimentos em processos bem definidos e investimentos em treinamentos e capacitações | DB49: Infraesutrura precisa vir acompanhanda do crescimento do número de pessoas e processos da empresa. Investimentos em desenvolvimento profissional é essencial para o alto crescimento da empresa. Investir em processos bem organizado também serão necessários olhando para o cenário de expansao da empresa.
A50: 45687.423 | B50: Concordo | C50: Ambiente sempre limpo e organizado, onde todos colaboradores estão buscando manter o ambiente agradável. | D50: Concordo | F50: Concordo | H50: Concordo | J50: Concordo | L50: Concordo | N50: Concordo | P50: Concordo | R50: Concordo Sempre | S50: Me senti muito bem acolhido na empresa desde o primeiro dia, e o sentido de atender bem as pessoas e ser bem visto pelos clientes pelo nome que a empresa carrega | T50: Concordo Sempre | U50: Como eu me senti muito bem acolhido, todos são muito bem recebido. | V50: Concordo | X50: Concordo Sempre | Z50: Concordo | AB50: Concordo | AD50: Concordo | AE50: Esse recurso é cabível a todo tipo de organização, tendo em vista a saúde financeira das empresas | AF50: Concordo | AH50: Concordo | AJ50: Concordo | AL50: Concordo | AN50: Concordo | AP50: Concordo | AR50: Concordo | AT50: Concordo | AV50: Concordo | AX50: Concordo | AZ50: Concordo | BB50: Concordo | BD50: Concordo | BF50: Concordo | BH50: Concordo | BJ50: Concordo Sempre | BL50: Concordo | BN50: Concordo | BP50: Concordo Sempre | BR50: Concordo | BT50: Discordo Sempre | BV50: Concordo | BX50: Concordo Sempre | BZ50: Concordo Sempre | CB50: Discordo Sempre | CD50: Concordo Sempre | CF50: Concordo | CH50: Concordo | CJ50: Concordo | CL50: Concordo Sempre | CN50: Discordo | CP50: Discordo | CR50: Concordo Sempre | CS50: Aqui fui muito bem recebido, gosto muito do ambiente e do meu trabalho, e a forma de como exerço as minhas tarefas. | CT50: Concordo | CV50: Concordo Sempre | CX50: Assistência Médica, Assistência Odontológica, Auxílio Combustível, Celular, Multibenefícios Alimentação/ Refeição | CZ50: Organização, transparência e foco | DA50: Área de descompressão, banheiros. | DB50: Informar mais uma vez que estou muito feliz em fazer parte dessa empresa, um time , uma organização que está focada em crescer a cada dia.
A51: 45687.427 | B51: Concordo | D51: Concordo | F51: Discordo | G51: Concordo parcialmente, mas creio que algumas pessoas não tem a mesma linha de pensamento. | H51: Concordo | J51: Concordo | L51: Concordo | N51: Concordo Sempre | P51: Concordo | R51: Concordo | T51: Concordo Sempre | V51: Concordo | X51: Concordo | Z51: Concordo Sempre | AB51: Concordo Sempre | AD51: Concordo | AF51: Concordo | AH51: Concordo | AJ51: Concordo Sempre | AL51: Concordo Sempre | AN51: Concordo Sempre | AP51: Concordo Sempre | AR51: Concordo Sempre | AT51: Concordo | AV51: Concordo Sempre | AX51: Concordo | AZ51: Concordo Sempre | BB51: Concordo Sempre | BD51: Concordo | BF51: Concordo | BH51: Concordo | BJ51: Concordo | BL51: Concordo Sempre | BN51: Concordo | BP51: Concordo | BR51: Concordo | BT51: Discordo Sempre | BV51: Concordo | BX51: Concordo | BZ51: Discordo | CA51: Alguns setores comemoram mais que outros setores. | CB51: Discordo Sempre | CD51: Concordo | CF51: Concordo | CH51: Concordo | CJ51: Concordo Sempre | CL51: Concordo | CN51: Concordo Sempre | CO51: Não adianta negar, cada setor tem uma intimidade entre si, entre os colaboradores , então gera algumas fofocas. Fofocas essas que podem ser relacionadas a empresa ou também a assuntos externos. | CP51: Discordo Sempre | CR51: Concordo | CT51: Concordo Sempre | CV51: Concordo | CX51: Assistência Médica, Assistência Odontológica, Auxílio Combustível, Cesta Básica, Seguro de Vida | CZ51: Colaboradores dedicados a ajudar, ambiente de trabalho, salário. | DA51: Organização de layout, Fardamento, horário de almoço. | DB51: Minha sugestão é a implementação se possível de vale combustível.
A52: 45687.434 | B52: Concordo Sempre | D52: Concordo Sempre | F52: Concordo | H52: Concordo Sempre | J52: Concordo | L52: Discordo | M52: Acho que é de suma importância que haja um plano de cargos e carreiras pra ontem. | N52: Discordo | O52: Acho que tem muita gente na empresa que trabalha duro e tem muita identificação com a organização e não é visto. E tem muita gente que mostra total desinteresse pela empresa, e muitas vezes deixa o ambiente conturbado, e é recompensado. | P52: Discordo | Q52: Sei de colaboradores antigos que estão em outras locadoras recebendo salários e benefícios melhores. | R52: Concordo | T52: Concordo Sempre | V52: Concordo | X52: Concordo | Z52: Concordo Sempre | AB52: Concordo | AD52: Concordo | AF52: Concordo | AG52: Concordo, mas acredito que não seja difícil melhorar. | AH52: Concordo Sempre | AJ52: Concordo | AL52: Concordo Sempre | AN52: Concordo Sempre | AP52: Concordo | AQ52: O meu líder eu sei que sim, mas sei de outros que não. | AR52: Concordo Sempre | AT52: Concordo | AU52: O meu sim, mas acho que podemos melhorar muito de maneira geral. | AV52: Concordo | AX52: Concordo Sempre | AZ52: Concordo | BB52: Concordo | BD52: Concordo Sempre | BF52: Discordo | BH52: Discordo | BI52: Acho que algumas pessoas tem algum tipo de preferência. | BJ52: Concordo Sempre | BL52: Concordo Sempre | BN52: Concordo | BP52: Concordo Sempre | BR52: Concordo Sempre | BT52: Discordo Sempre | BV52: Concordo | BW52: Acho que dentro dos setores sim, mas na relação entre setores isso é alterado. | BX52: Concordo | BZ52: Discordo Sempre | CA52: Alguns setores sempre comemoram, outros não. | CB52: Discordo | CC52: Sempre tem, mas na maioria não. | CD52: Concordo Sempre | CF52: Concordo Sempre | CH52: Concordo Sempre | CJ52: Discordo | CK52: Sinto que posso fazer a diferença, mas não me sinto tão valorizado. | CL52: Concordo Sempre | CN52: Concordo Sempre | CP52: Concordo | CR52: Concordo | CT52: Concordo | CV52: Concordo Sempre | CX52: Assistência Médica, Assistência Odontológica, Auxílio Combustível, Multibenefícios Alimentação/ Refeição, Auxílio Educação, Gympass (Convênio Academias) | CY52: Achei necessário marcar 6. | CZ52: Ambiente físico, clima amistoso, liberdade. | DA52: Flexibilidade de horário, reconhecimento, melhores salários | DB52: Acredito que de forma geral a empresa é excelente. Mas para mim poderia melhorar na parte de reconhecimento e salários.
A53: 45687.437 | B53: Concordo | D53: Concordo | F53: Concordo Sempre | H53: Concordo | J53: Concordo Sempre | K53: Os líderes sempre ajudando os colaboradores pra desenvolver no crescimento do fucionario | L53: Concordo | N53: Concordo | P53: Concordo Sempre | R53: Concordo Sempre | T53: Concordo Sempre | U53: Aq quando agente é contratado as pessoas nos tratam muito bem | V53: Concordo | X53: Concordo | Z53: Concordo | AB53: Concordo | AD53: Discordo | AF53: Concordo | AH53: Concordo Sempre | AJ53: Concordo Sempre | AL53: Concordo Sempre | AN53: Concordo Sempre | AP53: Concordo Sempre | AR53: Concordo Sempre | AT53: Concordo Sempre | AV53: Concordo Sempre | AX53: Concordo Sempre | AZ53: Concordo Sempre | BB53: Concordo Sempre | BD53: Concordo Sempre | BF53: Concordo Sempre | BH53: Concordo Sempre | BJ53: Concordo Sempre | BL53: Concordo Sempre | BN53: Concordo Sempre | BP53: Concordo Sempre | BR53: Concordo Sempre | BT53: Discordo Sempre | BV53: Concordo | BX53: Concordo | BZ53: Discordo | CB53: Discordo | CD53: Concordo | CF53: Concordo | CH53: Concordo | CJ53: Concordo | CL53: Concordo | CN53: Concordo | CP53: Concordo | CQ53: Vejo muitas pessoas falando um do outro com rivalidade pra crescer | CR53: Concordo Sempre | CT53: Concordo | CV53: Concordo | CX53: Assistência Médica, Multibenefícios Alimentação/ Refeição, Cesta Básica, Empréstimo Consignado, Vale conbustivel | CZ53: Os líderes muito atencioso ambientes bom pra trabalhar | DA53: Banheiro. um lugar maior pro descanso. poderia melhor no salário | DB53: Gostaria q melhorasse mais um pouco pa parte do espaço e outras coisas
A54: 45687.443 | B54: Concordo | D54: Concordo Sempre | F54: Concordo | H54: Concordo | J54: Concordo | L54: Concordo | N54: Discordo | P54: Discordo | R54: Concordo | T54: Concordo | V54: Concordo | X54: Concordo | Z54: Concordo Sempre | AB54: Discordo | AD54: Concordo | AF54: Discordo | AH54: Concordo Sempre | AJ54: Concordo | AL54: Concordo Sempre | AN54: Concordo Sempre | AP54: Concordo Sempre | AR54: Concordo Sempre | AT54: Concordo | AV54: Concordo Sempre | AX54: Concordo Sempre | AZ54: Concordo Sempre | BB54: Concordo Sempre | BD54: Concordo | BF54: Concordo | BH54: Concordo | BJ54: Concordo | BL54: Concordo | BN54: Concordo | BP54: Concordo Sempre | BR54: Concordo Sempre | BT54: Discordo Sempre | BV54: Discordo | BX54: Discordo | BZ54: Discordo | CB54: Discordo | CD54: Concordo | CF54: Discordo | CH54: Concordo | CJ54: Concordo | CL54: Concordo | CN54: Concordo Sempre | CP54: Concordo | CR54: Discordo | CT54: Discordo | CV54: Discordo | CX54: Auxílio Combustível, Cesta Básica, Seguro de Vida, Gympass (Convênio Academias), Day Off | CZ54: Liberdade, autonomia, clima organizacional. | DA54: Melhor tratamento e reconhecimento da Diretoria, aumento salário e benefícios e diminuir o acúmulo de funções. | DB54: No geral, respondendo as perguntas que discordei, vejo que há uma falta de reconhecimento por parte da diretoria em algumas atividades que venho exercendo, seja horas extras, otimização de processos e esforço em aprender e melhorar constantemente o setor. Havendo apenas cobranças e apontamento de erros e não enxergando os pontos positivos.
A55: 45687.449 | B55: Concordo | C55: Alguns setores como logística e manutenção, tem "brincadeiras" machistas e homofóbicas | D55: Discordo | E55: Algumas atividades que são solicitadas com "urgência" não são fornecidos os insumos necessários. | F55: Discordo Sempre | G55: Sempre existe um colaborador que faz mais e leva toda a equipe nas costas, e por ser eficiente sempre tem mais trabalho porque esse colaborador é o único que faz o trabalho com qualidade. Deixando os demais da equipe mais folgados. | H55: Concordo Sempre | J55: Concordo | K55: A empresa fornece crescimento somente para alguns setores, na área comercial não vejo essas oportunidades. Possui oportunidade para ser consultor, mas não é todos que tem interesse nessa vaga. | L55: Concordo | N55: Concordo | O55: A empresa reconhece alguns bons colaboradores, mas vejo muitos profissionais qualificados não serem reconhecidos por serem mais tímidos ou retraído. | P55: Discordo Sempre | Q55: Existe muita rotatividade, e a maioria pedi demissão para iniciar em outro emprego, ganhando mais. | R55: Concordo Sempre | T55: Concordo Sempre | V55: Concordo | X55: Concordo | Z55: Concordo Sempre | AB55: Discordo | AC55: Não vejo um canal direto onde podemos falar nossas sugestões ou críticas, algumas vezes falamos pro Rh e fica meio que falado de boca e as ideias acabam se perdendo. | AD55: Concordo Sempre | AF55: Discordo | AG55: Dedicamos mais tempo ao nosso trabalho do que a nossa família e amigos, então fazer algo fora do horário de trabalho, nem sempre é possível e as vezes parece que a empresa não entende e exige nossa participação. | AH55: Concordo Sempre | AJ55: Concordo | AL55: Concordo Sempre | AN55: Concordo | AP55: Discordo | AQ55: Vejo que o meu gestor está preocupado somente com a parte profissional, pra algumas pessoas acho inflexível é outras podem fazer tudo. | AR55: Concordo Sempre | AT55: Concordo Sempre | AV55: Concordo | AX55: Discordo | AY55: Vejo que as ideias só são aceitas quando não tem custo. | AZ55: Concordo Sempre | BB55: Concordo Sempre | BD55: Discordo | BE55: Alguns colaboradores fazem corpo mole e é necessário ficar verificando. | BF55: Concordo | BH55: Discordo | BI55: Algumas pessoas com quem o gestor tem mais intimidade, vejo que ele protege mais. | BJ55: Discordo | BK55: As pessoas que são mais eficientes e responsáveis, são sobrecarregadas porque sempre passam mais tarefas. | BL55: Concordo | BN55: Concordo | BP55: Concordo | BR55: Concordo | BT55: Concordo | BU55: Já me senti humilhada | BV55: Concordo | BX55: Concordo | BZ55: Concordo | CB55: Concordo Sempre | CC55: Muitas pessoas gostam de fazer "amizade" com os gestores e na frente deles fazem um bom trabalho e na ausência não fazem mais nada. | CD55: Concordo | CF55: Concordo | CH55: Concordo | CJ55: Discordo | CK55: Não me sinto tão valorizada. Não falo tanto na questão financeira, falo na questão do profissionalismo, recolhimento do meu trabalho. | CL55: Concordo | CN55: Concordo Sempre | CP55: Discordo | CQ55: Não vejo rivalidade! | CR55: Concordo | CT55: Concordo | CV55: Concordo | CX55: Auxílio Combustível, Cesta Básica, Gympass (Convênio Academias), Day Off | CZ55: 1- não existir mais vários sindicatos. 2- horário e os dias trabalhados 3 - comissão e bonificações | DA55: 1 - estrutura da empresa 2 - um treinamento mais elaborado para os novatos 3 - setores mais bem distribuídos, vejo uma pessoa fazendo o trabalho de duas. | DB55: Melhorar a estrutura da empresa: sala de espera para os clientes, banheiros maiores e mais organizados, um espaço mais higiênico para descansar
A56: 45687.455 | B56: Discordo | C56: Temos problemas de infraestrutura e muito barulho da manutenção. | D56: Discordo | E56: As vezes sobre material não é o suficiente pra executar o trabalho da melhor forma. | F56: Concordo | G56: . | H56: Discordo | I56: Muitas pessoas só levam em consideração suas vontades e a ajuda não é bem genuína. | J56: Discordo | K56: Vejo que existem alguns movimentos assim de treinamentos, mas bem seletivo. | L56: Discordo | M56: As vezes falta essa clareza e a empresa não é tão transparente com seus funcionários. | N56: Discordo | O56: Reconhecimento aqui é bem seletivo. | P56: Discordo Sempre | Q56: Salários seguem o limite do mínimo do mercado, não acho justo. | R56: Concordo | T56: Concordo Sempre | V56: Concordo | X56: Concordo | Z56: Discordo | AA56: Aqui se você não seguir o padrão de comportamento liberal, você não será muito bem recebido. | AB56: Discordo | AC56: Praticamente não temos esse canal. | AD56: Discordo | AE56: Ja ocorreu e não foi em último recurso. | AF56: Discordo | AH56: Concordo Sempre | AJ56: Concordo Sempre | AL56: Concordo Sempre | AN56: Concordo Sempre | AP56: Concordo Sempre | AR56: Concordo Sempre | AT56: Concordo Sempre | AV56: Concordo Sempre | AX56: Concordo Sempre | AZ56: Concordo Sempre | BB56: Discordo | BC56: A empresa não deixa isso muito bem claro. | BD56: Concordo | BF56: Concordo | BH56: Concordo Sempre | BJ56: Concordo Sempre | BL56: Concordo Sempre | BN56: Concordo Sempre | BP56: Concordo Sempre | BR56: Concordo | BT56: Concordo | BU56: Ja vi uma liderança de outro setor querer humilhar outra pessoa de outro setor. | BV56: Discordo Sempre | BW56: Se importam se for do Interesse indivual ou se podem ganhar algo com aquilo. | BX56: Concordo | BZ56: Discordo Sempre | CA56: Não vejo isso por toda a empresa, mas novamente de forma seletiva. | CB56: Concordo Sempre | CC56: Infelizmente existe. | CD56: Concordo Sempre | CF56: Concordo Sempre | CH56: Concordo | CJ56: Concordo | CL56: Concordo | CN56: Concordo Sempre | CP56: Concordo Sempre | CR56: Concordo | CT56: Discordo Sempre | CU56: Muitas só se importam com se mesmo e se possível julga e aponta o dedo para o erro dos outros. | CV56: Concordo | CX56: Assistência Médica, Auxílio Combustível, Vale Alimentação, Cesta Básica, Day Off | CZ56: Diretoria aberta oportunidade de crescimento integridade no dia de pagamento de salários | DA56: benefícios, focar na missão estabelecida, salários | DB56: .
A57: 45687.465 | B57: Discordo | C57: Ambiente muito fora do patrão para mecânico e técnico em eletrica | D57: Concordo | F57: Concordo | H57: Concordo | J57: Concordo | L57: Discordo | M57: Sobre a oficina e banheiro até agora não foi tomada nenhuma iniciativa com respeito a espaço e segurança . | N57: Concordo | P57: Discordo | Q57: Devido a questão de sindicato ou pela própria gestão deixa a desejar alguns benefícios q nós merecemos pelo local e forma de trabalho. | R57: Concordo | S57: Gosto do q faço independente de qual seja a empresa | T57: Concordo | V57: Concordo | X57: Discordo | Y57: Devido fatores de salários e ambiente de trabalho | Z57: Concordo | AB57: Concordo | AD57: Concordo | AF57: Concordo | AH57: Concordo | AJ57: Concordo | AL57: Concordo | AN57: Concordo | AP57: Concordo | AR57: Concordo | AT57: Concordo | AV57: Concordo | AX57: Concordo | AZ57: Concordo | BB57: Discordo | BC57: Pq não depende dele | BD57: Concordo | BF57: Discordo | BG57: Pq cabe a cada um realizar suas atividades | BH57: Concordo | BJ57: Concordo | BL57: Concordo | BN57: Concordo | BP57: Concordo | BR57: Concordo | BT57: Discordo Sempre | BU57: Em nenhum momento | BV57: Concordo | BX57: Concordo | BZ57: Concordo | CB57: Concordo | CC57: Algumas sim | CD57: Concordo | CF57: Concordo | CH57: Concordo | CJ57: Discordo | CK57: Devido ao ambiente de trabalho e tbm da parte de higiene q no caso banheiro | CL57: Discordo | CM57: Ambiente insalubre com pouca iluminação sem espaço e ambiente correto para desde de equipamentos | CN57: Concordo | CO57: Qual o canto que tem kkkk, | CP57: Concordo | CQ57: Algumas pessoas sim | CR57: Discordo | CS57: Vai depender muito de como a empresa vai mudar futuramente. | CT57: Concordo | CV57: Discordo | CW57: Tem muita coisa para ser ajustada com funcionários e lo oval de trabalho | CX57: Assistência Médica, Assistência Odontológica, Auxílio Combustível, Refeição na Empresa, Vale Refeição, Seguro de Vida | CY57: Vale combustível e seguro de vida deveria ser levado em pauta com os gestores | CZ57: Realizações de gincanas , aniversariantes e aumento de cargo | DA57: Banheiro vestiário e espaço de descanso de almoço | DB57: Tornar o ambiente mais agradável com ótimas condições de trabalho trazer mais benefícios tais como vale combustível seguro de vida faz com q o profissional se dedique mais a empresa e aumente sua produção .
A58: 45687.465 | B58: Concordo | C58: É um bom ambiente de se trabalhar, mas só isso não retém talentos. Temos muito a melhorar principalmente em benefícios, infraestrutura e planos de carreiras. Se a gente quer ser uma empresa que uma pessoa passe 5 anos ou mais, perder essa fama de empresa que as pessoas só aprendem, pegam experiência no mercado e saem para outros lugares. O ponto chave está aí. Ter salários mais competitivo, na minha visão o da Nordeste está muito abaixo do mercado para todas as áreas. | D58: Discordo | E58: Acredito que nossas máquinas são ultrapassadas. Em algumas áreas se faz necessidade o BI, e quando queremos isso se faz necessário aumento de memória nos PCs. Seria interessante já ter máquinas que suportem esse tipo de aplicação, para evitar outro investimento a respeito. | F58: Concordo | H58: Concordo | J58: Discordo | K58: Até tem às vezes, mas esporádico até demais. Pode melhorar muito ainda | L58: Concordo | M58: Entendo que a empresa está crescendo e evoluindo cada vez mais. Isso é ótimo. Entretanto acredito que a via de mão dupla empresa e funcionários não está acontecendo. Apenas para empresa. Não vejo retorno dos nossos resultados atuais em melhorias visíveis no nosso dia a dia. | N58: Discordo Sempre | O58: Até sim, mas infelizmente isso é setorizado. Alguns setores são valorizados e outros extremamente esquecidos. Se você der sorte de cair em uma gestão que reconheça esse esforço a mais, sim. Agora caso contrário, infelizmente isso não acontece | P58: Discordo Sempre | Q58: Acredito que deveria ser feito um estudo real e sério sobre o tema, pois está defasado demais! Chega a ser absurdo a discrepância. Entra no principal ponto, do número absurdo de saídas e turnovers em 2024. Inúmeras vezes perdemos talentos por esse motivo, principalmente. A nordeste precisa acordar, se não será mais do mesmo esse ano, justamente por conta de salários. | R58: Concordo | S58: Pra mim é, mas infelizmente ainda sinto que não obtive o retorno da empresa. Para que isso se torne ainda mais realidade. | T58: Concordo | V58: Concordo | X58: Concordo | Y58: No início sim, depois de alguns meses, as questões de benefícios fracos, salários baixos e falta de oportunidades de crescimento podem acabar desmotivando | Z58: Concordo | AB58: Discordo | AC58: Acredito que essa questão de auxílio do RH, como nos é informado quando entramos. Fica muito no papel, na prática não vejo muito isso, infelizmente. | AD58: Discordo Sempre | AE58: Já aconteceu ano passado, então pode vir a acontecer novamente. | AF58: Concordo | AH58: Concordo | AJ58: Concordo | AL58: Concordo | AN58: Concordo | AP58: Discordo | AQ58: Só falamos de trabalho o tempo todo, então só como profissional mesmo | AR58: Concordo | AT58: Concordo | AV58: Concordo | AX58: Concordo | AZ58: Discordo Sempre | BA58: Acredito que não, tenho que ir atrás das informações com os meus colegas. E também acho o nosso RH e DP muito inacessíveis. Parece que é pecado falar de dinheiro, de salário com eles. Tudo eles são instruídos a se silenciarem. Isso me incomoda bastante. | BB58: Concordo | BD58: Discordo | BF58: Discordo | BH58: Discordo | BJ58: Concordo | BL58: Concordo | BN58: Concordo | BP58: Discordo | BR58: Discordo | BS58: Infelizmente já presenciei casos de bullying e racismo na empresa. Mas a pessoa afetada não sei o motivo levaram na brincadeira, entretanto achei muito estranho e ruim de se presenciar | BT58: Concordo Sempre | BU58: Já presenciei em outros setores isso. Mas no meu até nunca no meu setor | BV58: Concordo | BX58: Discordo Sempre | BY58: Infelizmente, mesmo depois da saída do antigo sócio. Ainda vejo a empresa com muita setorização. Vejo muito o sentimento de "A prioridade é o meu setor, e não ligo para o resto". Infelizmente o sentimento de fazer parte do corpo Nordeste Locações não existe. É como se o braço e a perna, fossem independentes. | BZ58: Discordo Sempre | CA58: No meu caso, não. Infelizmente. Mas gostaria muito dessa mudança. | CB58: Concordo Sempre | CC58: Vejo bastante no meu dia a dia, infelizmente. | CD58: Concordo | CF58: Concordo | CH58: Concordo | CJ58: Concordo | CL58: Concordo | CN58: Concordo Sempre | CO58: Infelizmente sim | CP58: Discordo | CR58: Concordo | CS58: Sim, mas precisa acordar para o mercado. Ter benefícios, salários e oportunidades melhores. O que atualmente não ocorre, infelizmente | CT58: Discordo | CU58: Infelizmente sinto que cada um está na sua bolha. Como se existissem muros. Que separam os setores e as pessoas | CV58: Discordo | CW58: Ainda não. É uma empresa ok, espero que um dia possa se dizer que sim | CX58: Assistência Médica, Assistência Odontológica, Auxílio Combustível, Multibenefícios Alimentação/ Refeição, Gympass (Convênio Academias) | CY58: Se faz necessário com urgência o auxílio combustível. Poderia ser o mesmo valor disponibilizado no vale transporte ou um valor fixo de 200 reais mensais. | CZ58: Ambiente, vontade de ensinar da maioria das pessoas e uma direção que sabe o que está fazendo | DA58: Benefícios são fracos, salários muito abaixo do mercado e oportunidades de crescimento. | DB58: Renovação de benefícios. Vale ser um valor fixo, não sendo mais na diária. Assistência médica ser 100% coberta pela empresa, vale combustível fixo para quem tem veículos. Salários serem renovados e seguir o mercado ou pelo uma logica, e as oportunidades de crescimento aparecerem. Acontece por exemplo que a nordeste locações pagavam um salário X pra minha posição no passado. E tenho o mesmo cargo que essa pessoa e recebo muito menos que ela. Pra mim isso não faz o menor sentido, pagava mais pra pessoa e pra mim que tem o mesmo cargo não paga o mesmo valor. São esses tipos de inconsistências que também acabam desmotivando as pessoas. Acredito que deveria ter essa revisão de salários urgentes. A empresa tem que entender que o que faz a pessoa querer ficar vai muito além do ambiente de trabalho que aqui é bom, mas usar isso como propaganda por muito tempo não irá dar certo.
A59: 45687.466 | B59: Concordo | C59: Umas coisas eu concordo outras não por exemplo banheiro está deixando a desejar | D59: Concordo | E59: Está faltando ferramenta adequada para realizar as atividades como sacar rolamentos n608 | F59: Concordo | H59: Concordo | J59: Discordo | L59: Concordo | M59: Para a empresa sim mas para os colaboradores ainda deixar a desejar | N59: Discordo Sempre | P59: Discordo | Q59: Está deixando a desejar como os mecânicos trabalhador com produtos perigoso com gasolina a rede elétrica está precária e não vejo melhoras | R59: Concordo | S59: Meu trabalho tem um sentido para mim mas para a empresa eu acho quer não | T59: Concordo | V59: Concordo | X59: Discordo | Y59: Faltando olhar mas para a parte da mecânica | Z59: Discordo | AB59: Discordo Sempre | AD59: Concordo | AF59: Discordo | AH59: Discordo Sempre | AI59: Lider para mandar tem mas para resolver os problemas quer tem na oficina não | AJ59: Concordo | AK59: Quer faça as manutenções nas máquinas só isso | AL59: Concordo | AM59: Comprometimento com a empresa ele tem mas com os funcionários nas | AN59: Concordo | AP59: Concordo | AQ59: A favor da empresa mas para funcionários não | AR59: Concordo | AT59: Concordo | AV59: Concordo | AX59: Concordo | AZ59: Concordo | BB59: Concordo | BD59: Concordo | BF59: Concordo | BH59: Concordo | BJ59: Concordo | BL59: Discordo | BN59: Discordo | BP59: Concordo | BR59: Concordo | BT59: Discordo Sempre | BV59: Concordo | BX59: Discordo | BZ59: Discordo | CB59: Concordo | CD59: Concordo | CE59: Fala mas entra no ouvido sai no outro | CF59: Concordo | CH59: Concordo | CJ59: Discordo | CL59: Concordo Sempre | CN59: Concordo | CP59: Discordo | CR59: Discordo | CS59: Deus quem vai dizer | CT59: Discordo | CV59: Discordo | CX59: Assistência Médica, Auxílio Combustível, Celular, Vale Refeição, Vale Alimentação, Seguro de Vida | CZ59: Plano de saúde vale alimentação e farmácia | DA59: Perigolosidade . | DB59: Nos mecânico trabalhamos com produtos químicos e não recebemos nada com isso tinha quer olhar mais para isso
A60: 45687.47 | B60: Concordo | C60: É agradável trabalhar na Nordeste, porém se o ambiente fosse um pouco mais confortavel ajudaria | D60: Discordo | E60: Minhas máquinas de trabalho e meu ambiente são bons mas ja estao ultrapasados e para o conforto e ergonômia deveriam ser revistos | F60: Concordo Sempre | G60: Quase todos aqui na Nordeste fazem o seu trabalho bem e ate além de suas funções para concluir suas tarefas | H60: Concordo | I60: Quase todos sao muito receptivos e sempre tem a vontade de ajudar | J60: Discordo | K60: Aqui nao tem um suporte direto para cursos nem para o desenvolvimento, concordo que aqui na Nordeste temos varias oportunidades mas nao de cursos externos nem suporto ao estudo, sugiro um estudo sobre esse assunto para alem de oferecer um convenio ou curso gratuito , a nordeste focar mais nessa parte , | L60: Concordo Sempre | M60: A empresa esta em constante crescimento, e lutando para se torna uma das maiores do Nordeste, focando nas relações pessoais com os clientes , mas tambem com foco em evolução dos processos e otimização de recursos | N60: Concordo | P60: Discordo | R60: Concordo Sempre | S60: Aqui todos se tratam como uma grande família, acho que esse clima relaxante e descontraido faz com que nos sentimos em casa | T60: Concordo Sempre | V60: Concordo Sempre | X60: Concordo Sempre | Z60: Concordo Sempre | AB60: Discordo | AD60: Concordo | AF60: Concordo | AH60: Concordo | AJ60: Discordo | AL60: Concordo | AN60: Concordo | AP60: Discordo | AR60: Concordo | AT60: Discordo | AV60: Concordo | AX60: Concordo Sempre | AZ60: Concordo | BB60: Concordo | BD60: Concordo Sempre | BF60: Concordo | BH60: Concordo | BJ60: Concordo | BL60: Concordo Sempre | BN60: Concordo | BP60: Discordo | BR60: Concordo Sempre | BT60: Discordo Sempre | BV60: Concordo | BX60: Concordo | BZ60: Concordo | CB60: Concordo Sempre | CD60: Concordo Sempre | CF60: Concordo | CH60: Concordo Sempre | CJ60: Concordo Sempre | CL60: Concordo Sempre | CN60: Concordo Sempre | CP60: Concordo | CR60: Concordo Sempre | CT60: Discordo | CV60: Concordo | CX60: Assistência Médica, Celular, Multibenefícios Alimentação/ Refeição, Auxílio Educação, Empréstimo Consignado | CZ60: As pessoas, o ambiente, A comunicação | DA60: Estrutura , benefícios, salários | DB60: Gostaria que as mudanças realmente acontececem e nao somente fosse dito ou prometido
A61: 45687.478 | B61: Concordo | D61: Concordo | F61: Concordo | H61: Concordo | J61: Concordo | L61: Concordo | N61: Concordo | P61: Concordo | R61: Concordo | T61: Concordo | V61: Concordo | X61: Concordo | Z61: Concordo | AB61: Concordo | AD61: Discordo | AF61: Concordo | AH61: Concordo | AJ61: Concordo | AL61: Concordo | AN61: Concordo | AP61: Concordo | AR61: Concordo | AT61: Concordo | AV61: Concordo | AX61: Concordo | AZ61: Concordo | BB61: Concordo | BD61: Concordo | BF61: Concordo | BH61: Concordo | BJ61: Concordo | BL61: Concordo | BN61: Concordo | BP61: Concordo | BR61: Concordo | BT61: Concordo | BV61: Concordo | BX61: Concordo | BZ61: Concordo | CB61: Concordo | CD61: Concordo | CF61: Concordo | CH61: Concordo | CJ61: Concordo | CL61: Concordo | CN61: Concordo | CP61: Concordo | CR61: Concordo | CT61: Concordo | CV61: Concordo | CX61: Auxílio Combustível, Cesta Básica | DA61: Ok | DB61: Ok
A62: 45687.48 | B62: Concordo Sempre | D62: Concordo Sempre | F62: Concordo | H62: Concordo | J62: Concordo | L62: Concordo | N62: Concordo | P62: Discordo | Q62: Algumas pessoas saíram da empresa justamente pela baixa remuneração, indo para a concorrente. | R62: Concordo Sempre | T62: Concordo | V62: Concordo | X62: Concordo | Z62: Concordo | AB62: Concordo | AD62: Concordo | AF62: Concordo | AH62: Concordo Sempre | AJ62: Concordo | AL62: Concordo Sempre | AN62: Concordo | AP62: Concordo | AR62: Concordo | AT62: Concordo | AV62: Concordo | AW62: Não é | AX62: Concordo | AZ62: Concordo | BB62: Concordo | BD62: Concordo | BF62: Concordo | BH62: Discordo | BI62: Existe alguns tratamentos diferenciados | BJ62: Concordo | BL62: Concordo | BN62: Discordo | BO62: Às vezes tem postura inadequada de líder | BP62: Concordo | BR62: Concordo Sempre | BT62: Concordo | BU62: Líder de outro setor se achando superior a um colega de trabalho | BV62: Concordo | BX62: Concordo | BZ62: Concordo Sempre | CB62: Concordo | CD62: Concordo Sempre | CF62: Concordo Sempre | CH62: Concordo Sempre | CJ62: Concordo Sempre | CL62: Concordo | CN62: Concordo | CP62: Discordo | CQ62: Nunca presenciei | CR62: Concordo | CT62: Concordo | CV62: Concordo | CX62: Assistência Médica, Auxílio Combustível, Multibenefícios Alimentação/ Refeição, Seguro de Vida, Day Off | CZ62: O ambiente de trabalho, flexibilidade de horário e oportunidade de crescimento. | DA62: Poderia ser aderido a modalidade de trabalho híbrido para as tividades que couberem; Conscientizar os colaboradores da importância de manter limpo o espaço de uso coletivo; Os pagamentos deveriam ser realizados pelo turno da manhã e não ao final do dia. | DB62: Seria interessante ter laboral 1x por semana e o dia da fruta. O dia da fruta se dá da seguinte maneira , 1x por semana seria oferecido em cada sala uma cesta com diversas frutas( banana, tangerina, maçã,...) para que cada colaborador pudesse pegar uma. Isso faz toda a diferença num ambiente de trabalho, já trabalhei em uma empresa que oferecia e era bom demais.
A63: 45687.484 | B63: Concordo Sempre | D63: Concordo Sempre | F63: Concordo | H63: Concordo Sempre | I63: Vejo que a grande maioria dos colaboradores Nordeste são empenhados a ajudar as demandas | J63: Concordo Sempre | K63: Treinamentos e oportunidades sempre são oferecidas para crescimento | L63: Concordo | N63: Concordo | O63: Sempre fui reconhecida pelo que faço | P63: Discordo | Q63: Por conversas com outros colaboradores Nordeste e até mesmo de outras empresas, a Nordeste deixa a desejar no quesito SALÁRIO quanto a algumas funções | R63: Concordo Sempre | S63: Amo o que faço, e vejo total sentido no meu trabalho. | T63: Concordo | V63: Concordo Sempre | X63: Concordo | Z63: Concordo Sempre | AB63: Concordo | AD63: Concordo Sempre | AE63: Acredito que os sócios da empresa são bastante empáticos e humanos, tomando decisões quase sempre baseadas no bem estar do colaborador | AF63: Concordo Sempre | AH63: Concordo | AJ63: Concordo | AL63: Concordo Sempre | AM63: Meu líder é inspiração | AN63: Concordo | AP63: Concordo Sempre | AQ63: Sempre pensando no meu crescimento pessoal e profissional | AR63: Concordo Sempre | AS63: Tenho total acesso ao meu líder e sempre com fácil acesso para tratar qualquer assunto | AT63: Concordo | AV63: Concordo | AX63: Concordo | AZ63: Concordo | BB63: Concordo Sempre | BD63: Concordo | BF63: Concordo Sempre | BH63: Concordo | BJ63: Concordo Sempre | BL63: Concordo Sempre | BN63: Concordo | BP63: Concordo Sempre | BQ63: Semanalmente temos feedback simples e uma vez por mês temos o feedback estruturado, sempre posicionando o que precisa ser melhorado, e o que venho fazendo corretamente. | BR63: Concordo Sempre | BT63: Discordo | BU63: Sempre que há alguma pequena chateação, é solucionado e conversado | BV63: Concordo | BX63: Concordo Sempre | BZ63: Concordo Sempre | CB63: Discordo | CD63: Concordo Sempre | CF63: Concordo Sempre | CH63: Concordo Sempre | CI63: Inclusive acho incrível, como todos, independente do cargo, conseguimos ter esse tratamento por igual | CJ63: Concordo Sempre | CL63: Concordo Sempre | CN63: Concordo Sempre | CO63: Acredito que é algo inevitável, mas diferente de outras empresas onde já trabalhei, as fofocas não são pesadas e não me lembro de terem prejudicado alguém em um nível preocupante | CP63: Concordo | CQ63: Em algum momento sim percebo essa rivalidade mas acredito que algo que consigamos minimizar com conversas e ações | CR63: Concordo Sempre | CS63: Pretendo crescer e me aposentar por aqui kkkkkk | CT63: Concordo Sempre | CV63: Concordo Sempre | CW63: Até o momento o melhor que já trabalhei | CX63: Assistência Médica, Auxílio Combustível, Vale Alimentação, Auxílio Educação, Gympass (Convênio Academias) | CZ63: Acesso fácil a líderes e diretores, boa convivência com os colaboradores, reconhecimento. | DA63: Local de descanso, salários e auxílios | DB63: Atualmente estou muito satisfeita com a Nordeste Locacoes, acredito que com essa pesquisa algumas coisas que já são boas, serão ótimas e algumas que não são boas faremos ser. É uma empresa excelente de trabalhar, que pensa no colaborador e visa sempre o bem estar do mesmo.
A64: 45687.487 | B64: Concordo Sempre | C64: Empresa acolhedora, clima agradável e pessoas acessíveis. | D64: Concordo Sempre | F64: Concordo | G64: É um dos valores que se aplicam. | H64: Concordo | J64: Concordo Sempre | K64: Nítido que a empresa tem muitas possibilidades de crescimento e aposta no funcionário. | L64: Concordo Sempre | M64: Trabalhamos para sermos a numero 1 do Nordeste. | N64: Concordo Sempre | P64: Concordo | R64: Concordo Sempre | T64: Concordo Sempre | U64: A empresa é acolhedora | V64: Concordo Sempre | W64: Minha equipe é sem igual. | X64: Concordo | Z64: Concordo Sempre | AB64: Concordo | AD64: Concordo | AF64: Concordo | AG64: Empresa muito humana | AH64: Concordo Sempre | AJ64: Concordo Sempre | AK64: Ele busca desenvolver os seus liderados | AL64: Concordo Sempre | AN64: Concordo Sempre | AP64: Concordo Sempre | AR64: Concordo Sempre | AT64: Concordo Sempre | AV64: Concordo | AX64: Concordo Sempre | AZ64: Concordo Sempre | BB64: Concordo | BD64: Concordo Sempre | BF64: Concordo | BH64: Concordo Sempre | BJ64: Concordo Sempre | BL64: Concordo Sempre | BN64: Concordo | BP64: Concordo Sempre | BR64: Concordo | BT64: Discordo Sempre | BU64: Nunca vi acontecer | BV64: Concordo | BX64: Concordo | BZ64: Concordo | CA64: Alguns setores sim | CB64: Discordo | CC64: Não conheço quem faça. | CD64: Concordo Sempre | CF64: Concordo Sempre | CG64: Os diretores são super acessíveis e abertos a opiniões. | CH64: Concordo Sempre | CJ64: Concordo Sempre | CK64: Sinto que faço parte. | CL64: Concordo | CN64: Concordo | CO64: Todo ambiente tem, chega a ser inevitável, não denegrindo a imagem dos colaboradores é considerada saudável, aqui não seria diferente. | CP64: Discordo | CQ64: Não vejo isso acontecer | CR64: Concordo Sempre | CT64: Concordo Sempre | CU64: Acho que as equipes se dão muito bem, de fato uma EQUIPE | CV64: Concordo Sempre | CX64: Assistência Médica, Assistência Odontológica, Auxílio Combustível, Multibenefícios Alimentação/ Refeição, Empréstimo Consignado, Gympass (Convênio Academias), Day Off | CZ64: Sala de descanso ( poucas empresas possuem) Estrutura de trabalho Comunicação com lideranças Horários | DA64: Refeitório e sala de descanso são quentes, poderíamos climatizados. Local mais apropriado para as bolsas Juntar o administrativo ( anexo e galpão) | DB64: A empresa no geral é muito boa, claro que como todas outras tem seus pontos de melhoria, a sala de descanso é ótima, ter um espaço para repouso é essencial, porém é quente. Maior desconto no plano de saúde. Com o aumento no preço do ramo alimentício, seria interessante que tivéssemos um aumento mais significativo no vale refeição.
A65: 45687.492 | B65: Concordo Sempre | C65: Tem um bom espaço e possui boa temperatura ambiente. | D65: Concordo Sempre | E65: Possuo todos os materiais necessários para meu trabalho. | F65: Concordo | G65: Concordo que as pessoas fazem além da sua obrigação. Mas não deveria ocorrer isso. Deveria haver um meio para o trabalho ser feito durante o horário de trabalho e não levá-lo além dele. | H65: Concordo | I65: Até agora, sempre me ajudaram com o que eu precisasse. | J65: Discordo | K65: Oferece alguns treinamentos, mas não para todos e, as vezes, não há um treinamento completo. Por exemplo, o de excel foi útil, mas não foi tempo suficiente para absorver o conhecimento. | L65: Discordo | M65: Não possuo uma visão desse tipo no momento. | N65: Discordo | O65: A empresa não reconhece o que é feito. Não há um comentário crítico, que faça a pessoa melhorar. | P65: Discordo | Q65: Há empresas que remuneram muito mais. Mesmo uma pessoa possuindo ensino superior, o salário aqui é baixo e não muito atrativo. | R65: Discordo Sempre | S65: Infelizmente, sinto que é apenas um emprego. Não me sinto feliz com o que faço. | T65: Concordo Sempre | U65: Os novatos, de fato, são bem recebidos pela empresa. | V65: Concordo | W65: Quando preciso de ajuda, sempre há alguém disposto a ajudar. | X65: Discordo | Y65: Tenho que discordar. Tanto eu como outros, acredito que não todos, não possuem vontade de trabalhar aqui. Há um certo momento em que o trabalho fica monótono, muito repetitivo. | Z65: Discordo Sempre | AA65: Preciso sempre dar bom dia, gostaria de fazer só meu trabalho e ir para casa, falando o necessário sobre o trabalho. Aqui, eu me sinto obrigado a sorrir sempre, dar bom dia, até em dias que não desejo dar bom dia e há dias que não gostaria de falar com ninguém. | AB65: Discordo Sempre | AC65: Não possuo conhecimento de canais para sugestões e reinvidicações. | AD65: Concordo Sempre | AE65: Acredito que seja o último recurso de qualquer empresa, quando a situação financeira estiver ruim. | AF65: Discordo Sempre | AG65: As pessoas aqui levam seus trabalhos para casa, não tendo o seu momento de lazer. E acho o horário de trabalho puxado. Deveria ser de 8:00 às 16h. Seria um horário perfeito para equilibrar o profissional ao pessoal, fazendo com que a pessoa tenha mais tempo para se qualificar e ter seus momentos de lazer. | AH65: Concordo Sempre | AI65: Conheço muito bem. | AJ65: Concordo Sempre | AK65: Sim, ele deixa bem claro. | AL65: Concordo Sempre | AM65: Ele é um ótimo líder, sempre fazendo o possível para não deixar a empresa na mão. | AN65: Concordo Sempre | AO65: Com toda certeza. Ultimamente ele tem se dedicado muito a empresa | AP65: Concordo Sempre | AQ65: Sim, ele tem me motivado a melhorar profissionalmente. | AR65: Concordo Sempre | AS65: Ele é muito acessível. | AT65: Discordo | AU65: Não há um treinamento completo. Ele apenas ensina o que se deve fazer e a pessoa se vira. | AV65: Discordo | AW65: Os erros que são cometidos, geralmente, são bem simples, que não precisaria receber chamado. Fica um clima extremamente chato, como por exemplo, errar uma vírgula, um número, uma palavra, coisas que seriam facilmente corrigidas e não traria grandes problemas. | AX65: Concordo Sempre | AY65: Ele houve nossas sugestões e sempre toma ações com base nelas. | AZ65: Concordo Sempre | BA65: Eles nos informam muito bem sobre mudanças. | BB65: Concordo Sempre | BC65: Sim, sempre nos informam o rumo que a empresa está tomando. | BD65: Discordo | BE65: Em questão de honestidade, ele confia. Apenas nas questões sobre erros no trabalho, ele não confia. Não gosto muito quando ele fala que "não confiaria nem nele, imagine nos outros". Esse tipo de coisa não traz confiança para os colaboradores. | BF65: Discordo | BG65: Ele não prejudica ninguém por causa de suas decisões | BH65: Concordo Sempre | BI65: Sim, nos tratam da mesma forma. | BJ65: Concordo | BK65: Estamos frequentemente mudando o setor para se adequar a ele. | BL65: Concordo | BM65: Temos autonomia para fazermos algumas coisas. | BN65: Concordo | BO65: Somente às vezes. | BP65: Concordo Sempre | BQ65: Sim, ele da críticas construtivas. | BR65: Concordo Sempre | BS65: Em questão de preconceitos na empresa, aqui ela é excelente. | BT65: Concordo | BU65: Não diria humilhado, mas ele já chegou a ficar com raiva de mim por certos erros e isso fez com que eu me desmotivasse muito, a ponto de querer sair da empresa e sempre com certo receio de chegar na empresa e receber mais reclamação. Isso foi no começo, quando entrei. | BV65: Discordo | BW65: Conheço pessoas que não se davam bem na empresa | BX65: Concordo | BY65: Pelo menos no meu setor, sim | BZ65: Concordo Sempre | CA65: Sim, concordo! Gosto muito das datas festivas. | CB65: Discordo | CC65: Não vejo esse tipo de coisa aqui na empresa. | CD65: Discordo Sempre | CE65: Eles não sabem falar direito com o funcionário e não conseguem dar críticas construtivas. | CF65: Discordo | CG65: Sempre evito falar, porque não passam um ar de confiança para que possamos falar com eles. Parece que, se eu for falar com eles eu vou levar uma patada. | CH65: Concordo Sempre | CI65: Sim, nunca fui discriminado pelo minha função. | CJ65: Discordo Sempre | CK65: O que eu faço, qualquer outro pode fazer. | CL65: Discordo | CM65: No começo sim, mas depois se torna um lugar chato. | CN65: Concordo | CO65: Há fofocas, mas de maneira razoável. | CP65: Discordo | CQ65: Não vejo esse tipo de coisa aqui. | CR65: Discordo Sempre | CS65: Não pretendo ficar muito tempo. Provavelmente, menos de um ano. | CT65: Concordo | CU65: Acredito que os outros setores se dêem bem. | CV65: Discordo | CW65: Por curto período, ele é um bom lugar. Mas para um período longo, ele não é muito bom. | CX65: Assistência Médica, Assistência Odontológica, Vale Refeição, Vale Alimentação, Gympass (Convênio Academias) | CY65: Nem todos os setores comemoram metas. Alguns comemoram e outros não, o que dar um ar de exclusão. Porque os setores comemoram a batida de meta e outros não? | CZ65: A empresa recebe muito bem os novatos, faz distrações/eventos/comemorações para os funcionários não ficarem em um ambiente chato e isso é muito bom, e tem boa estrutura ambiente. | DA65: O salário, o horário de trabalho e as demandas para os funcionários. | DB65: Gostaria de sugerir um ambiente fechado e bem climatizado para a área de descanso, porque a empresa possue muito barulho e luz do sol, o torna o ambiente de descanso muito ruim para se descansar. Também gostaria de sugerir um horário de trabalho melhor, para que as pessoas possam ter tempo de lazer e educação, para melhorar profissionalmente e mentalmente. Também, definir melhor as demandas dos funcionários, para que eles não sobrecarreguem ao ponto de levar seu trabalho para casa e fiquem estressados durante o horário de trabalho.
A66: 45687.493 | B66: Discordo | C66: Temos necessidade de melhoria no ambiente de descanso e vestiários | D66: Concordo Sempre | F66: Concordo Sempre | H66: Concordo Sempre | J66: Discordo | K66: Sinto falta de cursos e treinamentos propostos pela empresa | L66: Concordo Sempre | N66: Concordo Sempre | P66: Concordo | R66: Concordo Sempre | T66: Concordo Sempre | V66: Concordo Sempre | X66: Concordo | Y66: Porém sempre tem aquela pessoa que atrapalha e joga contra pois deseja seguir outros projetos, na minha opinião não vale a pena ter alguém assim no time | Z66: Concordo Sempre | AB66: Concordo | AD66: Concordo Sempre | AF66: Concordo Sempre | AH66: Concordo Sempre | AJ66: Concordo Sempre | AL66: Concordo Sempre | AN66: Concordo Sempre | AP66: Concordo Sempre | AR66: Concordo Sempre | AT66: Concordo | AV66: Concordo | AX66: Concordo Sempre | AZ66: Concordo Sempre | BB66: Concordo Sempre | BD66: Concordo | BF66: Concordo | BH66: Concordo | BJ66: Concordo Sempre | BL66: Concordo | BN66: Concordo Sempre | BP66: Concordo | BR66: Concordo Sempre | BT66: Discordo Sempre | BV66: Concordo | BX66: Concordo | BZ66: Concordo Sempre | CB66: Discordo | CD66: Concordo Sempre | CF66: Concordo Sempre | CH66: Concordo Sempre | CJ66: Concordo Sempre | CL66: Concordo Sempre | CN66: Discordo | CP66: Discordo Sempre | CR66: Concordo Sempre | CT66: Concordo Sempre | CV66: Concordo Sempre | CX66: Assistência Médica, Auxílio Combustível, Auxílio Educação, Gympass (Convênio Academias), Day Off | CZ66: Cultura, ambiente saudável e acessibilidade a diretoria | DA66: Ambiente de descanso, banheiros femininos e planos de cargos e carreiras | DB66: Sem comentários
A67: 45687.503 | B67: Concordo Sempre | C67: Sim, pelos colaboradores deixar o ambiente mais leve no dia a dia. | D67: Concordo | F67: Concordo | H67: Discordo | I67: Nem sempre, tem colaborador que passa por você não dá nem bom dia, imaginar ajudar! | J67: Discordo | K67: Desde que entrei aqui nunca tive um treinamento e nem a oportunidade de crescimento. | L67: Concordo | N67: Discordo | O67: Zero reconhecimentos temos, temos pessoas que fazer de tudo e não ganham nem parabéns. | P67: Discordo Sempre | Q67: Fazendo um levantamento de mercado hoje meu salário não chega nem perto do que recebo hoje | R67: Concordo | T67: Concordo | V67: Discordo | W67: Zero orgulho, hoje em dia essas pessoas não gostam de ajudar ninguém. | X67: Concordo | Z67: Concordo | AB67: Discordo Sempre | AC67: Aqui na existe nem comunicação,imagina canal | AD67: Concordo | AF67: Discordo | AG67: Nunca, aqui temos que ser profissional e pronto | AH67: Concordo | AJ67: Concordo | AL67: Concordo | AN67: Concordo | AP67: Discordo | AQ67: Não e mesmo só quer ver resultados estão bem ou não. | AR67: Concordo | AT67: Discordo | AU67: Não,porque a empresa não disponibiliza qualquer tipo de treinamento. | AV67: Concordo | AX67: Concordo | AZ67: Concordo | BB67: Concordo | BD67: Concordo | BF67: Concordo | BH67: Concordo | BJ67: Concordo | BL67: Concordo | BN67: Concordo | BP67: Concordo | BR67: Concordo | BT67: Discordo | BU67: Nunca fui humilhado e nem vi. | BV67: Discordo | BW67: Nem sempre | BX67: Discordo | BY67: Nem sempre | BZ67: Concordo | CB67: Concordo | CD67: Concordo | CF67: Concordo | CH67: Concordo | CJ67: Discordo Sempre | CK67: Não me sinto valorizado e nem que posso fazer diferença | CL67: Concordo | CN67: Concordo Sempre | CP67: Concordo | CR67: Discordo | CT67: Concordo | CV67: Concordo | CX67: Auxílio Combustível, Cesta Básica, Seguro de Vida, Gympass (Convênio Academias), Day Off | CY67: VALORIZAR MAIS OS COLABORADORES E DA OPORTUNIDADE PRA QUEM QUER INGRESSAR EM OUTRA AREA | CZ67: Ambiente, pessoas, localização | DA67: Treinamentos, oportunidades, comunicação | DB67: Muita falta de comunicação e oportunidades e treinamentos.
A68: 45687.505 | B68: Concordo | D68: Concordo | F68: Concordo | H68: Concordo Sempre | I68: As pessoas aqui são muito solicitas e dispostas a ajudar. | J68: Concordo | L68: Concordo | M68: A empresa tá em fase de expansão e isso gera uma certa expectativa de oportunidade de crescimento, eu acredito que para eu como profissional estar nesse futuro próximo da empresa e necessário que eu me qualifique e busque capacitação para assim eu chegar nesse futuro. | N68: Discordo | O68: Eu acredito que poderia ter algum tipo de premiação por metas e trabalhos extras alcançados. | P68: Discordo | Q68: Os salários e benefícios da empresa são defasados, seria interessante uma criação de plano de cargos e salários para que o colaborador tenha o incentivo de que ele pode crescer dentro da empresa, seria bom a criação de novos benefícios por exemplo: um vale combustível pois a maioria dos colaboradores tem transporte próprio, seria interessante se o plano de saúde e odontológico fosse pago 100% pela empresa, seria bacana a criação de uma premiação por metas batidas e por fim uma participação dos lucros da empresa seria muito interessante. | R68: Concordo | S68: Me sinto muito bem no meu ambiente de trabalho. | T68: Concordo | U68: No setor onde estou inserido eu vejo uma boa camaradagem dos mais antigos com os novatos, agora nós outros setores eu não posso opinar. | V68: Concordo | X68: Discordo | Y68: Acredito que o setor da manutenção seja o mais insatisfeito com a sua situação pois eles acreditam quem tem alguns direitos seus sendo negligenciado por parte da empresa. | Z68: Concordo | AB68: Concordo | AD68: Concordo | AE68: Para esse tipo de situação acontecer teria um bom motivo por exemplo a empresa está encerrado as operações ou por incompetência por parte dos colaboradores, agora tem um outro ponto também, a empresa vem sofrendo a bastante tempo com baixas e pedidos de demissão de pessoas que realmente fazem a diferença, acredito eu por não se sentir valorizado financeiramente daí quando aparece uma oportunidade de ganhar $$ melhor essa pessoas vão embora e isso é péssimo para empresa pois vai ter o custo da rescisão, o custo de tempo pra achar uma peça de reposição, vai gastar recursos para contratar uma nova pessoa e ainda corre o risco de não da certo, eu tenho notado desde quando eu cheguei que as pessoas não permanecem muito tempo por conta dessas questões que eu citei acima então e uma coisa a se pensar por parte da diretoria pq vcs tem um time bom, e ainda tem um agravante na imagem da empresa por estar sempre contratando as pessoas vêm isso e não querem fazer parte do ti.e por receio. | AF68: Concordo | AH68: Concordo Sempre | AI68: Muito claro essa informação. | AJ68: Concordo | AL68: Concordo Sempre | AM68: E uma pessoa muito engajada com as metas e melhorias para empresa. | AN68: Concordo | AP68: Concordo | AR68: Concordo | AT68: Concordo | AV68: Concordo | AX68: Concordo | AZ68: Concordo | BB68: Concordo | BD68: Concordo | BF68: Concordo | BH68: Concordo | BJ68: Concordo | BL68: Concordo | BN68: Concordo | BP68: Concordo | BR68: Concordo | BT68: Discordo | BU68: Eu nunca presenciei nada parecido. | BV68: Discordo | BW68: E muito relativo quando a pessoa tem intimidade com a outra sim ela se importa quando não tem intimidade na maioria das vezes as pessoas não se importam | BX68: Concordo | BZ68: Concordo | CB68: Discordo | CC68: No meu setor eu não vejo isso, nos demais eu não posso opinar. | CD68: Concordo Sempre | CE68: Eles são sempre bem acessíveis. | CF68: Concordo | CH68: Concordo | CJ68: Concordo | CK68: Acho que falta só mais um incentivo financeiro. | CL68: Concordo | CN68: Concordo | CO68: Todo lugar tem e algo que não dá pra se controlar, querendo ou não sempre chega uma gofoca ou outra. | CP68: Discordo | CQ68: Não vejo isso. | CR68: Concordo | CS68: Se ouver melhorias de salário e benefícios com toda certeza. | CT68: Concordo | CV68: Concordo | CX68: Assistência Médica, Assistência Odontológica, Auxílio Combustível, Multibenefícios Alimentação/ Refeição, Cesta Básica, Gympass (Convênio Academias), Day Off | CY68: Se tivesse um vale combustível seria muito bom pois quase rodos os funcionários tem transporte próprio, e se o plano de saúde é odontológico fosse 100% pago pela empresa seria um grande diferencial, a cesta básica seria muito bom ajudaria bastante, e o va/VR está excelente foi feita u.a melhoria para o flash e tem sido uma boa experiência pois aceita em todo lugar, antes era muito limitado a utilização, seria bacana se ouve-se um aumento no valor. | CZ68: Liderança, ambiente/cultura, paga os seus compromissos financeiros com os colaboradores em dias | DA68: Reestruturação e reformulação de cargos, salários e benefícios, estrutura física tem pouco espaço e alguns setores precisam de reforma, | DB68: Olhem com carinho para as sugestões dadas, pois um colaborador feliz produz e entrega mais.
A69: 45687.511 | B69: Discordo | C69: O barulho gerado pelos testes dos equipamentos, juntamente com a poeira e os resíduos de gasolina e óleo, prejudicam o desempenho de algumas atividades. | D69: Concordo | E69: Ótimo notebook e serviço de assistência sempre prestativo quando acionado. | F69: Concordo | G69: Acredito que, com os valores integrados à Nordeste, como o valor: Não há hierarquia para boas ideias, as pessoas são incentivadas a trazer melhorias visto que aplicadas na prática e testadas | H69: Concordo | I69: Os colaboradores não têm restrições quanto ao compartilhamento de conhecimento e, sempre que preciso de ajuda, recebo total atenção. | J69: Concordo | L69: Concordo | N69: Discordo | O69: Para alguns setores, como a manutenção, onde os mecânicos recebem pontos a cada melhoria realizada, seria interessante implementar algum tipo de bonificação ou premiação como forma de reconhecer e incentivar esses esforços extras. | P69: Concordo | R69: Concordo | S69: Tenho a capacidade de implementar melhorias e processos que não apenas beneficiam meu setor, mas também trazem resultados positivos para a Nordeste como um todo. | T69: Concordo Sempre | U69: Um omboarding sensacional | V69: Concordo | X69: Concordo | Z69: Concordo Sempre | AB69: Concordo | AD69: Concordo Sempre | AF69: Concordo | AH69: Concordo Sempre | AJ69: Concordo | AL69: Concordo Sempre | AN69: Concordo Sempre | AP69: Concordo Sempre | AR69: Concordo Sempre | AT69: Concordo | AV69: Concordo | AX69: Concordo Sempre | AZ69: Concordo Sempre | BB69: Concordo Sempre | BD69: Concordo Sempre | BF69: Concordo | BH69: Concordo | BJ69: Concordo | BL69: Concordo Sempre | BN69: Concordo | BP69: Concordo | BR69: Concordo Sempre | BT69: Discordo Sempre | BV69: Concordo | BX69: Concordo | BZ69: Discordo | CB69: Discordo | CD69: Concordo Sempre | CF69: Concordo Sempre | CH69: Concordo Sempre | CJ69: Concordo | CL69: Discordo | CM69: Ambiente físico poderia ser melhor, visto que no PCM ficamos ao lado do setor da manutenção e ruidos, poeira e resíduos de gasolina e oleo podem nos afetar. | CN69: Discordo | CP69: Concordo | CQ69: Competitividade para crescimento profissional, buscando melhorar. | CR69: Concordo | CS69: Quero me desenvolver como profissional e pessoa na Nordeste, aqui minhas ideias de melhorias são ouvidas, colocadas em prática e aplicadas para melhorar o dia a dia no trabalho e também | CT69: Concordo | CV69: Concordo | CX69: Assistência Médica, Auxílio Combustível, Multibenefícios Alimentação/ Refeição, Gympass (Convênio Academias), Day Off | CZ69: Cultura organizacional de crescimento muito importante e traz um nível de competitividade diferente para o mercado. Os valores intrínsecos que estão estampados nas camisas sempre como o dia a dia funciona. A possibilidade de crescimentos horizontal. | DA69: Infraestrutura de alguns setores. Padronização de processos. Plano de carreira e desenvolvimento mais claro. | DB69: .
A70: 45687.521 | B70: Concordo | D70: Concordo | E70: Só vejo problema com as pilhas, acabam muito rápido. | F70: Concordo | H70: Concordo Sempre | J70: Concordo | L70: Concordo | N70: Discordo | O70: Percebo que esse reconhecimento acontece, mas não é aplicado a todas as áreas. Creio que isso parta mais da gestão das áreas, está presente e dizer obrigado não significam reconhecimento. | P70: Discordo Sempre | Q70: Existem muitas empresas com esse segmento, e em sua maioria a base é sempre maior, o fator que agrega e faz o funcionário permanecer na Nordeste é o ambiente e necessidade. | R70: Concordo | S70: Tem sim, mas é pelo fator de crescimento e aprendizado. | T70: Concordo Sempre | V70: Concordo | W70: Algumas pessoas sim. | X70: Discordo | Y70: Não posso opinar sobre a vontade dos outros, mas não vejo isso em ninguém. | Z70: Concordo | AB70: Concordo | AD70: Concordo Sempre | AF70: Discordo Sempre | AG70: Não vejo isso, ainda mais que muitas trabalham fora do expediente normal para poder cumprir as demandas, por isso não tem como ter esse equilíbrio. | AH70: Concordo Sempre | AJ70: Concordo Sempre | AL70: Concordo Sempre | AN70: Concordo Sempre | AP70: Concordo Sempre | AR70: Concordo Sempre | AT70: Concordo Sempre | AV70: Concordo | AW70: As vezes sim, mas sempre tem erros que não podem ser pensados dessa maneira. | AX70: Concordo | AY70: A maioria das vezes, acha um ponto que precisa melhorar, ou seja crítica mais que elogio. | AZ70: Concordo Sempre | BB70: Concordo Sempre | BD70: Concordo | BF70: Concordo | BH70: Concordo Sempre | BJ70: Concordo | BK70: As vezes passa inúmeras demandas e quer todas ao mesmo tempo. | BL70: Concordo Sempre | BN70: Concordo | BO70: Algumas vezes entra um pouco em contradição. | BP70: Concordo Sempre | BR70: Concordo Sempre | BT70: Discordo Sempre | BV70: Concordo | BX70: Concordo | BZ70: Discordo Sempre | CA70: Após a mudança de gestão alguns setores foram penalizado. A maioria ainda continua tendo suas comemorações como comercial e o financeiro é um dos penalizado e sem explicação, até porque não tem nada que justifique. | CB70: Concordo Sempre | CC70: Em todos os ambientes existem isso. | CD70: Concordo | CF70: Concordo | CH70: Concordo | CJ70: Discordo | CK70: Esperava isso quando entrei, mas não vejo essa valorização. | CL70: Concordo | CN70: Concordo Sempre | CP70: Discordo | CR70: Concordo | CS70: A empresa tem tudo para crescer, então por hora, pretendo ficar. | CT70: Concordo | CV70: Concordo | CX70: Assistência Médica, Multibenefícios Alimentação/ Refeição, Auxílio Educação, Gympass (Convênio Academias), Day Off | CY70: A questão médica é excelente, mas os valores são elevados. | CZ70: Ambiente, pessoa, horário. | DA70: 1 - Remuneração (até porque alguns setores ganharam o retroativo e os outros não. 2 - Melhorar os valores do plano de saúde. 3 - Voltar as comemorações de metas. | DB70: Os dias do carnaval serem pagos em um sábado, e não ficar de maneira fracionada.
A71: 45687.535 | B71: Concordo | C71: Precisa ter mais segurança, onde estamos todos correndo risco de ser assaltados dentro da empresa, pois qualquer pessoa atualmente pode entrar, e fazer o que bem entender, não temos recepção ou até mais um porteiro "segurança". Acredito que deve pensar mais sobre a segurança interna dos colaboradores e adotar medidas que controle essas entradas de pessoas não identificadas, como ambulantes, vendedores, que entram e não tem ninguém para impedir isso. | D71: Concordo | E71: Precisa melhorar o ambiente, ergonomia principalmente, cadeiras e altura de trabalho dos notebooks. Ambiente muito exposto a ruído e poeiras. | F71: Concordo | H71: Concordo | J71: Concordo | L71: Concordo | N71: Concordo | P71: Discordo | Q71: Salário abaixo em relação ao mercado | R71: Concordo | T71: Concordo | V71: Concordo | X71: Concordo | Z71: Concordo | AB71: Concordo | AD71: Concordo | AF71: Concordo | AH71: Concordo | AJ71: Concordo | AL71: Concordo | AN71: Concordo | AP71: Concordo | AR71: Concordo | AT71: Concordo | AV71: Concordo | AX71: Concordo | AZ71: Concordo | BB71: Concordo | BD71: Concordo | BF71: Concordo | BH71: Concordo | BJ71: Concordo | BL71: Concordo | BN71: Concordo | BP71: Concordo | BR71: Concordo | BT71: Discordo | BU71: Nunca aconteceu isso | BV71: Concordo | BX71: Concordo | BZ71: Concordo | CB71: Discordo | CC71: Isso não acontece | CD71: Concordo | CF71: Concordo | CH71: Concordo | CJ71: Concordo | CL71: Concordo | CN71: Concordo | CP71: Discordo | CQ71: Não existe | CR71: Concordo | CT71: Concordo | CV71: Concordo | CX71: Auxílio Combustível, Auxílio Educação, Seguro de Vida, Gympass (Convênio Academias), Day Off | CY71: Plano de saúde 100% para todos os colaboradores, independente de quem já tem esse direito adquirido anos atrás. | CZ71: Cultura, sua visão para o futuro e ambiente de trabalho agradável para trabalhar. | DA71: Infraestrutura, segurança e benefícios | DB71: Apenas melhorar a infraestrutura da empresa, segurança e apresentar mais benefícios aos colaboradores, isso vai fazer com que todos nós colaboradores se sente bem ao sair de casa e voltar pra casa, sabendo que o dia a dia do trabalho foi bom e que somos valorizados. E não se esquecer de que quem move a empresa, são as pessoas.
A72: 45687.536 | B72: Concordo | D72: Concordo | F72: Concordo | H72: Concordo | J72: Concordo | L72: Concordo | N72: Concordo | P72: Concordo | R72: Concordo | T72: Concordo | V72: Concordo | X72: Concordo | Z72: Concordo | AB72: Concordo | AD72: Concordo | AF72: Concordo | AH72: Concordo | AJ72: Concordo Sempre | AL72: Concordo Sempre | AN72: Concordo Sempre | AP72: Concordo | AR72: Concordo Sempre | AT72: Concordo Sempre | AV72: Concordo Sempre | AX72: Concordo Sempre | AZ72: Concordo Sempre | BB72: Concordo Sempre | BD72: Concordo Sempre | BF72: Concordo | BH72: Concordo Sempre | BJ72: Concordo Sempre | BL72: Concordo Sempre | BN72: Concordo Sempre | BP72: Concordo Sempre | BR72: Concordo Sempre | BT72: Discordo Sempre | BU72: Nunca tive essa experiência, vejo uma boa conduta. | BV72: Concordo | BX72: Concordo | BZ72: Concordo | CB72: Discordo | CC72: Nunca presenciei tal ação. | CD72: Concordo | CF72: Concordo | CH72: Concordo | CJ72: Concordo | CL72: Concordo | CN72: Discordo | CO72: Nao presenciei tal ação. | CP72: Discordo | CQ72: "Na grande maioria", só vejo pessoas dispostas a exercer sua função. | CR72: Concordo Sempre | CT72: Concordo | CV72: Concordo | CX72: Assistência Médica, Auxílio Combustível, Vale Alimentação, Auxílio Educação, Seguro de Vida | CZ72: Reconhecimento de que os colaboradores são a essência da empresa. Eventos, gincanas e datas comemorativas que existem para descontração do colaborador. Reconhecimento pelo bom trabalho. | DA72: Piso da área de oficina. Iluminação da área de oficina. Espaço para organização de máquinas, peças, e trabalho dos mecânicos | DB72: Nada mais a comentar.
A73: 45687.555 | B73: Concordo | D73: Concordo | F73: Discordo | H73: Discordo | I73: Mas não de todos | J73: Discordo | L73: Concordo | M73: Ajuda os diretores,a crece para gerar empregos | N73: Discordo | P73: Concordo | R73: Concordo | T73: Concordo | U73: Aqui as pessoas são bem acolhida | V73: Concordo | X73: Discordo | Z73: Concordo | AB73: Discordo | AD73: Discordo | AE73: Acredito que só ei, questão financeira. | AF73: Concordo | AG73: Sim,mas por os diretores e colegas,pq a supervisão deixa a desejar | AH73: Concordo | AJ73: Discordo | AK73: Pq eles vevi muito no mundinhi dles,e não procuram saber oque está sr passando por de traz de um funcionário | AL73: Discordo | AM73: Não,pq se ele demonstrasse interesse não tinha muito funcionário desmotivado,colocando culpa na empresa ou nos diretores,pq nem tudo os diretores sabe | AN73: Discordo | AO73: Não vejo maturidade pra ele ta nesse cargo que ele está alcupado,não tem ética no que ele escuta | AP73: Discordo | AR73: Concordo | AS73: Sim | AT73: Discordo | AV73: Discordo | AX73: Concordo | AY73: Não,as vezes escuta mas não atribuir | AZ73: Discordo | BB73: Discordo | BD73: Discordo | BF73: Concordo | BH73: Discordo | BJ73: Discordo | BL73: Discordo | BN73: Discordo | BP73: Concordo | BR73: Concordo | BT73: Discordo | BV73: Concordo | BW73: Nem todos,mas tem muitos que se coloca no lugar do outro | BX73: Concordo | BZ73: Discordo | CA73: Era pra tem comemoração de metas dos mecânicos | CB73: Concordo | CD73: Concordo Sempre | CE73: São umas pessoas que sabe escutar,mas tbem saber aconselha | CF73: Concordo Sempre | CG73: São chefe,mas tbem São amigos | CH73: Concordo Sempre | CJ73: Concordo | CL73: Concordo Sempre | CN73: Concordo Sempre | CP73: Concordo | CR73: Concordo Sempre | CS73: Qro crece e ajuda a empresa crece muito mas | CT73: Discordo | CV73: Concordo | CX73: Assistência Médica, Assistência Odontológica, Auxílio Combustível, Multibenefícios Alimentação/ Refeição, Auxílio Educação, Cesta Básica, Seguro de Vida, Gympass (Convênio Academias), Day Off | CY73: Que assistência médica seja 100 ajuda muito | CZ73: O horas | DA73: Sala de descanso climatizadas,e tbem o refeitório | DB73: Banheiros masculino precisa de reforma
A74: 45687.564 | B74: Concordo | D74: Concordo | F74: Concordo | H74: Concordo Sempre | J74: Concordo Sempre | L74: Concordo Sempre | N74: Concordo | P74: Discordo | Q74: Se a empresa tem em mente ser a locadora número 1 do nordeste ,no meu entendimento tem que ser exemplo de mercado em relação a salário,não se compara a outra | R74: Concordo | T74: Concordo Sempre | V74: Concordo Sempre | X74: Discordo | Z74: Concordo Sempre | AB74: Concordo | AD74: Concordo Sempre | AF74: Concordo | AH74: Discordo | AJ74: Concordo | AK74: Líder sim , supervisor não | AL74: Discordo | AM74: Líder sim , supervisor não | AN74: Concordo Sempre | AP74: Concordo Sempre | AR74: Concordo | AT74: Concordo Sempre | AV74: Discordo | AW74: Supervisor quer da exemplo,mais não que ser exemplo | AX74: Concordo Sempre | AZ74: Concordo | BB74: Concordo Sempre | BD74: Concordo | BF74: Discordo | BH74: Concordo | BJ74: Concordo | BL74: Concordo | BN74: Discordo | BP74: Concordo Sempre | BR74: Concordo | BT74: Concordo | BV74: Concordo Sempre | BX74: Concordo | BZ74: Discordo | CB74: Discordo | CD74: Concordo | CF74: Concordo | CH74: Concordo | CJ74: Concordo | CK74: Poderia valorizar mais ,não acho certo uma pessoa trabalhar,dar resultados acima da meia e receber o mesmo de outra pessoa da mesma função. | CL74: Concordo | CN74: Concordo | CP74: Concordo | CR74: Discordo | CS74: Dia de amanhã só pertence a Deus | CT74: Concordo | CV74: Concordo | CX74: Assistência Médica, Assistência Odontológica, Auxílio Combustível, Multibenefícios Alimentação/ Refeição, Cesta Básica | CZ74: Comprimento com folha de pagamento. Valorização de pessoas novos no mercado de trabalho . Momentos para descontrair | DA74: Tem mais benefícios Melhores acomodações Melhores condições de trabalho | DB74: Faltou falar diretamente do supervisor,só tinha lider , meio que deixou de lado a responsabilidade dele. Na aria de benefícios, seria um boa ,ter colocado só os que a empresa não oferece.
A75: 45687.568 | B75: Concordo | D75: Concordo | F75: Discordo | H75: Discordo | J75: Discordo | L75: Discordo | N75: Discordo | P75: Discordo | R75: Concordo | T75: Discordo Sempre | V75: Concordo | X75: Concordo Sempre | Z75: Concordo | AB75: Discordo | AD75: Concordo | AF75: Discordo | AH75: Concordo | AJ75: Discordo | AK75: É necessário ser mais claro | AL75: Concordo | AN75: Concordo | AP75: Concordo Sempre | AR75: Concordo Sempre | AT75: Discordo | AV75: Discordo | AX75: Concordo Sempre | AZ75: Discordo | BB75: Concordo | BD75: Concordo | BF75: Discordo | BH75: Discordo | BJ75: Concordo | BL75: Discordo | BN75: Concordo Sempre | BP75: Concordo Sempre | BR75: Concordo | BT75: Discordo | BV75: Discordo | BX75: Discordo | BZ75: Discordo | CB75: Concordo | CD75: Discordo | CF75: Concordo | CH75: Concordo Sempre | CJ75: Discordo | CL75: Concordo | CN75: Concordo | CP75: Concordo | CR75: Discordo | CT75: Discordo | CV75: Concordo | CX75: Auxílio Combustível, Cesta Básica, Day Off | CZ75: Dinâmica Em evolução sempre Confraterniza | DA75: Olhar com mais afeto para os funcionários Falar e cumprir Observar as pessoas que estão nos cargos de liderança. | DB75: ND
A76: 45687.582 | B76: Concordo Sempre | D76: Concordo Sempre | F76: Concordo Sempre | H76: Concordo Sempre | J76: Concordo Sempre | L76: Concordo Sempre | N76: Concordo Sempre | P76: Concordo | R76: Concordo Sempre | T76: Concordo Sempre | V76: Concordo Sempre | X76: Concordo | Z76: Concordo Sempre | AB76: Concordo | AD76: Concordo | AF76: Concordo | AH76: Concordo Sempre | AJ76: Concordo Sempre | AL76: Concordo Sempre | AN76: Concordo Sempre | AP76: Concordo Sempre | AR76: Concordo Sempre | AT76: Concordo Sempre | AV76: Concordo Sempre | AX76: Concordo Sempre | AZ76: Concordo Sempre | BB76: Concordo Sempre | BD76: Concordo Sempre | BF76: Discordo Sempre | BH76: Concordo Sempre | BJ76: Concordo Sempre | BL76: Concordo Sempre | BN76: Concordo Sempre | BP76: Concordo Sempre | BR76: Concordo Sempre | BT76: Discordo Sempre | BV76: Concordo Sempre | BX76: Concordo Sempre | BZ76: Concordo Sempre | CB76: Discordo | CD76: Concordo Sempre | CF76: Concordo Sempre | CH76: Concordo Sempre | CJ76: Concordo Sempre | CL76: Concordo Sempre | CN76: Discordo Sempre | CP76: Discordo | CR76: Concordo Sempre | CT76: Concordo Sempre | CV76: Concordo Sempre | CX76: Auxílio Combustível, Auxílio Educação, Cesta Básica, Seguro de Vida, Empréstimo Consignado | CZ76: Ótimos donos, bons líderes e colaboradores | DA76: Na minha opinião tá tudo em ordem | DB76: A empresa é ótima pra se trabalhar..
A77: 45687.59 | B77: Concordo | D77: Concordo | F77: Concordo | H77: Concordo | J77: Concordo | K77: Eu concordo que a empresa disponibiliza oportunidade de crescimento é da desafios que incentivam o desenvolvimento pessoal, no entanto gostaria que a empresa disponibiliza alguns cursos ou treinamento, para podemos aprimorar algumas habilidades como liderança. | L77: Concordo | N77: Concordo | P77: Discordo | Q77: Por mais que a empresa seja maravilhosa, dando oportunidade para desenvolvimento dando espaço para crescer o a remuneração ainda está abaixo do mercado. | R77: Concordo | S77: Gosto muito do que faço na Nordeste. | T77: Concordo | V77: Concordo | X77: Concordo | Y77: Não consigo opinar de forma correta, pois não estou ciente dos pensamentos dos demais, mas por mim, sim, tenho bastante vontade de vir ao trabalho. | Z77: Concordo | AB77: Concordo | AD77: Discordo | AF77: Concordo | AH77: Concordo | AJ77: Concordo | AL77: Concordo | AN77: Concordo | AP77: Concordo | AR77: Concordo | AT77: Concordo | AU77: Essa pergunta é muito abrange, não há um definição sólida, necessidade como pessoa? Como líder ou com foco em metas? | AV77: Concordo | AX77: Concordo | AZ77: Concordo | BB77: Concordo | BD77: Concordo | BF77: Concordo | BH77: Concordo | BJ77: Concordo | BL77: Concordo | BN77: Concordo | BP77: Concordo | BR77: Concordo | BT77: Discordo | BV77: Concordo | BX77: Concordo | BZ77: Discordo | CA77: Só participei de um evento assim. | CB77: Discordo | CD77: Concordo | CF77: Concordo | CG77: Creio que sim, nunca percebi nada que me levasse ao contrário. | CH77: Concordo | CJ77: Concordo | CL77: Concordo | CM77: Habitante da empresa é maravilhoso. | CN77: Concordo Sempre | CO77: Sempre ha fofocas. | CP77: Discordo | CR77: Concordo | CT77: Concordo | CV77: Concordo | CX77: Assistência Médica, Assistência Odontológica, Auxílio Combustível, Gympass (Convênio Academias), Seria ótimo se a empresa ajudasse os funcionários com um financiamento, como carteira de motorista. | CZ77: Ambiente, fácil comunicação e da oportunidade para crescer. | DA77: Salário, disponibiliza um auxílio combustível e aumentar a área de descanso e colocar um ar-condicionado. | DB77: .
A78: 45687.593 | B78: Concordo | D78: Concordo Sempre | F78: Discordo | G78: A maioria das pessoas sim, outras fazem algumas atividades, mas o “além” nem sempre! | H78: Concordo | J78: Concordo Sempre | L78: Concordo Sempre | N78: Concordo Sempre | P78: Concordo | R78: Concordo Sempre | T78: Concordo | V78: Concordo | X78: Concordo | Z78: Concordo | AB78: Concordo | AD78: Concordo | AF78: Concordo | AH78: Concordo | AJ78: Concordo | AL78: Concordo Sempre | AN78: Concordo Sempre | AP78: Concordo Sempre | AR78: Concordo Sempre | AT78: Concordo Sempre | AV78: Concordo Sempre | AX78: Concordo Sempre | AZ78: Concordo Sempre | BB78: Concordo Sempre | BD78: Concordo Sempre | BF78: Concordo Sempre | BH78: Concordo Sempre | BJ78: Concordo Sempre | BL78: Concordo Sempre | BN78: Concordo Sempre | BP78: Concordo Sempre | BR78: Concordo Sempre | BT78: Discordo Sempre | BU78: Nunca vi, pelo contrário vejo uma postura muito bacana da nossa liderança! | BV78: Concordo | BX78: Concordo | BZ78: Concordo Sempre | CB78: Concordo | CC78: Acredito que sempre tem, mas vejo a empresa se empenhando em quem de fato se esforça! | CD78: Concordo Sempre | CF78: Concordo Sempre | CG78: Demais! São muito acessíveis, coisas que em outras empresas é algo muito distante! | CH78: Concordo Sempre | CJ78: Concordo Sempre | CL78: Concordo Sempre | CN78: Concordo Sempre | CP78: Concordo | CQ78: Comigo nunca aconteceu, mas já presenciei com alguns colegas! | CR78: Concordo Sempre | CS78: Com certeza! | CT78: Concordo | CV78: Concordo Sempre | CX78: Assistência Médica, Assistência Odontológica, Auxílio Combustível, Vale Refeição, Enxoval Maternidade, Gympass (Convênio Academias) | CZ78: Nos divertimos enquanto trabalhamos haha, vale alimentação, oportunidade de crescimento | DA78: Plano de saúde (com mais desconto), sala de descanso, vale combustível | DB78: Finalizando, vejo a Nordeste como uma empresa excelente para se trabalhar! E os demais pontos foram citados acima!
A79: 45687.607 | B79: Concordo Sempre | C79: Em todas as empresas eu passei aqui pode se dizer que o ambiente é bem agradável, pessoal tudo se ajuda, tira dúvidas e é tão bom que as vezes nem pensamos em faltar o trabalho pois o ambiente é agradável. | D79: Concordo Sempre | E79: . | F79: Concordo Sempre | G79: . | H79: Concordo Sempre | I79: . | J79: Concordo Sempre | K79: .. | L79: Concordo Sempre | M79: .. | N79: Concordo | O79: . | P79: Discordo | Q79: Salário não é tão ruim mas também não é bom, pelo o esforço que eu faço pra deixar tudo perfeito para que não venha problema tanto pra mim, pra empresa e pro cliente onde é por ele que a empresa consegue pagar nossos salários! Tento deixar o máximo possível fazer aquilo funcionar por muito mais tempo, ter zelo pelo o patrimônios da empresa, então eu gostaria de ganhar um pouco mais. | R79: Concordo Sempre | S79: Eu amo que eu faço, por isso me dar mais vontade trabalhar aqui. | T79: Concordo Sempre | U79: Vejo que quando eu cheguei aqui fui bem recebido e tratado assim que vejo os outros funcionários novos chegarem. | V79: Concordo Sempre | W79: Tenho algumas pessoas que não levo como colegas de trabalho mas sim, comos amigos que posso contar sempre! | X79: Concordo Sempre | Y79: Por mim eu tenho vontade de trabalhar, me espelho em algumas pessoas, quero construir uma carreira aqui. | Z79: Concordo Sempre | AA79: . | AB79: Discordo | AC79: Até agora só vim um canal que mostra pra gente dar nossos sugestões. | AD79: Concordo | AE79: Penso isso sempre, mas pode até alguns motivos como troca de gestão ou diminuição de custos. | AF79: Concordo Sempre | AG79: . | AH79: Concordo | AI79: . | AJ79: Discordo | AK79: Sinto ele muito ausente, mal participando nas reuniões conosco. | AL79: Concordo | AM79: . | AN79: Concordo | AO79: . | AP79: Discordo | AR79: Discordo | AS79: Raramente falo com ele. | AT79: Concordo | AU79: .. | AV79: Concordo | AW79: .. | AX79: Concordo | AY79: . | AZ79: Discordo | BA79: . | BB79: Discordo | BC79: . | BD79: Concordo | BE79: . | BF79: Discordo | BG79: . | BH79: Discordo | BI79: Vejo algumas pessoas ser tratadas bem diferente que as outras | BJ79: Concordo | BK79: . | BL79: Concordo | BM79: . | BN79: Concordo | BO79: . | BP79: Concordo | BQ79: Acho bom feedback, assim mostra como precisamos melhorar como profissional e pessoal. | BR79: Concordo | BS79: . | BT79: Discordo Sempre | BU79: . | BV79: Discordo | BW79: Acho que algumas pessoas se importam mais com elas . | BX79: Concordo Sempre | BY79: . | BZ79: Discordo | CA79: Pelo menos no meu setor não comemorarmos metas batidas. | CB79: Discordo Sempre | CC79: . | CD79: Concordo | CE79: . | CF79: Concordo Sempre | CG79: . | CH79: Concordo Sempre | CI79: . | CJ79: Concordo | CK79: .. | CL79: Concordo Sempre | CM79: . | CN79: Discordo Sempre | CO79: Até agora nunca vi isso e espero nunca ver. | CP79: Discordo Sempre | CQ79: . | CR79: Concordo Sempre | CS79: Gostaria crescer profissionalmente aqui. | CT79: Concordo | CU79: . | CV79: Concordo Sempre | CW79: . | CX79: Assistência Médica, Assistência Odontológica, Auxílio Combustível, Multibenefícios Alimentação/ Refeição, Empréstimo Consignado | CY79: Gostaria muito que a empresa adotasse vale combustível, onde poderia calcular a passagem do ônibus e colocar no vale combustível, vejo muito funcionário vindo com veículos próprio e a pessoa poderia escolher se quer vale combustível ou transporte. | CZ79: Ambiente e pessoas | DA79: Espaço | DB79: ..
